{
  "id": "./docs/en/autoFill.md",
  "content": "---\ncreatedAt: 2025-03-13\nupdatedAt: 2025-09-20\ntitle: Auto Fill\ndescription: Learn how to use auto fill functionality in Intlayer to automatically populate content based on predefined patterns. Follow this documentation to implement auto fill features efficiently in your project.\nkeywords:\n  - Auto Fill\n  - Content Automation\n  - Dynamic Content\n  - Intlayer\n  - Next.js\n  - JavaScript\n  - React\nslugs:\n  - doc\n  - concept\n  - auto-fill\nhistory:\n  - version: 7.0.0\n    date: 2025-10-23\n    changes: Rename `autoFill` to `fill` and update behavior\n  - version: 6.0.0\n    date: 2025-09-20\n    changes: Add global configuration\n  - version: 6.0.0\n    date: 2025-09-17\n    changes: Add `{{fileName}}` variable\n  - version: 5.5.10\n    date: 2025-06-29\n    changes: Init history\n---\n\n# Fill Content Declaration File Translations\n\n**Autofill content declaration files** in your CI are a way to speed up your development workflow.\n\n## Understanding the behavior\n\nThe `fill` command includes two modes:\n\n- **Complete**: Automatically fill all missing content for each locale and edit the current file, or another file if specified. That say, complete mode will skip the translation of existing content, if already translated.\n- **Review**: Automatically fill **all** content for each locale and generate for a specific file, or another file if specified.\n\nThe will command will process all your locale content declaration files. That say, it will not process your remote content from the CMS. The CMS includes its own translations management.\nIf you use plugins as `@intlayer/sync-json-plugin`, Intlayer will transform the JSON files into a locale content declaration files. That say, they will be processed by the `fill` command.\n\nThe new generated files include a `filled` instruction as dictionary metadata. This instruction will be used by Intlayer to know if the file has been autofilled or not, and skip this file from being translated again if present.\n\nIntlayer will also consider the following instruction for autofill:\n\n- From your `.content.{ts|js|json}` → `fill` instruction\n- From your configuration file `.intlayer.config.ts` → `dictionary.fill` instruction\n- Will be set to `true` by default otherwise\n\nFor per-locale content declaration files, the `true` instruction will be replaced by `./{{fileName}}.fill.content.json`. This is because the a per-locale content declaration file cannot receive additional localized content. So it will generate a new file to do not overwrite the existing file.\n\n## Default Behavior\n\nBy default, `fill` is set to `true` globally, which means Intlayer will automatically fill all content files and edit the file itself. This behavior can be customized in several ways:\n\n### Global Configuration Options\n\n1. **`fill: true` (default)** - Automatically fill all locales and edit the current file\n2. **`fill: false`** - Disable auto-fill for this content file\n3. **`fill: \"./relative/path/to/file\"`** - Create/update the specified file without editing the current one by pointing to a relative path resolved based on the location of the current file\n4. **`fill: \"/absolute/path/to/file\"`** - Create/update the specified file without editing the current one by pointing to an relative path resolved based on the location of base directory (field `baseDir` in the configuration file `.intlayer.config.ts`)\n5. **`fill: \"C:\\\\absolute\\path\\to\\file\"`** - Create/update the specified file without editing the current one by pointing to an absolute path resolved based on your operating system\n6. **`fill: { [key in Locales]?: string }`** - Create/update the specified file for each locale\n\n### v7 Behavior Changes\n\nIn v7, the `fill` command behavior has been updated:\n\n- **`fill: true`** - Rewrites the current file with filled content for all locales\n- **`fill: \"path/to/file\"`** - Fills the specified file without modifying the current file\n- **`fill: false`** - Disables auto-fill completely\n\nWhen using a path option to write to another file, the fill mechanism works through a _master-slave_ relationship between content declaration files. The main (master) file serves as the source of truth, and when it's updated, Intlayer will automatically apply those changes to the derived (filled) declaration files specified by the path.\n\n### Per-Locale Customization\n\nYou can also customize the behavior for each locale by using an object:\n\n```ts fileName=\"intlayer.config.ts\"\nconst config: IntlayerConfig = {\n  content: {\n    internationalization: {\n      locales: [Locales.ENGLISH, Locales.FRENCH, Locales.POLISH],\n      defaultLocale: Locales.ENGLISH,\n      requiredLocales: [Locales.ENGLISH], // Recommended to avoid Property 'pl' is missing in type '{ en: string; xxx } on your t function if\n    },\n  },\n  dictionary: {\n    fill: {\n      en: true, // Fill and edit the current file for English\n      fr: \"./translations/fr.json\", // Create separate file for French\n      es: false, // Disable fill for Spanish\n    },\n  },\n};\n```\n\nThis allows you to have different fill behaviors for different locales within the same project.\n\n```ts fileName=\"src/components/example/example.content.ts\"\nimport { Locales, type Dictionary } from \"intlayer\";\n\nconst exampleContent = {\n  key: \"example\",\n  locale: Locales.ENGLISH,\n  fill: \"./example.content.json\",\n  content: {\n    contentExample: \"This is an example of content\",\n  },\n} satisfies Dictionary;\n\nexport default exampleContent;\n```\n\nHere is a [per-locale content declaration file](https://github.com/aymericzip/intlayer/blob/main/docs/docs/en/per_locale_file.md) using the `fill` instruction.\n\nThen, when you run the following command:\n\n```bash\nnpx intlayer fill --file 'src/components/example/example.content.ts'\n```\n\nIntlayer will automatically generate the derived declaration file at `src/components/example/example.content.json`, filling in all locales not already declared in the main file.\n\n```json5 fileName=\"src/components/example/example.content.json\"\n{\n  \"key\": \"example\",\n  \"content\": {\n    \"contentExample\": {\n      \"nodeType\": \"translation\",\n      \"translation\": {\n        \"fr\": \"Ceci est un exemple de contenu\",\n        \"es\": \"Este es un ejemplo de contenido\",\n      },\n    },\n  },\n}\n```\n\nAfterward, both declaration files will be merged into a single dictionary, accessible using the standard `useIntlayer(\"example\")` hook (react) / composable (vue).\n\n## Global Configuration\n\nYou can configure the global auto fill configuration in the `intlayer.config.ts` file.\n\n```ts fileName=\"intlayer.config.ts\"\nimport { type IntlayerConfig, Locales } from \"intlayer\";\n\nconst config: IntlayerConfig = {\n  internationalization: {\n    locales: [Locales.ENGLISH, Locales.FRENCH, Locales.SPANISH],\n    defaultLocale: Locales.ENGLISH,\n    requiredLocales: [Locales.ENGLISH, Locales.FRENCH],\n  },\n  dictionary: {\n    // Auto-generate missing translations for all dictionaries\n    fill: \"./{{fileName}}Filled.content.ts\",\n    //\n    // fill: \"/messages/{{locale}}/{{key}}/{{fileName}}.content.json\",\n    //\n    // fill: true, // auto-generate missing translations for all dictionaries like using \"./{{fileName}}.content.json\"\n    //\n    // fill: {\n    //   en: \"./{{fileName}}.en.content.json\",\n    //   fr: \"./{{fileName}}.fr.content.json\",\n    //   es: \"./{{fileName}}.es.content.json\",\n    // },\n  },\n};\n\nexport default config;\n```\n\nYou can still fine‑tune per dictionary using the `fill` field in content files. Intlayer will first consider the per dictionary configuration and then fallback to the global configuration.\n\n## Autofilled File Format\n\nThe recommended format for autofilled declaration files is **JSON**, which helps avoid formatting constraints. However, Intlayer also supports `.ts`, `.js`, `.mjs`, `.cjs`, and other formats.\n\n```ts fileName=\"src/components/example/example.content.ts\"\nconst exampleContent = {\n  key: \"example\",\n  fill: \"./example.filled.content.ts\",\n  content: {\n    // Your content\n  },\n};\n```\n\nThis will generate the file at:\n\n```\nsrc/components/example/example.filled.content.ts\n```\n\n> The generation of `.js`, `.ts`, and similar files works as follows:\n>\n> - If the file already exists, Intlayer will parse it using the AST (Abstract Syntax Tree) to locate each field and insert any missing translations.\n> - If the file does not exist, Intlayer will generate it using the default content declaration file template.\n\n## Absolute Paths\n\nThe `fill` field also supports absolute paths.\n\n```ts fileName=\"src/components/example/example.content.ts\"\nconst exampleContent = {\n  key: \"example\",\n  fill: \"/messages/example.content.json\",\n  content: {\n    // Your content\n  },\n};\n```\n\nThis will generate the file at:\n\n```\n/messages/example.content.json\n```\n\n## Autogenerate Per-Locale Content Declaration Files\n\nThe `fill` field also supports generation of **per-locale** content declaration files.\n\n```ts fileName=\"src/components/example/example.content.ts\"\nconst exampleContent = {\n  key: \"example\",\n  fill: {\n    fr: \"./example.fr.content.json\",\n    es: \"./example.es.content.json\",\n  },\n  content: {\n    // Your content\n  },\n};\n```\n\nThis will generate two separate files:\n\n- `src/components/example/example.fr.content.json`\n- `src/components/example/example.es.content.json`\n\n> In this case, if the object does not contain all locales, Intlayer skip the generation of the remaining locales.\n\n## Filter Specific Locale Autofill\n\nUsing an object for the `fill` field allows you to apply filters and generate only specific locale files.\n\n```ts fileName=\"src/components/example/example.content.ts\"\nconst exampleContent = {\n  key: \"example\",\n  fill: {\n    fr: \"./example.fr.content.json\",\n  },\n  content: {\n    // Your content\n  },\n};\n```\n\nThis will only generate the French translation file.\n\n## Path Variables\n\nYou can use variables inside the `fill` path to dynamically resolve the target paths for the generated files.\n\n**Available variables:**\n\n- `{{locale}}` – Locale code (e.g. `fr`, `es`)\n- `{{fileName}}` – File name (e.g. `index`)\n- `{{key}}` – Dictionary key (e.g. `example`)\n\n```ts fileName=\"src/components/example/index.content.ts\"\nconst exampleContent = {\n  key: \"example\",\n  fill: \"/messages/{{locale}}/{{key}}.content.json\",\n  content: {\n    // Your content\n  },\n};\n```\n\nThis will generate:\n\n- `/messages/fr/example.content.json`\n- `/messages/es/example.content.json`\n\n```ts fileName=\"src/components/example/index.content.ts\"\nconst exampleContent = {\n  key: \"example\",\n  fill: \"./{{fileName}}.content.json\",\n  content: {\n    // Your content\n  },\n};\n```\n\nThis will generate:\n\n- `./index.content.json`\n- `./index.content.json`\n",
  "createdAt": "2025-03-13",
  "updatedAt": "2025-09-20",
  "title": "Auto Fill",
  "description": "Learn how to use auto fill functionality in Intlayer to automatically populate content based on predefined patterns. Follow this documentation to implement auto fill features efficiently in your project.",
  "keywords": [
    "Auto Fill",
    "Content Automation",
    "Dynamic Content",
    "Intlayer",
    "Next.js",
    "JavaScript",
    "React"
  ],
  "slugs": [
    "doc",
    "concept",
    "auto-fill"
  ],
  "history": [
    {
      "version": "7.0.0",
      "date": "2025-10-23",
      "changes": "Rename `autoFill` to `fill` and update behavior"
    },
    {
      "version": "6.0.0",
      "date": "2025-09-20",
      "changes": "Add global configuration"
    },
    {
      "version": "6.0.0",
      "date": "2025-09-17",
      "changes": "Add `{{fileName}}` variable"
    },
    {
      "version": "5.5.10",
      "date": "2025-06-29",
      "changes": "Init history"
    }
  ],
  "docKey": "./docs/en/autoFill.md",
  "githubUrl": "https://github.com/aymericzip/intlayer/blob/main/docs/docs/en/autoFill.md",
  "relativeUrl": "/doc/concept/auto-fill",
  "url": "https://intlayer.org/doc/concept/auto-fill"
}