{
  "id": "./docs/en/cli/build.md",
  "content": "---\ncreatedAt: 2024-08-11\nupdatedAt: 2025-11-22\ntitle: Build Dictionaries\ndescription: Learn how to build your Intlayer dictionaries from content declaration files.\nkeywords:\n  - Build\n  - Dictionaries\n  - CLI\n  - Intlayer\nslugs:\n  - doc\n  - concept\n  - cli\n  - build\n---\n\n# Build Dictionaries\n\nTo build your dictionaries, you can run the commands:\n\n```bash\nnpx intlayer build\n```\n\nor in watch mode\n\n```bash\nnpx intlayer build --watch\n```\n\nThis command will find your declaration content files as default as `./src/**/*.content.{ts|js|mjs|cjs|json|tsx|jsx}`. And build the dictionaries in the `.intlayer` directory.\n\n## Aliases:\n\n- `npx intlayer dictionaries build`\n- `npx intlayer dictionary build`\n- `npx intlayer dic build`\n\n## Arguments:\n\n- **`--base-dir`**: Specify the base directory for the project. To retrieve the intlayer configuration, the command will look for the `intlayer.config.{ts,js,json,cjs,mjs}` file in the base directory.\n\n  > Example: `npx intlayer build --base-dir ./src`\n\n- **`--env`**: Specify the environment (e.g., `development`, `production`). Useful in the case you use environment variables in your intlayer configuration file.\n\n  > Example: `npx intlayer build --env production`\n\n- **`--env-file`**: Provide a custom environment file to load variables from. Useful in the case you use environment variables in your intlayer configuration file.\n\n  > Example: `npx intlayer build --env-file .env.production.local`\n\n- **`--with`**: Start command in parallel with the build.\n\n  > Example: `npx intlayer build --with \"next dev --turbopack\"`\n\n- **`--skip-prepare`**: Skip the prepare step.\n\n  > Example: `npx intlayer build --skip-prepare`\n\n- **`--no-cache`**: Disable the cache.\n\n  > Example: `npx intlayer build --no-cache`\n",
  "createdAt": "2024-08-11",
  "updatedAt": "2025-11-22",
  "title": "Build Dictionaries",
  "description": "Learn how to build your Intlayer dictionaries from content declaration files.",
  "keywords": [
    "Build",
    "Dictionaries",
    "CLI",
    "Intlayer"
  ],
  "slugs": [
    "doc",
    "concept",
    "cli",
    "build"
  ],
  "docKey": "./docs/en/cli/build.md",
  "githubUrl": "https://github.com/aymericzip/intlayer/blob/main/docs/docs/en/cli/build.md",
  "relativeUrl": "/doc/concept/cli/build",
  "url": "https://intlayer.org/doc/concept/cli/build"
}