{
  "id": "./docs/en/cli/init.md",
  "content": "---\ncreatedAt: 2025-12-30\nupdatedAt: 2025-12-30\ntitle: Initialize Intlayer\ndescription: Learn how to initialize Intlayer in your project.\nkeywords:\n  - Initialize\n  - CLI\n  - Intlayer\n  - AI\nslugs:\n  - doc\n  - concept\n  - cli\n  - init\nhistory:\n  - version: 7.5.9\n    date: 2025-12-30\n    changes: Add init command\n---\n\n# Initialize Intlayer\n\n```bash\nnpx intlayer init\n```\n\nThe `init` command automatically sets up Intlayer in your project by configuring necessary files and settings. It's the recommended way to get started with Intlayer.\n\n## Aliases:\n\n- `npx intlayer init`\n\n## Arguments:\n\n- `--project-root [projectRoot]` - Optional. Specify the project root directory. If not provided, the command will search for the project root starting from the current working directory.\n\n## What it does:\n\nThe `init` command performs the following setup tasks:\n\n1. **Validates project structure** - Ensures you're in a valid project directory with a `package.json` file\n2. **Updates `.gitignore`** - Adds `.intlayer` to your `.gitignore` file to exclude generated files from version control\n3. **Configures TypeScript** - Updates all `tsconfig.json` files to include Intlayer type definitions (`.intlayer/**/*.ts`)\n4. **Creates configuration file** - Generates an `intlayer.config.ts` (for TypeScript projects) or `intlayer.config.mjs` (for JavaScript projects) with default settings\n5. **Updates Vite config** - If a Vite configuration file is detected, adds the `vite-intlayer` plugin import\n6. **Updates Next.js config** - If a Next.js configuration file is detected, adds the `next-intlayer` plugin import\n\n## Examples:\n\n### Basic initialization:\n\n```bash\nnpx intlayer init\n```\n\nThis will initialize Intlayer in the current directory, automatically detecting the project root.\n\n### Initialize with custom project root:\n\n```bash\nnpx intlayer init --project-root ./my-project\n```\n\nThis will initialize Intlayer in the specified directory.\n\n## Example output:\n\n```bash\nnpx intlayer init\nChecking Intlayer configuration...\n✓ Added .intlayer to .gitignore\n✓ Updated tsconfig.json to include intlayer types\nCreated intlayer.config.ts\n✓ Injected import into vite.config.ts\n✓ Intlayer init setup complete.\n```\n\n## Notes:\n\n- The command is idempotent - you can run it multiple times safely. It will skip steps that are already configured.\n- If a configuration file already exists, it won't be overwritten.\n- TypeScript config files without an `include` array (e.g., solution-style configs with references) are skipped.\n- The command will exit with an error if no `package.json` is found in the project root.\n",
  "createdAt": "2025-12-30",
  "updatedAt": "2025-12-30",
  "title": "Initialize Intlayer",
  "description": "Learn how to initialize Intlayer in your project.",
  "keywords": [
    "Initialize",
    "CLI",
    "Intlayer",
    "AI"
  ],
  "slugs": [
    "doc",
    "concept",
    "cli",
    "init"
  ],
  "history": [
    {
      "version": "7.5.9",
      "date": "2025-12-30",
      "changes": "Add init command"
    }
  ],
  "docKey": "./docs/en/cli/init.md",
  "githubUrl": "https://github.com/aymericzip/intlayer/blob/main/docs/docs/en/cli/init.md",
  "relativeUrl": "/doc/concept/cli/init",
  "url": "https://intlayer.org/doc/concept/cli/init"
}