{
  "id": "./docs/en/cli/fill.md",
  "content": "---\ncreatedAt: 2024-08-11\nupdatedAt: 2025-11-22\ntitle: Fill Dictionaries\ndescription: Learn how to fill, audit, and translate your dictionaries using AI.\nkeywords:\n  - Fill\n  - Audit\n  - Translate\n  - Dictionaries\n  - CLI\n  - Intlayer\n  - AI\nslugs:\n  - doc\n  - concept\n  - cli\n  - fill\n---\n\n# Fill / audit / translate dictionaries\n\n```bash\nnpx intlayer fill\n```\n\nThis command analyzes your content declaration files for potential issues such as missing translations, structural inconsistencies, or type mismatches. If it finds any problems, **intlayer fill** will propose or apply updates to keep your dictionaries consistent and complete.\n\n## Key Points:\n\n- Splits large JSON files into chunks to stay within the AI model's context window limits.\n- Retries translation if the output format is incorrect.\n- Incorporates application and file-specific context for improved translation accuracy.\n- Preserves existing translations by not overwriting them.\n- Processes files, chunks, and locales in parallel using a queue system to increase speed.\n\n## Aliases:\n\n- `npx intlayer dictionaries fill`\n- `npx intlayer dictionary fill`\n- `npx intlayer dic fill`\n\n## Examples of output:\n\n```bash\nnpx intlayer fill\n\nPreparing Intlayer (v7.5.14)\nDone 76ms\n@intlayer/ai found - Run process locally\nProvider: (default) - Model: (default) - API Key: âœ“\nAffected dictionary keys for processing: app, comp-test, hello-world, lang-switcher\n - [comp-test]      No locales to fill, Skipping comp-test.content.json\n - [app]            Processing app.content.tsx\n - [app]            Filling missing metadata for app.content.tsx\n - [hello-world]    Processing test.content.ts\n - [hello-world]   [French (fr)]      Preparing test.content.ts\n - [hello-world]   [Spanish (es)]     Preparing test.content.ts\n - [lang-switcher]  Processing langSwitcher.content.ts\n - [lang-switcher]  Filling missing metadata for langSwitcher.content.ts\n - [hello-world]    Translation completed successfully for test.content.ts\n - [lang-switcher] [Spanish (es)]     Preparing langSwitcher.content.ts\n - [app]           [French (fr)]      Preparing app.content.tsx\n - [app]           [Spanish (es)]     Preparing app.content.tsx\n - [hello-world]    Content declaration written to test.content.ts\n - [app]            Translation completed successfully for app.content.tsx\n - [app]            Content declaration written to app.content.tsx\n - [lang-switcher]  Translation completed successfully for langSwitcher.content.ts\n - [lang-switcher]  Content declaration written to langSwitcher.content.ts\n```\n\n## Arguments:\n\n**Files list options:**\n\n- **`-f, --file [files...]`**: A list of specific content declaration files to audit. If not provided, all discovered `*.content.{ts,js,mjs,cjs,tsx,jsx,json}` based on your configuration file setup will be audited.\n\n  > Example: `npx intlayer dictionary fill -f src/home/app.content.ts`\n\n- **`-k, --keys [keys...]`**: Filter dictionaries based on keys. If not provided, all dictionaries will be audited.\n\n  > Example: `npx intlayer dictionary fill -k key1 key2`\n\n- **`--key [keys...]`**: Filter dictionaries based on keys (alias for --keys).\n\n  > Example: `npx intlayer dictionary fill --key key1 key2`\n\n- **`--excluded-keys [excludedKeys...]`**: Filter out dictionaries based on keys. If not provided, all dictionaries will be audited.\n\n  > Example: `npx intlayer dictionary fill --excluded-keys key1 key2`\n\n- **`--excluded-key [excludedKeys...]`**: Filter out dictionaries based on keys (alias for --excluded-keys).\n\n  > Example: `npx intlayer dictionary fill --excluded-key key1 key2`\n\n- **`--path-filter [pathFilters...]`**: Filter dictionaries based on glob pattern for file paths.\n\n  > Example: `npx intlayer dictionary fill --path-filter \"src/home/**\"`\n\n**Entry output options:**\n\n- **`--source-locale [sourceLocale]`**: The source locale to translate from. If not specified, the default locale from your configuration will be used.\n\n- **`--output-locales [outputLocales...]`**: Target locales to translate to. If not specified, all locales from your configuration will be used except the source locale.\n\n- **`--mode [mode]`**: Translation mode: `complete`, `review`. Default is `complete`. `complete` will fill all missing content, `review` will fill missing content and review existing keys.\n\n**Git options:**\n\n- **`--git-diff`**: Only run on dictionaries that includes changes from base (default `origin/main`) to current branch (default: `HEAD`).\n- **`--git-diff-base`**: Specify the base reference for git diff (default `origin/main`).\n- **`--git-diff-current`**: Specify the current reference for git diff (default: `HEAD`).\n- **`--uncommitted`**: Include uncommitted changes.\n- **`--unpushed`**: Include unpushed changes.\n- **`--untracked`**: Include untracked files.\n\n  > Example: `npx intlayer doc translate --git-diff --git-diff-base origin/main --git-diff-current HEAD`\n\n  > Example: `npx intlayer doc translate --uncommitted --unpushed --untracked`\n\n**AI options:**\n\n- **`--model [model]`**: The AI model to use for the translation (e.g., `gpt-3.5-turbo`).\n- **`--provider [provider]`**: The AI provider to use for the translation.\n- **`--temperature [temperature]`**: Temperature setting for the AI model.\n- **`--api-key [apiKey]`**: Provide your own API key for the AI service.\n- **`--custom-prompt [prompt]`**: Provide a custom prompt for your translation instructions.\n- **`--application-context [applicationContext]`**: Provide additional context for the AI translation.\n\n  > Example: `npx intlayer fill --model gpt-3.5-turbo --provider openai --temperature 0.5 --api-key sk-1234567890 --application-context \"My application is a cat store\"`\n\n**Environment variables options:**\n\n- **`--env`**: Specify the environment (e.g., `development`, `production`).\n- **`--env-file [envFile]`**: Provide a custom environment file to load variables from.\n\n  > Example: `npx intlayer fill --env-file .env.production.local`\n\n  > Example: `npx intlayer fill --env production`\n\n**Configuration options:**\n\n- **`--base-dir`**: Specify the base directory for the project.\n\n  > Example: `npx intlayer fill --base-dir ./src`\n\n- **`--no-cache`**: Disable the cache.\n\n  > Example: `npx intlayer build --no-cache`\n\n**Preparation options:**\n\n- **`--build`**: Build the dictionaries before pushing to ensure the content is up to date. True will force the build, false will skip the build, undefined will allow using the cache of the build.\n\n- **`--skip-metadata`**: Skip filling missing metadata (description, title, tags) for dictionaries.\n\n**Log options:**\n\n- **`--verbose`**: Enable verbose logging for debugging. (default to true using CLI)\n\n## Example:\n\n```bash\nnpx intlayer fill --file src/home/*.content.ts --source-locale en --output-locales fr es --model gpt-3.5-turbo\n```\n\nThis command will translate content from English to French and Spanish for all content declaration files in the `src/home/` directory using the GPT-3.5 Turbo model.\n",
  "createdAt": "2024-08-11",
  "updatedAt": "2025-11-22",
  "title": "Fill Dictionaries",
  "description": "Learn how to fill, audit, and translate your dictionaries using AI.",
  "keywords": [
    "Fill",
    "Audit",
    "Translate",
    "Dictionaries",
    "CLI",
    "Intlayer",
    "AI"
  ],
  "slugs": [
    "doc",
    "concept",
    "cli",
    "fill"
  ],
  "docKey": "./docs/en/cli/fill.md",
  "githubUrl": "https://github.com/aymericzip/intlayer/blob/main/docs/docs/en/cli/fill.md",
  "relativeUrl": "/doc/concept/cli/fill",
  "url": "https://intlayer.org/doc/concept/cli/fill"
}