{
  "id": "./docs/en/dictionary/content_file.md",
  "content": "---\ncreatedAt: 2025-02-07\nupdatedAt: 2026-01-28\ntitle: Content File\ndescription: Learn how to customize the extensions for your content declaration files. Follow this documentation to implement conditions efficiently in your project.\nkeywords:\n  - Content File\n  - Documentation\n  - Intlayer\nslugs:\n  - doc\n  - concept\n  - content\nhistory:\n  - version: 8.0.0\n    date: 2026-01-28\n    changes: Add `html` content node type\n  - version: 8.0.0\n    date: 2026-01-24\n    changes: Rename `live` import mode to `fetch` to better describe the underlying mechanism.\n  - version: 8.0.0\n    date: 2026-01-18\n    changes: Add `location`, `schema`, and `importMode` dictionary options\n  - version: 7.5.13\n    date: 2026-01-10\n    changes: Add support for JSON5 and JSONC file formats\n  - version: 7.5.0\n    date: 2025-12-13\n    changes: Add ICU and i18next format support\n  - version: 7.0.0\n    date: 2025-10-23\n    changes: Rename `autoFill` to `fill`\n  - version: 6.0.0\n    date: 2025-09-20\n    changes: Add fields documentation\n  - version: 5.5.10\n    date: 2025-06-29\n    changes: Init history\n---\n\n# Content File\n\n<iframe title=\"i18n, Markdown, JSON… one single solution to manage it all | Intlayer\" class=\"m-auto aspect-16/9 w-full overflow-hidden rounded-lg border-0\" allow=\"autoplay; gyroscope;\" loading=\"lazy\" width=\"1080\" height=\"auto\" src=\"https://www.youtube.com/embed/1VHgSY_j9_I?autoplay=0&amp;origin=http://intlayer.org&amp;controls=0&amp;rel=1\"/>\n\n## What is a Content File?\n\nA content file in Intlayer is a file that contains dictionary definitions.\nThese files declare your application's text content, translations, and resources.\nContent files are processed by Intlayer to generate dictionaries.\n\nThe dictionaries will be the final result that your application will import using the `useIntlayer` hook.\n\n### Key Concepts\n\n#### Dictionary\n\nA dictionary is a structured collection of content organized by keys. Each dictionary contains:\n\n- **Key**: A unique identifier for the dictionary\n- **Content**: The actual content values (text, numbers, objects, etc.)\n- **Metadata**: Additional information like title, description, tags, etc.\n\n#### Content File\n\nContent file example:\n\n```tsx fileName=\"src/example.content.tsx\" contentDeclarationFormat=\"typescript\"\nimport { type ReactNode } from \"react\";\nimport {\n  t,\n  enu,\n  cond,\n  nest,\n  md,\n  insert,\n  file,\n  type Dictionary,\n} from \"intlayer\";\n\ninterface Content {\n  imbricatedContent: {\n    imbricatedContent2: {\n      stringContent: string;\n      numberContent: number;\n      booleanContent: boolean;\n      javaScriptContent: string;\n    };\n  };\n  multilingualContent: string;\n  quantityContent: string;\n  conditionalContent: string;\n  markdownContent: never;\n  htmlContent: never;\n  externalContent: string;\n  insertionContent: string;\n  nestedContent: string;\n  fileContent: string;\n  jsxContent: ReactNode;\n}\n\nexport default {\n  key: \"page\",\n  content: {\n    imbricatedContent: {\n      imbricatedContent2: {\n        stringContent: \"Hello World\",\n        numberContent: 123,\n        booleanContent: true,\n        javaScriptContent: `${process.env.NODE_ENV}`,\n      },\n    },\n    multilingualContent: t({\n      en: \"English content\",\n      \"en-GB\": \"English content (UK)\",\n      fr: \"French content\",\n      es: \"Spanish content\",\n    }),\n    quantityContent: enu({\n      \"<-1\": \"Less than minus one car\",\n      \"-1\": \"Minus one car\",\n      \"0\": \"No cars\",\n      \"1\": \"One car\",\n      \">5\": \"Some cars\",\n      \">19\": \"Many cars\",\n    }),\n    conditionalContent: cond({\n      true: \"Validation is enabled\",\n      false: \"Validation is disabled\",\n    }),\n    insertionContent: insert(\"Hello {{name}}!\"),\n    nestedContent: nest(\n      \"navbar\", // The key of the dictionary to nest\n      \"login.button\" // [Optional] The path to the content to nest\n    ),\n    fileContent: file(\"./path/to/file.txt\"),\n    externalContent: fetch(\"https://example.com\").then((res) => res.json()),\n    markdownContent: md(\"# Markdown Example\"),\n    htmlContent: html(\"<p>Hello <strong>World</strong></p>\"),\n\n    /*\n     * Only available using `react-intlayer` or `next-intlayer`\n     */\n    jsxContent: <h1>My title</h1>,\n  },\n} satisfies Dictionary<Content>; // [optional] Dictionary is generic and allow you to strengthen the formatting of your dictionary\n```\n\n```javascript fileName=\"src/example.content.mjx\" contentDeclarationFormat=\"esm\"\nimport { t, enu, cond, nest, md, insert, file } from \"intlayer\";\n\n/** @type {import('intlayer').Dictionary} */\nexport default {\n  key: \"page\",\n  content: {\n    imbricatedContent: {\n      imbricatedContent2: {\n        stringContent: \"Hello World\",\n        numberContent: 123,\n        booleanContent: true,\n        javaScriptContent: `${process.env.NODE_ENV}`,\n      },\n      imbricatedArray: [1, 2, 3],\n    },\n    multilingualContent: t({\n      en: \"English content\",\n      \"en-GB\": \"English content (UK)\",\n      fr: \"French content\",\n      es: \"Spanish content\",\n    }),\n    quantityContent: enu({\n      \"<-1\": \"Less than minus one car\",\n      \"-1\": \"Minus one car\",\n      \"0\": \"No cars\",\n      \"1\": \"One car\",\n      \">5\": \"Some cars\",\n      \">19\": \"Many cars\",\n    }),\n    conditionalContent: cond({\n      true: \"Validation is enabled\",\n      false: \"Validation is disabled\",\n    }),\n    insertionContent: insert(\"Hello {{name}}!\"),\n    nestedContent: nest(\n      \"navbar\", // The key of the dictionary to nest\n      \"login.button\" // [Optional] The path to the content to nest\n    ),\n    markdownContent: md(\"# Markdown Example\"),\n    htmlContent: html(\"<p>Hello <strong>World</strong></p>\"),\n    fileContent: file(\"./path/to/file.txt\"),\n    externalContent: fetch(\"https://example.com\").then((res) => res.json())\n\n    // Only available using `react-intlayer` or `next-intlayer`\n    jsxContent: <h1>My title</h1>,\n  },\n};\n```\n\n```javascript fileName=\"src/example.content.cjx\" contentDeclarationFormat=\"commonjs\"\nconst { t, enu, cond, nest, md, insert, file } = require(\"intlayer\");\n\n/** @type {import('intlayer').Dictionary} */\nmodule.exports = {\n  key: \"page\",\n  content: {\n    imbricatedContent: {\n      imbricatedContent2: {\n        stringContent: \"Hello World\",\n        numberContent: 123,\n        booleanContent: true,\n        javaScriptContent: `${process.env.NODE_ENV}`,\n      },\n      imbricatedArray: [1, 2, 3],\n    },\n    multilingualContent: t({\n      en: \"English content\",\n      \"en-GB\": \"English content (UK)\",\n      fr: \"French content\",\n      es: \"Spanish content\",\n    }),\n    quantityContent: enu({\n      \"<-1\": \"Less than minus one car\",\n      \"-1\": \"Minus one car\",\n      \"0\": \"No cars\",\n      \"1\": \"One car\",\n      \">5\": \"Some cars\",\n      \">19\": \"Many cars\",\n    }),\n    conditionalContent: cond({\n      true: \"Validation is enabled\",\n      false: \"Validation is disabled\",\n    }),\n    insertionContent: insert(\"Hello {{name}}!\"),\n    nestedContent: nest(\n      \"navbar\", // The key of the dictionary to nest\n      \"login.button\" // [Optional] The path to the content to nest\n    ),\n    markdownContent: md(\"# Markdown Example\"),\n    htmlContent: html(\"<p>Hello <strong>World</strong></p>\"),\n    fileContent: file(\"./path/to/file.txt\"),\n    externalContent: fetch(\"https://example.com\").then((res) => res.json())\n\n    // Only available using `react-intlayer` or `next-intlayer`\n    jsxContent: <h1>My title</h1>,\n  },\n};\n```\n\n```json5 fileName=\"src/example.content.json\"  contentDeclarationFormat=\"json\"\n{\n  \"$schema\": \"https://intlayer.org/schema.json\",\n  \"key\": \"page\",\n  \"content\": {\n    \"imbricatedContent\": {\n      \"imbricatedContent2\": {\n        \"stringContent\": \"Hello World\",\n        \"numberContent\": 123,\n        \"booleanContent\": true,\n      },\n      \"imbricatedArray\": [1, 2, 3],\n    },\n    \"multilingualContent\": {\n      \"nodeType\": \"translation\",\n      \"translation\": {\n        \"en\": \"English content\",\n        \"en-GB\": \"English content (UK)\",\n        \"fr\": \"French content\",\n        \"es\": \"Spanish content\",\n      },\n    },\n    \"quantityContent\": {\n      \"nodeType\": \"enumeration\",\n      \"enumeration\": {\n        \"0\": \"No cars\",\n        \"1\": \"One car\",\n        \"<-1\": \"Less than minus one car\",\n        \"-1\": \"Minus one car\",\n        \">5\": \"Some cars\",\n        \">19\": \"Many cars\",\n      },\n    },\n    \"conditionalContent\": {\n      \"nodeType\": \"condition\",\n      \"condition\": {\n        \"true\": \"Validation is enabled\",\n        \"false\": \"Validation is disabled\",\n      },\n    },\n    \"insertionContent\": {\n      \"nodeType\": \"insertion\",\n      \"insertion\": \"Hello {{name}}!\",\n    },\n    \"nestedContent\": {\n      \"nodeType\": \"nested\",\n      \"nested\": { \"dictionaryKey\": \"app\" },\n    },\n    \"markdownContent\": {\n      \"nodeType\": \"markdown\",\n      \"markdown\": \"# Markdown Example\",\n    },\n    \"htmlContent\": {\n      \"nodeType\": \"html\",\n      \"html\": \"<p>Hello <strong>World</strong></p>\",\n    },\n    \"fileContent\": {\n      \"nodeType\": \"file\",\n      \"file\": \"./path/to/file.txt\",\n    },\n    \"jsxContent\": {\n      \"type\": \"h1\",\n      \"key\": null,\n      \"ref\": null,\n      \"props\": {\n        \"children\": [\"My title\"],\n      },\n    },\n  },\n}\n```\n\n#### Content Nodes\n\nContent nodes are the building blocks of dictionary content. They can be:\n\n- **Primitive values**: strings, numbers, booleans, null, undefined\n- **Typed nodes**: Special content types like translations, conditions, markdown, etc.\n- **Functions**: Dynamic content that can be evaluated at runtime [see Function Fetching](https://github.com/aymericzip/intlayer/blob/main/docs/docs/en/dictionary/function_fetching.md)\n- **Nested content**: References to other dictionaries\n\n#### Content Types\n\nIntlayer supports various content types through typed nodes:\n\n- **Translation Content**: Multilingual text with locale-specific values [see Translation Content](https://github.com/aymericzip/intlayer/blob/main/docs/docs/en/dictionary/translation_content.md)\n- **Condition Content**: Conditional content based on boolean expressions [see Condition Content](https://github.com/aymericzip/intlayer/blob/main/docs/docs/en/dictionary/condition_content.md)\n- **Enumeration Content**: Content that varies based on enumerated values [see Enumeration Content](https://github.com/aymericzip/intlayer/blob/main/docs/docs/en/dictionary/enumeration_content.md)\n- **Insertion Content**: Content that can be inserted into other content [see Insertion Content](https://github.com/aymericzip/intlayer/blob/main/docs/docs/en/dictionary/insertion_content.md)\n- **Markdown Content**: Rich text content in Markdown format [see Markdown Content](https://github.com/aymericzip/intlayer/blob/main/docs/docs/en/dictionary/markdown_content.md)\n- **HTML Content**: Rich HTML content with optional custom components [see HTML Content](https://github.com/aymericzip/intlayer/blob/main/docs/docs/en/dictionary/html.md)\n- **Nested Content**: References to other dictionaries [see Nested Content](https://github.com/aymericzip/intlayer/blob/main/docs/docs/en/dictionary/nested_content.md)\n- **Gender Content**: Content that varies based on gender [see Gender Content](https://github.com/aymericzip/intlayer/blob/main/docs/docs/en/dictionary/gender_content.md)\n- **File Content**: References to external files [see File Content](https://github.com/aymericzip/intlayer/blob/main/docs/docs/en/dictionary/file_content.md)\n\n## Dictionary Structure\n\nA dictionary in Intlayer is defined by the `Dictionary` type and contains several properties that control its behavior:\n\n### Required Properties\n\n#### `key` (string)\n\nThe identifier for the dictionary. If multiple dictionaries have the same key, Intlayer will merge them automatically.\n\n> Use kebab-case naming convention (e.g., `\"about-page-meta\"`).\n\n#### Content (string | number | boolean | object | array | function)\n\nThe `content` property contains the actual dictionary data and supports:\n\n- **Primitive values**: strings, numbers, booleans, null, undefined\n- **Typed nodes**: Special content types using Intlayer's helper functions\n- **Nested objects**: Complex data structures\n- **Arrays**: Collections of content\n- **Functions**: Dynamic content evaluation\n\n### Optional Properties\n\n#### `title` (string)\n\nHuman-readable title for the dictionary that helps identify it in editors and CMS systems. This is particularly useful when managing large numbers of dictionaries or when working with content management interfaces.\n\n**Example:**\n\n```typescript\n{\n  key: \"about-page-meta\",\n  title: \"About Page Metadata\",\n  content: { /* ... */ }\n}\n```\n\n#### `description` (string)\n\nDetailed description explaining the dictionary's purpose, usage guidelines, and any special considerations. This description is also used as context for AI-powered translation generation, making it valuable for maintaining translation quality and consistency.\n\n**Example:**\n\n```typescript\n{\n  key: \"about-page-meta\",\n  description: [\n    \"This dictionary manages the metadata of the About Page\",\n    \"Consider good practices for SEO:\",\n    \"- The title should be between 50 and 60 characters\",\n    \"- The description should be between 150 and 160 characters\",\n  ].join('\\n'),\n  content: { /* ... */ }\n}\n```\n\n#### `tags` (string[])\n\nArray of strings for categorizing and organizing dictionaries. Tags provide additional context and can be used for filtering, searching, or organizing dictionaries in editors and CMS systems.\n\n**Example:**\n\n```typescript\n{\n  key: \"about-page-meta\",\n  tags: [\"metadata\", \"about-page\", \"seo\"],\n  content: { /* ... */ }\n}\n```\n\n#### `format` ('intlayer' | 'icu' | 'i18next')\n\nSpecifies the formatter to use for the dictionary content. This allows using different message formatting syntaxes.\n\n- `'intlayer'`: The default Intlayer formatter.\n- `'icu'`: Uses ICU message formatting.\n- `'i18next'`: Uses i18next message formatting.\n\n**Example:**\n\n```typescript\n{\n  key: \"my-dictionary\",\n  format: \"icu\",\n  content: {\n    message: \"Hello {name}, you have {count, plural, one {# message} other {# messages}}\"\n  }\n}\n```\n\n#### `locale` (LocalesValues)\n\nTransforms the dictionary into a per-locale dictionary where each field declared in the content will be automatically transformed into a translation node. When this property is set:\n\n- The dictionary is treated as a single-locale dictionary\n- Each field becomes a translation node for that specific locale\n- You should NOT use translation nodes (`t()`) in the content when using this property\n- If missing, the dictionary will be treated as a multilingual dictionary\n\n> See [Per-Locale Content Declaration in Intlayer](https://github.com/aymericzip/intlayer/blob/main/docs/docs/en/per_locale_file.md) for more information.\n\n**Example:**\n\n```json\n// Per-locale dictionary\n{\n  \"key\": \"about-page\",\n  \"locale\": \"en\",\n  \"content\": {\n    \"title\": \"About Us\", // This becomes a translation node for 'en'\n    \"description\": \"Learn more about our company\"\n  }\n}\n```\n\n#### `schema` (SchemaKeys)\n\nThe schema of the dictionary content. If set, the content will be validated against this schema. This allows you to enforce a specific structure for your dictionary content using custom validation schemas defined in your Intlayer configuration.\n\n**Example:**\n\n```typescript fileName=\"intlayer.config.ts\"\nimport { z } from \"zod\";\n\nexport default {\n  schemas: {\n    \"seo-metadata\": z.object({\n      title: z.string().min(50).max(60),\n      description: z.string().min(150).max(160),\n    }),\n  },\n};\n```\n\n```typescript fileName=\"src/example.content.ts\"\nimport { type Dictionary } from \"intlayer\";\n\nconst aboutPageMetaContent = {\n  key: \"about-page-meta\",\n  schema: \"seo-metadata\",\n  content: {\n    title: \"About Our Company - Learn More About Us\",\n    description: \"Discover our company's mission, values, and team.\",\n  },\n} satisfies Dictionary<\"seo-metadata\">;\n\nexport default aboutPageMetaContent;\n```\n\n#### `location` ('remote' | 'local' | 'hybrid' | 'plugin')\n\nIndicates the location of the dictionary. This property can be set to control where the dictionary is sourced from:\n\n- `'local'`: Local dictionary (from content files)\n- `'remote'`: Remote dictionary (from external source/CMS)\n- `'hybrid'`: Dictionary that exists both locally and remotely\n- `'plugin'`: Dictionary provided by a plugin\n\n**Example:**\n\n```typescript\n{\n  key: \"about-page\",\n  location: \"local\",\n  content: {\n    title: \"About Us\"\n  }\n}\n```\n\n#### `fill` (Fill)\n\nInstructions for automatically filling dictionary content from external sources. This can be configured globally in `intlayer.config.ts` or per-dictionary. Supports multiple formats:\n\n- **`true`**: Enable filling for all locales\n- **`false`**: Disable filling for all locales\n- **`string`**: Path to a single file or template with variables\n- **`object`**: Per-locale file paths\n\n**Examples:**\n\n```json\n// Disable filling\n{\n  \"fill\": false\n}\n// Single file\n{\n  \"fill\": \"./translations/aboutPage.content.json\"\n}\n// Template with variables\n{\n  \"fill\": \"/messages/{{locale}}/{{key}}/{{fileName}}.content.json\"\n}\n// Fine per-locale configuration\n{\n  \"fill\": {\n    \"en\": \"./translations/en/aboutPage.content.json\",\n    \"fr\": \"./translations/fr/aboutPage.content.json\",\n    \"es\": \"./translations/es/aboutPage.content.json\"\n  }\n}\n```\n\n**Available variables:**\n\n- `{{locale}}` – Locale code (e.g. `fr`, `es`)\n- `{{fileName}}` – File name (e.g. `example`)\n- `{{key}}` – Dictionary key (e.g. `example`)\n\n> See [Auto-Fill Configuration in Intlayer](https://github.com/aymericzip/intlayer/blob/main/docs/docs/en/fill.md) for more information.\n\n##### `priority` (number)\n\nIndicates the priority of the dictionary for conflict resolution. When multiple dictionaries have the same key, the dictionary with the highest priority number will override the others. This is useful for managing content hierarchies and overrides.\n\n**Example:**\n\n```typescript\n// Base dictionary\n{\n  key: \"welcome-message\",\n  priority: 1,\n  content: { message: \"Welcome!\" }\n}\n\n// Override dictionary\n{\n  key: \"welcome-message\",\n  priority: 10,\n  content: { message: \"Welcome to our premium service!\" }\n}\n// This will override the base dictionary\n```\n\n### CMS Properties\n\n##### `version` (string)\n\nVersion identifier for remote dictionaries. Helps track which version of the dictionary is currently being used, especially useful when working with remote content management systems.\n\n##### `importMode` ('static' | 'dynamic' | 'fetch')\n\nThe import mode determines how your dictionary is imported in your application.\n\n- `'static'`: The dictionary is imported statically at build time. This is the default mode.\n- `'dynamic'`: The dictionary is imported dynamically at runtime using the suspense API.\n- `'fetch'`: The dictionary is imported dynamically using the live sync API.\n\nIf set, this property overrides the global `importMode` defined in the `dictionary` property of `intlayer.config.ts`.\n\n### System Properties (Auto-generated)\n\nThese properties are automatically generated by Intlayer and should not be manually modified:\n\n##### `$schema` (string)\n\nJSON schema used for validation of the dictionary structure. Automatically added by Intlayer to ensure dictionary integrity.\n\n##### `id` (string)\n\nFor remote dictionaries, this is the unique identifier of the dictionary in the remote server. Used for fetching and managing remote content.\n\n##### `projectIds` (string[])\n\nFor remote dictionaries, this array contains the IDs of the projects that can use this dictionary. A remote dictionary can be shared between multiple projects.\n\n##### `localId` (LocalDictionaryId)\n\nUnique identifier for local dictionaries. Auto-generated by Intlayer to help identify the dictionary and determine if it's local or remote, along with its location.\n\n##### `localIds` (LocalDictionaryId[])\n\nFor merged dictionaries, this array contains the IDs of all dictionaries that were merged together. Useful for tracking the source of merged content.\n\n##### `filePath` (string)\n\nThe file path of the local dictionary, indicating which `.content` file the dictionary was generated from. Helps with debugging and source tracking.\n\n##### `versions` (string[])\n\nFor remote dictionaries, this array contains all available versions of the dictionary. Helps track which versions are available for use.\n\n##### `filled` (true)\n\nIndicates whether the dictionary has been auto-filled from external sources. In case of conflicts, base dictionaries will override auto-filled dictionaries.\n\n## Content Node Types\n\nIntlayer provides several specialized content node types that extend basic primitive values:\n\n### Translation Content (`t`)\n\nMultilingual content that varies by locale:\n\n```typescript\nimport { t } from \"intlayer\";\n\n// TypeScript/JavaScript\nmultilingualContent: t({\n  en: \"Welcome to our website\",\n  fr: \"Bienvenue sur notre site web\",\n  es: \"Bienvenido a nuestro sitio web\",\n});\n```\n\n### Condition Content (`cond`)\n\nContent that changes based on boolean conditions:\n\n```typescript\nimport { cond } from \"intlayer\";\n\nconditionalContent: cond({\n  true: \"User is logged in\",\n  false: \"Please log in to continue\",\n});\n```\n\n### Enumeration Content (`enu`)\n\nContent that varies based on enumerated values:\n\n```typescript\nimport { enu } from \"intlayer\";\n\nstatusContent: enu({\n  pending: \"Your request is pending\",\n  approved: \"Your request has been approved\",\n  rejected: \"Your request has been rejected\",\n});\n```\n\n### Insertion Content (`insert`)\n\nContent that can be inserted into other content:\n\n```typescript\nimport { insert } from \"intlayer\";\n\ninsertionContent: insert(\"This text can be inserted anywhere\");\n```\n\n### Nested Content (`nest`)\n\nReferences to other dictionaries:\n\n```typescript\nimport { nest } from \"intlayer\";\n\nnestedContent: nest(\"about-page\");\n```\n\n### Markdown Content (`md`)\n\nRich text content in Markdown format:\n\n```typescript\nimport { md } from \"intlayer\";\n\nmarkdownContent: md(\n  \"# Welcome\\n\\nThis is **bold** text with [links](https://example.com)\"\n);\n\nlocalizedMarkdownContent: t({\n  en: md(file(\"./content.en.md\")),\n  fr: md(file(\"./content.fr.md\")),\n});\n```\n\n### HTML Content (`html`)\n\nRich HTML content that can use standard tags or custom components:\n\n```typescript\nimport { html, file, t } from \"intlayer\";\n\n// Inline HTML\nhtmlContent: html(\"<p>Hello <strong>World</strong></p>\");\n\n// Per-locale HTML from external files\nlocalizedHtmlContent: t({\n  en: html(file(\"./content.en.html\")),\n  fr: html(file(\"./content.fr.html\")),\n});\n```\n\n### Gender Content (`gender`)\n\nContent that varies based on gender:\n\n```typescript\nimport { gender } from \"intlayer\";\n\ngenderContent: gender({\n  male: \"He is a developer\",\n  female: \"She is a developer\",\n  other: \"They are a developer\",\n});\n```\n\n### File Content (`file`)\n\nReferences to external files:\n\n```typescript\nimport { file } from \"intlayer\";\n\nfileContent: file(\"./path/to/content.txt\");\n```\n\n## Creating Content Files\n\n### Basic Content File Structure\n\nA content file exports a default object that satisfies the `Dictionary` type:\n\n```typescript\n// example.content.ts\nimport { t, cond, nest, md, insert, file } from \"intlayer\";\n\nexport default {\n  key: \"welcome-page\",\n  title: \"Welcome Page Content\",\n  description:\n    \"Content for the main welcome page including hero section and features\",\n  tags: [\"page\", \"welcome\", \"homepage\"],\n  content: {\n    hero: {\n      title: t({\n        en: \"Welcome to Our Platform\",\n        fr: \"Bienvenue sur Notre Plateforme\",\n        es: \"Bienvenido a Nuestra Plataforma\",\n      }),\n      subtitle: t({\n        en: \"Build amazing applications with ease\",\n        fr: \"Construisez des applications incroyables avec facilité\",\n        es: \"Construye aplicaciones increíbles con facilidad\",\n      }),\n      cta: cond({\n        true: t({\n          en: \"Get Started\",\n          fr: \"Commencer\",\n          es: \"Comenzar\",\n        }),\n        false: t({\n          en: \"Sign Up\",\n          fr: \"S'inscrire\",\n          es: \"Registrarse\",\n        }),\n      }),\n    },\n    features: [\n      {\n        title: t({\n          en: \"Easy to Use\",\n          fr: \"Facile à Utiliser\",\n          es: \"Fácil de Usar\",\n        }),\n        description: t({\n          en: \"Intuitive interface for all skill levels\",\n          fr: \"Interface intuitive pour tous les niveaux\",\n          es: \"Interfaz intuitiva para todos los niveles\",\n        }),\n      },\n    ],\n    documentation: nest(\"documentation\"),\n    readme: file(\"./README.md\"),\n  },\n} satisfies Dictionary;\n```\n\n### JSON Content File\n\nYou can also create content files in JSON format:\n\n```json\n{\n  \"key\": \"welcome-page\",\n  \"title\": \"Welcome Page Content\",\n  \"description\": \"Content for the main welcome page\",\n  \"tags\": [\"page\", \"welcome\"],\n  \"content\": {\n    \"hero\": {\n      \"title\": {\n        \"nodeType\": \"translation\",\n        \"translation\": {\n          \"en\": \"Welcome to Our Platform\",\n          \"fr\": \"Bienvenue sur Notre Plateforme\"\n        }\n      },\n      \"subtitle\": {\n        \"nodeType\": \"translation\",\n        \"translation\": {\n          \"en\": \"Build amazing applications with ease\",\n          \"fr\": \"Construisez des applications incroyables avec facilité\"\n        }\n      }\n    }\n  }\n}\n```\n\n### Per-Locale Content Files\n\nFor per-locale dictionaries, specify the `locale` property:\n\n```typescript\n// welcome-page.en.content.ts\nexport default {\n  key: \"welcome-page\",\n  locale: \"en\",\n  content: {\n    hero: {\n      title: \"Welcome to Our Platform\",\n      subtitle: \"Build amazing applications with ease\",\n    },\n  },\n} satisfies Dictionary;\n```\n\n```typescript\n// welcome-page.fr.content.ts\nexport default {\n  key: \"welcome-page\",\n  locale: \"fr\",\n  content: {\n    hero: {\n      title: \"Bienvenue sur Notre Plateforme\",\n      subtitle: \"Construisez des applications incroyables avec facilité\",\n    },\n  },\n} satisfies Dictionary;\n```\n\n## Content File Extensions\n\nIntlayer allows you to customize the extensions for your content declaration files. This customization provides flexibility in managing large-scale projects and helps to avoid conflicts with other modules.\n\n### Default Extensions\n\nBy default, Intlayer watches all files with the following extensions for content declarations:\n\n- `.content.json`\n- `.content.json5`\n- `.content.jsonc`\n- `.content.ts`\n- `.content.tsx`\n- `.content.js`\n- `.content.jsx`\n- `.content.mjs`\n- `.content.mjx`\n- `.content.cjs`\n- `.content.cjx`\n\nThese default extensions are suitable for most applications. However, when you have specific needs, you can define custom extensions to streamline the build process and reduce the risk of conflicts with other components.\n\n> To customize the file extensions Intlayer uses to identify content declaration files, you can specify them in the Intlayer configuration file. This approach is beneficial for large-scale projects where limiting the scope of the watch process improves build performance.\n\n## Advanced Concepts\n\n### Dictionary Merging\n\nWhen multiple dictionaries have the same key, Intlayer automatically merges them. The merging behavior depends on several factors:\n\n- **Priority**: Dictionaries with higher `priority` values override those with lower values\n- **Auto-fill vs Base**: Base dictionaries override auto-filled dictionaries\n- **Location**: Local dictionaries override remote dictionaries (when priorities are equal)\n\n### Type Safety\n\nIntlayer provides full TypeScript support for content files:\n\n```typescript\n// Define your content type\ninterface WelcomePageContent {\n  hero: {\n    title: string;\n    subtitle: string;\n    cta: string;\n  };\n  features: Array<{\n    title: string;\n    description: string;\n  }>;\n}\n\n// Use it in your dictionary\nexport default {\n  key: \"welcome-page\",\n  content: {\n    // TypeScript will provide autocomplete and type checking\n    hero: {\n      title: \"Welcome\",\n      subtitle: \"Build amazing apps\",\n      cta: \"Get Started\",\n    },\n  },\n} satisfies Dictionary<WelcomePageContent>;\n```\n\n### Node Imbrication\n\nYou can without problem imbricate functions into other ones.\n\nExample :\n\n```javascript fileName=\"src/example.content.tsx\" contentDeclarationFormat=\"typescript\"\nimport { t, enu, cond, nest, md, type Dictionary } from \"intlayer\";\n\nconst getName = async () => \"John Doe\";\n\nexport default {\n  key: \"page\",\n  content: {\n    // `getIntlayer('page','en').hiMessage` returns `['Hi', ' ', 'John Doe']`\n    hiMessage: [\n      t({\n        en: \"Hi\",\n        fr: \"Salut\",\n        es: \"Hola\",\n      }),\n      \" \",\n      getName(),\n    ],\n    // Composite content imbricating condition, enumeration, and multilingual content\n    // `getIntlayer('page','en').advancedContent(true)(10) returns 'Multiple items found'`\n    advancedContent: cond({\n      true: enu({\n        \"0\": t({\n          en: \"No items found\",\n          fr: \"Aucun article trouvé\",\n          es: \"No se encontraron artículos\",\n        }),\n        \"1\": t({\n          en: \"One item found\",\n          fr: \"Un article trouvé\",\n          es: \"Se encontró un artículo\",\n        }),\n        \">1\": t({\n          en: \"Multiple items found\",\n          fr: \"Plusieurs articles trouvés\",\n          es: \"Se encontraron múltiples artículos\",\n        }),\n      }),\n      false: t({\n        en: \"No valid data available\",\n        fr: \"Aucune donnée valide disponible\",\n        es: \"No hay datos válidos disponibles\",\n      }),\n    }),\n  },\n} satisfies Dictionary;\n```\n\n```javascript fileName=\"src/example.content.mjx\" contentDeclarationFormat=\"esm\"\nimport { t, enu, cond, nest, md } from \"intlayer\";\n\nconst getName = async () => \"John Doe\";\n\n/** @type {import('intlayer').Dictionary} */\nexport default {\n  key: \"page\",\n  content: {\n    // `getIntlayer('page','en').hiMessage` returns `['Hi', ' ', 'John Doe']`\n    hiMessage: [\n      t({\n        en: \"Hi\",\n        fr: \"Salut\",\n        es: \"Hola\",\n      }),\n      \" \",\n      getName(),\n    ],\n    // Composite content imbricating condition, enumeration, and multilingual content\n    // `getIntlayer('page','en').advancedContent(true)(10) returns 'Multiple items found'`\n    advancedContent: cond({\n      true: enu({\n        \"0\": t({\n          en: \"No items found\",\n          fr: \"Aucun article trouvé\",\n          es: \"No se encontraron artículos\",\n        }),\n        \"1\": t({\n          en: \"One item found\",\n          fr: \"Un article trouvé\",\n          es: \"Se encontró un artículo\",\n        }),\n        \">1\": t({\n          en: \"Multiple items found\",\n          fr: \"Plusieurs articles trouvés\",\n          es: \"Se encontraron múltiples artículos\",\n        }),\n      }),\n      false: t({\n        en: \"No valid data available\",\n        fr: \"Aucune donnée valide disponible\",\n        es: \"No hay datos válidos disponibles\",\n      }),\n    }),\n  },\n};\n```\n\n```javascript fileName=\"src/example.content.cjx\" contentDeclarationFormat=\"commonjs\"\nconst { t, enu, cond, nest, md } = require(\"intlayer\");\n\nconst getName = async () => \"John Doe\";\n\n/** @type {import('intlayer').Dictionary} */\nmodule.exports = {\n  key: \"page\",\n  content: {\n    // `getIntlayer('page','en').hiMessage` returns `['Hi', ' ', 'John Doe']`\n    hiMessage: [\n      t({\n        en: \"Hi\",\n        fr: \"Salut\",\n        es: \"Hola\",\n      }),\n      \" \",\n      getName(),\n    ],\n    // Composite content imbricating condition, enumeration, and multilingual content\n    // `getIntlayer('page','en').advancedContent(true)(10) returns 'Multiple items found'`\n    advancedContent: cond({\n      true: enu({\n        \"0\": t({\n          en: \"No items found\",\n          fr: \"Aucun article trouvé\",\n          es: \"No se encontraron artículos\",\n        }),\n        \"1\": t({\n          en: \"One item found\",\n          fr: \"Un article trouvé\",\n          es: \"Se encontró un artículo\",\n        }),\n        \">1\": t({\n          en: \"Multiple items found\",\n          fr: \"Plusieurs articles trouvés\",\n          es: \"Se encontraron múltiples artículos\",\n        }),\n      }),\n      false: t({\n        en: \"No valid data available\",\n        fr: \"Aucune donnée valide disponible\",\n        es: \"No hay datos válidos disponibles\",\n      }),\n    }),\n  },\n};\n```\n\n```json5 fileName=\"src/example.content.json\"  contentDeclarationFormat=\"json\"\n{\n  \"$schema\": \"https://intlayer.org/schema.json\",\n  \"key\": \"page\",\n  \"content\": {\n    \"hiMessage\": {\n      \"nodeType\": \"composite\",\n      \"composite\": [\n        {\n          \"nodeType\": \"translation\",\n          \"translation\": {\n            \"en\": \"Hi\",\n            \"fr\": \"Salut\",\n            \"es\": \"Hola\",\n          },\n        },\n        \" \",\n        \"John Doe\",\n      ],\n    },\n    \"advancedContent\": {\n      \"nodeType\": \"condition\",\n      \"condition\": {\n        \"true\": {\n          \"nodeType\": \"enumeration\",\n          \"enumeration\": {\n            \"0\": {\n              \"nodeType\": \"translation\",\n              \"translation\": {\n                \"en\": \"No items found\",\n                \"fr\": \"Aucun article trouvé\",\n                \"es\": \"No se encontraron artículos\",\n              },\n            },\n            \"1\": {\n              \"nodeType\": \"translation\",\n              \"translation\": {\n                \"en\": \"One item found\",\n                \"fr\": \"Un article trouvé\",\n                \"es\": \"Se encontró un artículo\",\n              },\n            },\n            \">1\": {\n              \"nodeType\": \"translation\",\n              \"translation\": {\n                \"en\": \"Multiple items found\",\n                \"fr\": \"Plusieurs articles trouvés\",\n                \"es\": \"Se encontraron múltiples artículos\",\n              },\n            },\n          },\n        },\n        \"false\": {\n          \"nodeType\": \"translation\",\n          \"translation\": {\n            \"en\": \"No valid data available\",\n            \"fr\": \"Aucune donnée valide disponible\",\n            \"es\": \"No hay datos válidos disponibles\",\n          },\n        },\n      },\n    },\n  },\n}\n```\n\n### Best Practices\n\n1. **Naming Conventions**:\n   - Use kebab-case for dictionary keys (`\"about-page-meta\"`)\n   - Group related content under the same key prefix\n\n2. **Content Organization**:\n   - Keep related content together in the same dictionary\n   - Use nested objects to organize complex content structures\n   - Leverage tags for categorization\n   - Use the `fill` to automatically fill the missing translations\n\n3. **Performance**:\n   - Ajust the content configuration to limit the scope of watched files\n   - Use live dictionaries only when real-time updates are necessary, (e.g. A/B testing, etc.)\n   - Ensure the build transformation plugin (`@intlayer/swc`, or `@intlayer/babel`) is enabled to optimize the dictionary at build time\n",
  "createdAt": "2025-02-07",
  "updatedAt": "2026-01-28",
  "title": "Content File",
  "description": "Learn how to customize the extensions for your content declaration files. Follow this documentation to implement conditions efficiently in your project.",
  "keywords": [
    "Content File",
    "Documentation",
    "Intlayer"
  ],
  "slugs": [
    "doc",
    "concept",
    "content"
  ],
  "history": [
    {
      "version": "8.0.0",
      "date": "2026-01-28",
      "changes": "Add `html` content node type"
    },
    {
      "version": "8.0.0",
      "date": "2026-01-24",
      "changes": "Rename `live` import mode to `fetch` to better describe the underlying mechanism."
    },
    {
      "version": "8.0.0",
      "date": "2026-01-18",
      "changes": "Add `location`, `schema`, and `importMode` dictionary options"
    },
    {
      "version": "7.5.13",
      "date": "2026-01-10",
      "changes": "Add support for JSON5 and JSONC file formats"
    },
    {
      "version": "7.5.0",
      "date": "2025-12-13",
      "changes": "Add ICU and i18next format support"
    },
    {
      "version": "7.0.0",
      "date": "2025-10-23",
      "changes": "Rename `autoFill` to `fill`"
    },
    {
      "version": "6.0.0",
      "date": "2025-09-20",
      "changes": "Add fields documentation"
    },
    {
      "version": "5.5.10",
      "date": "2025-06-29",
      "changes": "Init history"
    }
  ],
  "docKey": "./docs/en/dictionary/content_file.md",
  "githubUrl": "https://github.com/aymericzip/intlayer/blob/main/docs/docs/en/dictionary/content_file.md",
  "relativeUrl": "/doc/concept/content",
  "url": "https://intlayer.org/doc/concept/content"
}