{
  "id": "./docs/en/intlayer_with_nestjs.md",
  "content": "---\ncreatedAt: 2025-09-09\nupdatedAt: 2025-12-30\ntitle: NestJS i18n - How to translate your NestJS app – guide 2026\ndescription: Discover how to make your NestJS backend multilingual. Follow the documentation to internationalize (i18n) and translate it.\nkeywords:\n  - Internationalization\n  - Documentation\n  - Intlayer\n  - NestJS\n  - JavaScript\n  - Backend\nslugs:\n  - doc\n  - environment\n  - nest\napplicationTemplate: https://github.com/aymericzip/intlayer-nestjs-template\nhistory:\n  - version: 7.5.9\n    date: 2025-12-30\n    changes: Add init command\n  - version: 5.8.0\n    date: 2025-09-09\n    changes: Initial doc\n---\n\n# Translate your Nest backend website using Intlayer | Internationalization (i18n)\n\n`express-intlayer` is a powerful internationalization (i18n) middleware for Express applications, designed to make your backend services globally accessible by providing localized responses based on the client's preferences. Since NestJS is built on top of Express, you can seamlessly integrate `express-intlayer` into your NestJS applications to handle multilingual content effectively.\n\ntical Use Cases\n\n- **Displaying Backend Errors in User's Language**: When an error occurs, displaying messages in the user's native language improves understanding and reduces frustration. This is especially useful for dynamic error messages that might be shown in front-end components like toasts or modals.\n\n- **Retrieving Multilingual Content**: For applications pulling content from a database, internationalization ensures that you can serve this content in multiple languages. This is crucial for platforms like e-commerce sites or content management systems that need to display product descriptions, articles, and other content in the language preferred by the user.\n\n- **Sending Multilingual Emails**: Whether it's transactional emails, marketing campaigns, or notifications, sending emails in the recipient’s language can significantly increase engagement and effectiveness.\n\n- **Multilingual Push Notifications**: For mobile applications, sending push notifications in a user's preferred language can enhance interaction and retention. This personal touch can make notifications feel more relevant and actionable.\n\n- **Other Communications**: Any form of communication from the backend, such as SMS messages, system alerts, or user interface updates, benefits from being in the user's language, ensuring clarity and enhancing the overall user experience.\n\nBy internationalizing the backend, your application not only respects cultural differences but also aligns better with global market needs, making it a key step in scaling your services worldwide.\n\n## Getting Started\n\n<iframe\n  src=\"https://stackblitz.com/github/aymericzip/intlayer-nestjs-template?embed=1&ctl=1&file=intlayer.config.ts\"\n  className=\"m-auto overflow-hidden rounded-lg border-0 max-md:size-full max-md:h-[700px] md:aspect-16/9 md:w-full\"\n  title=\"Demo CodeSandbox - How to Internationalize your application using Intlayer\"\n  sandbox=\"allow-forms allow-modals allow-popups allow-presentation allow-same-origin allow-scripts\"\n  loading=\"lazy\"\n/>\n\nSee [Application Template](https://github.com/aymericzip/intlayer-nestjs-template) on GitHub.\n\n### Create a new NestJS Project\n\n```bash packageManager=\"npm\"\nnpm install -g @nestjs/cli\nnest new my-nest-app\n```\n\n### Installation\n\nTo begin using `express-intlayer`, install the package using npm:\n\n```bash packageManager=\"npm\"\nnpm install intlayer express-intlayer\nnpx intlayer init\n```\n\n```bash packageManager=\"pnpm\"\npnpm add intlayer express-intlayer\npnpm intlayer init\n```\n\n```bash packageManager=\"yarn\"\nyarn add intlayer express-intlayer\nyarn intlayer init\n```\n\n```bash packageManager=\"bun\"\nbun add intlayer express-intlayer\nbunx intlayer init\n```\n\n### Configure tsconfig.json\n\nIn order to use Intlayer with TypeScript, ensure your `tsconfig.json` is set up to support ES modules. You can do this by setting the `module` and `moduleResolution` options to `nodenext`.\n\n```json5 fileName=\"tsconfig.json\"\n{\n  compilerOptions: {\n    module: \"nodenext\",\n    moduleResolution: \"nodenext\",\n    // ... other options\n  },\n}\n```\n\n### Setup\n\nConfigure the internationalization settings by creating an `intlayer.config.ts` in your project root:\n\n```typescript fileName=\"intlayer.config.ts\"  codeFormat=\"typescript\"\nimport { Locales, type IntlayerConfig } from \"intlayer\";\n\nconst config: IntlayerConfig = {\n  internationalization: {\n    locales: [Locales.ENGLISH, Locales.FRENCH, Locales.SPANISH],\n    defaultLocale: Locales.ENGLISH,\n  },\n};\n\nexport default config;\n```\n\n```javascript fileName=\"intlayer.config.mjs\" codeFormat=\"esm\"\nimport { Locales } from \"intlayer\";\n\n/** @type {import('intlayer').IntlayerConfig} */\nconst config = {\n  internationalization: {\n    locales: [Locales.ENGLISH, Locales.FRENCH, Locales.SPANISH],\n    defaultLocale: Locales.ENGLISH,\n  },\n};\n\nexport default config;\n```\n\n```javascript fileName=\"intlayer.config.cjs\" codeFormat=\"commonjs\"\nconst { Locales } = require(\"intlayer\");\n\n/** @type {import('intlayer').IntlayerConfig} */\nconst config = {\n  internationalization: {\n    locales: [Locales.ENGLISH, Locales.FRENCH, Locales.SPANISH],\n    defaultLocale: Locales.ENGLISH,\n  },\n};\n\nmodule.exports = config;\n```\n\n### Declare Your Content\n\nCreate and manage your content declarations to store translations:\n\n```typescript fileName=\"src/app.content.ts\" contentDeclarationFormat=\"typescript\"\nimport { t, type Dictionary } from \"intlayer\";\n\nconst appContent: Dictionary = {\n  key: \"app\",\n  content: {\n    greet: t({\n      en: \"Hello World!\",\n      fr: \"Bonjour le monde !\",\n      es: \"¡Hola Mundo!\",\n    }),\n  },\n};\n\nexport default appContent;\n```\n\n> Your content declarations can be defined anywhere in your application as soon as they are included into the `contentDir` directory (by default, `./src`). And match the content declaration file extension (by default, `.content.{json,ts,tsx,js,jsx,mjs,cjs}`).\n\n> For more details, refer to the [content declaration documentation](/doc/concept/content).\n\n### Express Middleware Setup\n\nIntegrate the `express-intlayer` middleware into your NestJS application to handle internationalization:\n\n```typescript fileName=\"src/app.module.ts\" codeFormat=\"typescript\"\nimport { MiddlewareConsumer, Module, NestModule } from \"@nestjs/common\";\nimport { AppController } from \"./app.controller\";\nimport { AppService } from \"./app.service\";\nimport { intlayer } from \"express-intlayer\";\n\n@Module({\n  imports: [],\n  controllers: [AppController],\n  providers: [AppService],\n})\nexport class AppModule implements NestModule {\n  configure(consumer: MiddlewareConsumer) {\n    consumer.apply(intlayer()).forRoutes(\"*\"); // Apply to all routes\n  }\n}\n```\n\n### Use Translations in Your Services or Controllers\n\nYou can now use the `getIntlayer` function to access translations in your services or controllers:\n\n```typescript fileName=\"src/app.service.ts\" codeFormat=\"typescript\"\nimport { Injectable } from \"@nestjs/common\";\nimport { getIntlayer } from \"express-intlayer\";\n\n@Injectable()\nexport class AppService {\n  getHello(): string {\n    return getIntlayer(\"app\").greet;\n  }\n}\n```\n\n### Compatibility\n\n`express-intlayer` is fully compatible with:\n\n- [`react-intlayer`](/doc/packages/react-intlayer) for React applications\n- [`next-intlayer`](/doc/packages/next-intlayer) for Next.js applications\n- [`vite-intlayer`](/doc/packages/vite-intlayer) for Vite applications\n\nIt also works seamlessly with any internationalization solution across various environments, including browsers and API requests. You can customize the middleware to detect locale through headers or cookies:\n\n```typescript fileName=\"intlayer.config.ts\" codeFormat=\"typescript\"\nimport { Locales, type IntlayerConfig } from \"intlayer\";\n\nconst config: IntlayerConfig = {\n  // ... Other configuration options\n  middleware: {\n    headerName: \"my-locale-header\",\n    cookieName: \"my-locale-cookie\",\n  },\n};\n\nexport default config;\n```\n\nBy default, `express-intlayer` will interpret the `Accept-Language` header to determine the client's preferred language.\n\n> For more information on configuration and advanced topics, visit our [documentation](/doc/concept/configuration).\n\n### Configure TypeScript\n\n`express-intlayer` leverages the robust capabilities of TypeScript to enhance the internationalization process. TypeScript's static typing ensures that every translation key is accounted for, reducing the risk of missing translations and improving maintainability.\n\n![Autocompletion](https://github.com/aymericzip/intlayer/blob/main/docs/assets/autocompletion.png?raw=true)\n\n![Translation error](https://github.com/aymericzip/intlayer/blob/main/docs/assets/translation_error.png?raw=true)\n\nEnsure the autogenerated types (by default at ./types/intlayer.d.ts) are included in your tsconfig.json file.\n\n```json5 fileName=\"tsconfig.json\"\n{\n  // ... Your existing TypeScript configurations\n  include: [\n    // ... Your existing TypeScript configurations\n    \".intlayer/**/*.ts\", // Include the auto-generated types\n  ],\n}\n```\n\n### VS Code Extension\n\nTo improve your development experience with Intlayer, you can install the official **Intlayer VS Code Extension**.\n\n[Install from the VS Code Marketplace](https://marketplace.visualstudio.com/items?itemName=intlayer.intlayer-vs-code-extension)\n\nThis extension provides:\n\n- **Autocompletion** for translation keys.\n- **Real-time error detection** for missing translations.\n- **Inline previews** of translated content.\n- **Quick actions** to easily create and update translations.\n\nFor more details on how to use the extension, refer to the [Intlayer VS Code Extension documentation](https://intlayer.org/doc/vs-code-extension).\n\n### Git Configuration\n\nIt is recommended to ignore the files generated by Intlayer. This allows you to avoid committing them to your Git repository.\n\nTo do this, you can add the following instructions to your `.gitignore` file:\n\n```plaintext fileName=\".gitignore\"\n# Ignore the files generated by Intlayer\n.intlayer\n```\n",
  "createdAt": "2025-09-09",
  "updatedAt": "2025-12-30",
  "title": "NestJS i18n - How to translate your NestJS app – guide 2026",
  "description": "Discover how to make your NestJS backend multilingual. Follow the documentation to internationalize (i18n) and translate it.",
  "keywords": [
    "Internationalization",
    "Documentation",
    "Intlayer",
    "NestJS",
    "JavaScript",
    "Backend"
  ],
  "slugs": [
    "doc",
    "environment",
    "nest"
  ],
  "applicationTemplate": "https://github.com/aymericzip/intlayer-nestjs-template",
  "history": [
    {
      "version": "7.5.9",
      "date": "2025-12-30",
      "changes": "Add init command"
    },
    {
      "version": "5.8.0",
      "date": "2025-09-09",
      "changes": "Initial doc"
    }
  ],
  "docKey": "./docs/en/intlayer_with_nestjs.md",
  "githubUrl": "https://github.com/aymericzip/intlayer/blob/main/docs/docs/en/intlayer_with_nestjs.md",
  "relativeUrl": "/doc/environment/nest",
  "url": "https://intlayer.org/doc/environment/nest"
}