{
  "id": "./docs/en/intlayer_with_adonisjs.md",
  "content": "---\ncreatedAt: 2025-08-23\nupdatedAt: 2025-12-30\ntitle: AdonisJS i18n - How to translate your AdonisJS app – guide 2026\ndescription: Discover how to make your AdonisJS backend multilingual. Follow the documentation to internationalize (i18n) and translate it.\nkeywords:\n  - Internationalization\n  - Documentation\n  - Intlayer\n  - AdonisJS\n  - JavaScript\n  - Backend\nslugs:\n  - doc\n  - environment\n  - adonisjs\napplicationTemplate: https://github.com/aymericzip/intlayer-adonisjs-template\nhistory:\n  - version: 8.0.0\n    date: 2025-12-30\n    changes: Init history\n---\n\n# Translate your AdonisJS backend website using Intlayer | Internationalization (i18n)\n\n`adonis-intlayer` is a powerful internationalization (i18n) package for AdonisJS applications, designed to make your backend services globally accessible by providing localized responses based on the client's preferences.\n\n### Practical Use Cases\n\n- **Displaying Backend Errors in User's Language**: When an error occurs, displaying messages in the user's native language improves understanding and reduces frustration. This is especially useful for dynamic error messages that might be shown in front-end components like toasts or modals.\n\n- **Retrieving Multilingual Content**: For applications pulling content from a database, internationalization ensures that you can serve this content in multiple languages. This is crucial for platforms like e-commerce sites or content management systems that need to display product descriptions, articles, and other content in the language preferred by the user.\n\n- **Sending Multilingual Emails**: Whether it's transactional emails, marketing campaigns, or notifications, sending emails in the recipient’s language can significantly increase engagement and effectiveness.\n\n- **Multilingual Push Notifications**: For mobile applications, sending push notifications in a user's preferred language can enhance interaction and retention. This personal touch can make notifications feel more relevant and actionable.\n\n- **Other Communications**: Any form of communication from the backend, such as SMS messages, system alerts, or user interface updates, benefits from being in the user's language, ensuring clarity and enhancing the overall user experience.\n\nBy internationalizing the backend, your application not only respects cultural differences but also aligns better with global market needs, making it a key step in scaling your services worldwide.\n\n## Getting Started\n\n<iframe\n  src=\"https://stackblitz.com/github/aymericzip/intlayer-adonisjs-template?embed=1&ctl=1&file=intlayer.config.ts\"\n  className=\"m-auto overflow-hidden rounded-lg border-0 max-md:size-full max-md:h-[700px] md:aspect-16/9 md:w-full\"\n  title=\"Demo CodeSandbox - How to Internationalize your application using Intlayer\"\n  sandbox=\"allow-forms allow-modals allow-popups allow-presentation allow-same-origin allow-scripts\"\n  loading=\"lazy\"\n/>\n\nSee [Application Template](https://github.com/aymericzip/intlayer-adonisjs-template) on GitHub.\n\n### Installation\n\nTo begin using `adonis-intlayer`, install the package using npm:\n\n```bash packageManager=\"npm\"\nnpm install intlayer adonis-intlayer\nnpx intlayer init\n```\n\n```bash packageManager=\"pnpm\"\npnpm add intlayer adonis-intlayer\npnpm intlayer init\n```\n\n```bash packageManager=\"yarn\"\nyarn add intlayer adonis-intlayer\nyarn intlayer init\n```\n\n```bash packageManager=\"bun\"\nbun add intlayer adonis-intlayer\nbunx intlayer init\n```\n\n### Setup\n\nConfigure the internationalization settings by creating an `intlayer.config.ts` in your project root:\n\n```typescript fileName=\"intlayer.config.ts\"  codeFormat=\"typescript\"\nimport { Locales, type IntlayerConfig } from \"intlayer\";\n\nconst config: IntlayerConfig = {\n  internationalization: {\n    locales: [\n      Locales.ENGLISH,\n      Locales.RUSSIAN,\n      Locales.JAPANESE,\n      Locales.FRENCH,\n      Locales.KOREAN,\n      Locales.CHINESE,\n      Locales.SPANISH,\n      Locales.GERMAN,\n      Locales.ARABIC,\n      Locales.ITALIAN,\n      Locales.ENGLISH_UNITED_KINGDOM,\n      Locales.PORTUGUESE,\n      Locales.HINDI,\n      Locales.TURKISH,\n      Locales.POLISH,\n      Locales.INDONESIAN,\n      Locales.VIETNAMESE,\n      Locales.UKRAINIAN,\n    ],\n    defaultLocale: Locales.ENGLISH,\n  },\n};\n\nexport default config;\n```\n\n```javascript fileName=\"intlayer.config.mjs\" codeFormat=\"esm\"\nimport { Locales } from \"intlayer\";\n\n/** @type {import('intlayer').IntlayerConfig} */\nconst config = {\n  internationalization: {\n    locales: [\n      Locales.ENGLISH,\n      Locales.RUSSIAN,\n      Locales.JAPANESE,\n      Locales.FRENCH,\n      Locales.KOREAN,\n      Locales.CHINESE,\n      Locales.SPANISH,\n      Locales.GERMAN,\n      Locales.ARABIC,\n      Locales.ITALIAN,\n      Locales.ENGLISH_UNITED_KINGDOM,\n      Locales.PORTUGUESE,\n      Locales.HINDI,\n      Locales.TURKISH,\n      Locales.POLISH,\n      Locales.INDONESIAN,\n      Locales.VIETNAMESE,\n      Locales.UKRAINIAN,\n    ],\n    defaultLocale: Locales.ENGLISH,\n  },\n};\n\nexport default config;\n```\n\n```javascript fileName=\"intlayer.config.cjs\" codeFormat=\"commonjs\"\nconst { Locales } = require(\"intlayer\");\n\n/** @type {import('intlayer').IntlayerConfig} */\nconst config = {\n  internationalization: {\n    locales: [\n      Locales.ENGLISH,\n      Locales.RUSSIAN,\n      Locales.JAPANESE,\n      Locales.FRENCH,\n      Locales.KOREAN,\n      Locales.CHINESE,\n      Locales.SPANISH,\n      Locales.GERMAN,\n      Locales.ARABIC,\n      Locales.ITALIAN,\n      Locales.ENGLISH_UNITED_KINGDOM,\n      Locales.PORTUGUESE,\n      Locales.HINDI,\n      Locales.TURKISH,\n      Locales.POLISH,\n      Locales.INDONESIAN,\n      Locales.VIETNAMESE,\n      Locales.UKRAINIAN,\n    ],\n    defaultLocale: Locales.ENGLISH,\n  },\n};\n\nmodule.exports = config;\n```\n\n### Declare Your Content\n\nCreate and manage your content declarations to store translations:\n\n```typescript fileName=\"app/index.content.ts\" contentDeclarationFormat=\"typescript\"\nimport { t, type Dictionary } from \"intlayer\";\n\nconst indexContent = {\n  key: \"index\",\n  content: {\n    exampleOfContent: t({\n      en: \"Example of returned content in English\",\n      fr: \"Exemple de contenu renvoyé en français\",\n      \"es-ES\": \"Ejemplo de contenido devuelto en español (España)\",\n      \"es-MX\": \"Ejemplo de contenido devuelto en español (México)\",\n    }),\n  },\n} satisfies Dictionary;\n\nexport default indexContent;\n```\n\n```javascript fileName=\"app/index.content.mjs\" contentDeclarationFormat=\"esm\"\nimport { t } from \"intlayer\";\n\n/** @type {import('intlayer').Dictionary} */\nconst indexContent = {\n  key: \"index\",\n  content: {\n    exampleOfContent: t({\n      en: \"Example of returned content in English\",\n      fr: \"Exemple de contenu renvoyé en français\",\n      \"es-ES\": \"Ejemplo de contenido devuelto en español (España)\",\n      \"es-MX\": \"Ejemplo de contenido devuelto en español (México)\",\n    }),\n  },\n};\n\nexport default indexContent;\n```\n\n```javascript fileName=\"app/index.content.cjs\" contentDeclarationFormat=\"commonjs\"\nconst { t } = require(\"intlayer\");\n\n/** @type {import('intlayer').Dictionary} */\nconst indexContent = {\n  key: \"index\",\n  content: {\n    exampleOfContent: t({\n      en: \"Example of returned content in English\",\n      fr: \"Exemple de contenu renvoyé en français\",\n      \"es-ES\": \"Ejemplo de contenido devuelto en español (España)\",\n      \"es-MX\": \"Ejemplo de contenido devuelto en español (México)\",\n    }),\n  },\n};\n\nmodule.exports = indexContent;\n```\n\n```json fileName=\"app/index.content.json\" contentDeclarationFormat=\"json\"\n{\n  \"$schema\": \"https://intlayer.org/schema.json\",\n  \"key\": \"index\",\n  \"content\": {\n    \"exampleOfContent\": {\n      \"nodeType\": \"translation\",\n      \"translation\": {\n        \"en\": \"Example of returned content in English\",\n        \"fr\": \"Exemple de contenu renvoyé en français\",\n        \"es-ES\": \"Ejemplo de contenido devuelto en español (España)\",\n        \"es-MX\": \"Ejemplo de contenido devuelto en español (México)\"\n      }\n    }\n  }\n}\n```\n\n> Your content declarations can be defined anywhere in your application as soon as they are included into the `contentDir` directory (by default, `./src` or `./app`). And match the content declaration file extension (by default, `.content.{json,ts,tsx,js,jsx,mjs,cjs}`).\n\n> For more details, refer to the [content declaration documentation](https://github.com/aymericzip/intlayer/blob/main/docs/docs/en/dictionary/content_file.md).\n\n### AdonisJS Application Setup\n\nSetup your AdonisJS application to use `adonis-intlayer`.\n\n#### Register the middleware\n\nFirst, you need to register the `intlayer` middleware in your application.\n\n```typescript fileName=\"start/kernel.ts\"\nrouter.use([() => import(\"adonis-intlayer/middleware\")]);\n```\n\n#### Define your routes\n\n```typescript fileName=\"start/routes.ts\"\nimport router from \"@adonisjs/core/services/router\";\nimport { t, getIntlayer, getDictionary } from \"adonis-intlayer\";\nimport indexContent from \"../app/index.content\";\n\nrouter.get(\"/t_example\", async () => {\n  return t({\n    en: \"Example of returned content in English\",\n    fr: \"Exemple de contenu renvoyé en français\",\n    \"es-ES\": \"Ejemplo de contenido devuelto en español (España)\",\n    \"es-MX\": \"Ejemplo de contenido devuelto en español (México)\",\n  });\n});\n\nrouter.get(\"/getIntlayer_example\", async () => {\n  return getIntlayer(\"index\").exampleOfContent;\n});\n\nrouter.get(\"/getDictionary_example\", async () => {\n  return getDictionary(indexContent).exampleOfContent;\n});\n```\n\n#### Functions\n\n`adonis-intlayer` exports several functions to handle internationalization in your application:\n\n- `t(content, locale?)`: Basic translation function.\n- `getIntlayer(key, locale?)`: Retrieve content by key from your dictionaries.\n- `getDictionary(dictionary, locale?)`: Retrieve content from a specific dictionary object.\n- `getLocale()`: Retrieve the current locale from the request context.\n\n#### Use in Controllers\n\n```typescript fileName=\"app/controllers/example_controller.ts\"\nimport type { HttpContext } from \"@adonisjs/core/http\";\nimport { t } from \"adonis-intlayer\";\n\nexport default class ExampleController {\n  async index({ response }: HttpContext) {\n    return response.send(\n      t({\n        en: \"Hello from controller\",\n        fr: \"Bonjour depuis le contrôleur\",\n      })\n    );\n  }\n}\n```\n\n### Compatibility\n\n`adonis-intlayer` is fully compatible with:\n\n- [`react-intlayer`](https://github.com/aymericzip/intlayer/blob/main/docs/docs/en/packages/react-intlayer/index.md) for React applications\n- [`next-intlayer`](https://github.com/aymericzip/intlayer/blob/main/docs/docs/en/packages/next-intlayer/index.md) for Next.js applications\n- [`vite-intlayer`](https://github.com/aymericzip/intlayer/blob/main/docs/docs/en/packages/vite-intlayer/index.md) for Vite applications\n\nIt also works seamlessly with any internationalization solution across various environments, including browsers and API requests. You can customize the middleware to detect locale through headers or cookies:\n\n```typescript fileName=\"intlayer.config.ts\" codeFormat=\"typescript\"\nimport { Locales, type IntlayerConfig } from \"intlayer\";\n\nconst config: IntlayerConfig = {\n  // ... Other configuration options\n  middleware: {\n    headerName: \"my-locale-header\",\n    cookieName: \"my-locale-cookie\",\n  },\n};\n\nexport default config;\n```\n\nBy default, `adonis-intlayer` will interpret the `Accept-Language` header to determine the client's preferred language.\n\n> For more information on configuration and advanced topics, visit our [documentation](https://github.com/aymericzip/intlayer/blob/main/docs/docs/en/configuration.md).\n\n### Configure TypeScript\n\n`adonis-intlayer` leverages the robust capabilities of TypeScript to enhance the internationalization process. TypeScript's static typing ensures that every translation key is accounted for, reducing the risk of missing translations and improving maintainability.\n\n![Autocompletion](https://github.com/aymericzip/intlayer/blob/main/docs/assets/autocompletion.png?raw=true)\n\n![Translation error](https://github.com/aymericzip/intlayer/blob/main/docs/assets/translation_error.png?raw=true)\n\nEnsure the autogenerated types (by default at ./types/intlayer.d.ts) are included in your tsconfig.json file.\n\n```json5 fileName=\"tsconfig.json\"\n{\n  // ... Your existing TypeScript configurations\n  \"include\": [\n    // ... Your existing TypeScript configurations\n    \".intlayer/**/*.ts\", // Include the auto-generated types\n  ],\n}\n```\n\n### VS Code Extension\n\nTo improve your development experience with Intlayer, you can install the official **Intlayer VS Code Extension**.\n\n[Install from the VS Code Marketplace](https://marketplace.visualstudio.com/items?itemName=intlayer.intlayer-vs-code-extension)\n\nThis extension provides:\n\n- **Autocompletion** for translation keys.\n- **Real-time error detection** for missing translations.\n- **Inline previews** of translated content.\n- **Quick actions** to easily create and update translations.\n\nFor more details on how to use the extension, refer to the [Intlayer VS Code Extension documentation](https://intlayer.org/doc/vs-code-extension).\n\n### Git Configuration\n\nIt is recommended to ignore the files generated by Intlayer. This allows you to avoid committing them to your Git repository.\n\nTo do this, you can add the following instructions to your `.gitignore` file:\n\n```plaintext fileName=\".gitignore\"\n# Ignore the files generated by Intlayer\n.intlayer\n```\n",
  "createdAt": "2025-08-23",
  "updatedAt": "2025-12-30",
  "title": "AdonisJS i18n - How to translate your AdonisJS app – guide 2026",
  "description": "Discover how to make your AdonisJS backend multilingual. Follow the documentation to internationalize (i18n) and translate it.",
  "keywords": [
    "Internationalization",
    "Documentation",
    "Intlayer",
    "AdonisJS",
    "JavaScript",
    "Backend"
  ],
  "slugs": [
    "doc",
    "environment",
    "adonisjs"
  ],
  "applicationTemplate": "https://github.com/aymericzip/intlayer-adonisjs-template",
  "history": [
    {
      "version": "8.0.0",
      "date": "2025-12-30",
      "changes": "Init history"
    }
  ],
  "docKey": "./docs/en/intlayer_with_adonisjs.md",
  "githubUrl": "https://github.com/aymericzip/intlayer/blob/main/docs/docs/en/intlayer_with_adonisjs.md",
  "relativeUrl": "/doc/environment/adonisjs",
  "url": "https://intlayer.org/doc/environment/adonisjs"
}