{
  "id": "./docs/en/intlayer_CMS.md",
  "content": "---\ncreatedAt: 2025-08-23\nupdatedAt: 2025-08-23\ntitle: Intlayer CMS | Externalize your content into the Intlayer CMS\ndescription: Externalize your content into the Intlayer CMS to delegate the management of your content to your team.\nkeywords:\n  - CMS\n  - Visual Editor\n  - Internationalization\n  - Documentation\n  - Intlayer\n  - Next.js\n  - JavaScript\n  - React\nslugs:\n  - doc\n  - concept\n  - cms\nyoutubeVideo: https://www.youtube.com/watch?v=UDDTnirwi_4\nhistory:\n  - version: 6.0.1\n    date: 2025-09-22\n    changes: Add live sync documentation\n  - version: 6.0.0\n    date: 2025-09-04\n    changes: Replace `hotReload` field by `liveSync`\n  - version: 5.5.10\n    date: 2025-06-29\n    changes: Init history\n---\n\n# Intlayer Content Management System (CMS) Documentation\n\n<iframe title=\"Visual Editor + CMS for Your Web App: Intlayer Explained\" class=\"m-auto aspect-16/9 w-full overflow-hidden rounded-lg border-0\" allow=\"autoplay; gyroscope;\" loading=\"lazy\" width=\"1080\" height=\"auto\" src=\"https://www.youtube.com/embed/UDDTnirwi_4?autoplay=0&amp;origin=http://intlayer.org&amp;controls=0&amp;rel=1\"/>\n\nThe Intlayer CMS is am Application that allows you to externalize your content of an Intlayer project.\n\nFor that, Intlayer introduce the concept of 'distant dictionaries'.\n\n![Intlayer CMS Interface](https://github.com/aymericzip/intlayer/blob/main/docs/assets/CMS.png)\n\n## Table of Contents\n\n<TOC/>\n\n---\n\n## Understanding distant dictionaries\n\nIntlayer make a difference between 'local' and 'remote' dictionaries.\n\n- A 'local' dictionary is a dictionary that is declared in your Intlayer project. Such as the declaration file of a button, or your navigation bar. Externalizing your content do not make sense in this case because this content is not supposed to change often.\n\n- A 'remote' dictionary is a dictionary that is managed through the Intlayer CMS. It could be useful to allow your team to manage your content in direct on your website, and also aims to use A/B testing features and SEO automatic optimization.\n\n## Visual editor vs CMS\n\nThe [Intlayer Visual](https://github.com/aymericzip/intlayer/blob/main/docs/docs/en/intlayer_visual_editor.md) editor is a tool that allows you to manage your content in a visual editor for local dictionaries. Once a change is made, the content will be replaced in the code-base. That means that the application will be rebuilt and the page will be reloaded to display the new content.\n\nIn contrast, the Intlayer CMS is a tool that allows you to manage your content in a visual editor for distant dictionaries. Once a change is made, the content will **not** impact your code-base. And the website will automatically display the changed content.\n\n## Integrating\n\nFor more details on how to install the package, see the relevant section below:\n\n### Integrating with Next.js\n\nFor integration with Next.js, refer to the [setup guide](https://github.com/aymericzip/intlayer/blob/main/docs/docs/en/intlayer_with_nextjs_15.md).\n\n### Integrating with Create React App\n\nFor integration with Create React App, refer to the [setup guide](https://github.com/aymericzip/intlayer/blob/main/docs/docs/en/intlayer_with_create_react_app.md).\n\n### Integrating with Vite + React\n\nFor integration with Vite + React, refer to the [setup guide](https://github.com/aymericzip/intlayer/blob/main/docs/docs/en/intlayer_with_vite+react.md).\n\n## Configuration\n\nRun the following command to login to the Intlayer CMS:\n\n```bash packageManager=\"npm\"\nnpx intlayer login\n```\n\n```bash packageManager=\"yarn\"\nyarn intlayer login\n```\n\n```bash packageManager=\"pnpm\"\npnpm intlayer login\n```\n\n```bash packageManager=\"bun\"\nbunx intlayer login\n```\n\nThis will open your default browser to complete the authentication process and receive the necessary credentials (Client ID and Client Secret) to use Intlayer services.\n\nIn your Intlayer configuration file, you can customize the CMS settings:\n\n```typescript fileName=\"intlayer.config.ts\" codeFormat=\"typescript\"\nimport type { IntlayerConfig } from \"intlayer\";\n\nconst config: IntlayerConfig = {\n  // ... other configuration settings\n  editor: {\n    /**\n     * Required\n     *\n     * The URL of the application.\n     * This is the URL targeted by the visual editor.\n     */\n    applicationURL: process.env.INTLAYER_APPLICATION_URL,\n\n    /**\n     * Required\n     *\n     * Client ID and client secret are required to enable the editor.\n     * They allow the identify the user who is editing the content.\n     * They can be obtained by creating a new client in the Intlayer Dashboard - Projects (https://app.intlayer.org/projects).\n     * clientId: process.env.INTLAYER_CLIENT_ID,\n     * clientSecret: process.env.INTLAYER_CLIENT_SECRET,\n     */\n    clientId: process.env.INTLAYER_CLIENT_ID,\n    clientSecret: process.env.INTLAYER_CLIENT_SECRET,\n\n    /**\n     * Optional\n     *\n     * In the case you are self-hosting the Intlayer CMS, you can set the URL of the CMS.\n     *\n     * The URL of the Intlayer CMS.\n     * By default, it is set to https://intlayer.org\n     */\n    cmsURL: process.env.INTLAYER_CMS_URL,\n\n    /**\n     * Optional\n     *\n     * In the case you are self-hosting the Intlayer CMS, you can set the URL of the backend.\n     *\n     * The URL of the Intlayer CMS.\n     * By default, it is set to https://back.intlayer.org\n     */\n    backendURL: process.env.INTLAYER_BACKEND_URL,\n  },\n};\n\nexport default config;\n```\n\n```javascript fileName=\"intlayer.config.mjs\" codeFormat=\"esm\"\n/** @type {import('intlayer').IntlayerConfig} */\nconst config = {\n  // ... other configuration settings\n  editor: {\n    /**\n     * Required\n     *\n     * The URL of the application.\n     * This is the URL targeted by the visual editor.\n     */\n    applicationURL: process.env.INTLAYER_APPLICATION_URL,\n\n    /**\n     * Required\n     *\n     * Client ID and client secret are required to enable the editor.\n     * They allow the identify the user who is editing the content.\n     * They can be obtained by creating a new client in the Intlayer Dashboard - Projects (https://app.intlayer.org/projects).\n     * clientId: process.env.INTLAYER_CLIENT_ID,\n     * clientSecret: process.env.INTLAYER_CLIENT_SECRET,\n     */\n    clientId: process.env.INTLAYER_CLIENT_ID,\n    clientSecret: process.env.INTLAYER_CLIENT_SECRET,\n\n    /**\n     * Optional\n     *\n     * In the case you are self-hosting the Intlayer CMS, you can set the URL of the CMS.\n     *\n     * The URL of the Intlayer CMS.\n     * By default, it is set to https://intlayer.org\n     */\n    cmsURL: process.env.INTLAYER_CMS_URL,\n\n    /**\n     * Optional\n     *\n     * In the case you are self-hosting the Intlayer CMS, you can set the URL of the backend.\n     *\n     * The URL of the Intlayer CMS.\n     * By default, it is set to https://back.intlayer.org\n     */\n    backendURL: process.env.INTLAYER_BACKEND_URL,\n  },\n};\n\nexport default config;\n```\n\n```javascript fileName=\"intlayer.config.cjs\" codeFormat=\"commonjs\"\n/** @type {import('intlayer').IntlayerConfig} */\nconst config = {\n  // ... other configuration settings\n  editor: {\n    /**\n     * Required\n     *\n     * The URL of the application.\n     * This is the URL targeted by the visual editor.\n     */\n    applicationURL: process.env.INTLAYER_APPLICATION_URL,\n\n    /**\n     * Required\n     *\n     * Client ID and client secret are required to enable the editor.\n     * They allow the identify the user who is editing the content.\n     * They can be obtained by creating a new client in the Intlayer Dashboard - Projects (https://app.intlayer.org/projects).\n     * clientId: process.env.INTLAYER_CLIENT_ID,\n     * clientSecret: process.env.INTLAYER_CLIENT_SECRET,\n     */\n    clientId: process.env.INTLAYER_CLIENT_ID,\n    clientSecret: process.env.INTLAYER_CLIENT_SECRET,\n\n    /**\n     * Optional\n     *\n     * In the case you are self-hosting the Intlayer CMS, you can set the URL of the CMS.\n     *\n     * The URL of the Intlayer CMS.\n     * By default, it is set to https://intlayer.org\n     */\n    cmsURL: process.env.INTLAYER_CMS_URL,\n\n    /**\n     * Optional\n     *\n     * In the case you are self-hosting the Intlayer CMS, you can set the URL of the backend.\n     *\n     * The URL of the Intlayer CMS.\n     * By default, it is set to https://back.intlayer.org\n     */\n    backendURL: process.env.INTLAYER_BACKEND_URL,\n  },\n};\n\nmodule.exports = config;\n```\n\n> If you don't have a client ID and client secret, you can obtain them by creating a new client in the [Intlayer Dashboard - Projects](https://app.intlayer.org/projects).\n\n> To see all available parameters, refer to the [configuration documentation](https://github.com/aymericzip/intlayer/blob/main/docs/docs/en/configuration.md).\n\n## Using the CMS\n\n### Push your configuration\n\nTo configure the Intlayer CMS, you can use the [intlayer CLI](https://github.com/aymericzip/intlayer/tree/main/docs/en/intlayer_cli.md) commands.\n\n```bash\nnpx intlayer config push\n```\n\n> If you use environment variables in your `intlayer.config.ts` configuration file, you can specify the desired environment using the `--env` argument:\n\n```bash\nnpx intlayer config push --env production\n```\n\nThis command uploads your configuration to the Intlayer CMS.\n\n### Push a dictionary\n\nTo transform your locale dictionaries in a distant dictionary, you can use the [intlayer CLI](https://github.com/aymericzip/intlayer/tree/main/docs/en/intlayer_cli.md) commands.\n\n```bash\nnpx intlayer dictionary push -d my-first-dictionary-key\n```\n\n> If you use environment variables in your `intlayer.config.ts` configuration file, you can specify the desired environment using the `--env` argument:\n\n```bash\nnpx intlayer dictionary push -d my-first-dictionary-key --env production\n```\n\nThis command uploads your initial content dictionaries, making them available for asynchronous fetching and editing through the Intlayer platform.\n\n### Edit the dictionary\n\nThen you will be able to see and manage your dictionary in the [Intlayer CMS](https://app.intlayer.org/content).\n\n## Live sync\n\nLive Sync lets your app reflect CMS content changes at runtime. No rebuild or redeploy required. When enabled, updates are streamed to a Live Sync server that refreshes the dictionaries your application reads.\n\nEnable Live Sync by updating your Intlayer configuration:\n\n```typescript fileName=\"intlayer.config.ts\" codeFormat=\"typescript\"\nimport type { IntlayerConfig } from \"intlayer\";\n\nconst config: IntlayerConfig = {\n  // ... other configuration settings\n  editor: {\n    /**\n     * Enables hot reloading of locale configurations when changes are detected.\n     * For example, when a dictionary is added or updated, the application updates\n     * the content displayed on the page.\n     *\n     * Because hot reloading requires a continuous connection to the server, it is\n     * only available for clients of the `enterprise` plan.\n     *\n     * Default: false\n     */\n    liveSync: true,\n  },\n  dictionary: {\n    /**\n     * Controls how dictionaries are imported:\n     *\n     * - \"fetch\": Dictionaries are fetched dynamically using the Live Sync API.\n     *   Replaces useIntlayer with useDictionaryDynamic.\n     *\n     * Note: Live mode uses the Live Sync API to fetch dictionaries. If the API call\n     * fails, dictionaries are imported dynamically.\n     * Note: Only dictionaries with remote content and \"live\" flags use live mode.\n     * Others use dynamic mode for performance.\n     */\n    importMode: \"fetch\",\n  },\n};\n\nexport default config;\n```\n\n```javascript fileName=\"intlayer.config.mjs\" codeFormat=\"esm\"\n/** @type {import('intlayer').IntlayerConfig} */\nconst config = {\n  // ... other configuration settings\n  editor: {\n    /**\n     * Enables hot reloading of locale configurations when changes are detected.\n     * For example, when a dictionary is added or updated, the application updates\n     * the content displayed on the page.\n     *\n     * Because hot reloading requires a continuous connection to the server, it is\n     * only available for clients of the `enterprise` plan.\n     *\n     * Default: false\n     */\n    liveSync: true,\n  },\n  dictionary: {\n    /**\n     * Controls how dictionaries are imported:\n     *\n     * - \"fetch\": Dictionaries are fetched dynamically using the Live Sync API.\n     *   Replaces useIntlayer with useDictionaryDynamic.\n     *\n     * Note: Live mode uses the Live Sync API to fetch dictionaries. If the API call\n     * fails, dictionaries are imported dynamically.\n     * Note: Only dictionaries with remote content and \"live\" flags use live mode.\n     * Others use dynamic mode for performance.\n     */\n    importMode: \"fetch\",\n  },\n};\n\nexport default config;\n```\n\n```javascript fileName=\"intlayer.config.cjs\" codeFormat=\"commonjs\"\n/** @type {import('intlayer').IntlayerConfig} */\nconst config = {\n  // ... other configuration settings\n  editor: {\n    /**\n     * Enables hot reloading of locale configurations when changes are detected.\n     * For example, when a dictionary is added or updated, the application updates\n     * the content displayed on the page.\n     *\n     * Because hot reloading requires a continuous connection to the server, it is\n     * only available for clients of the `enterprise` plan.\n     *\n     * Default: false\n     */\n    liveSync: true,\n\n    /**\n     * The port of the Live Sync server.\n     *\n     * Default: 4000\n     */\n    liveSyncPort: 4000,\n\n    /**\n     * The URL of the Live Sync server.\n     *\n     * Default: http://localhost:{liveSyncPort}\n     */\n    liveSyncURL: \"https://live.example.com\",\n  },\n  build: {\n    /**\n     * Controls how dictionaries are imported:\n     *\n     * - \"fetch\": Dictionaries are fetched dynamically using the Live Sync API.\n     *   Replaces useIntlayer with useDictionaryDynamic.\n     *\n     * Note: Live mode uses the Live Sync API to fetch dictionaries. If the API call\n     * fails, dictionaries are imported dynamically.\n     * Note: Only dictionaries with remote content and \"live\" flags use live mode.\n     * Others use dynamic mode for performance.\n     */\n    importMode: \"fetch\",\n  },\n};\n\nmodule.exports = config;\n```\n\nStart the Live Sync server to wrap your application:\n\nExample using standalone server:\n\n```json5 fileName=\"package.json\"\n{\n  \"scripts\": {\n    // ... other scripts\n    \"live:start\": \"npx intlayer live\",\n  },\n}\n```\n\nYou can also use your application server in parallel using the `--process` argument.\n\nExample using Next.js:\n\n```json5 fileName=\"package.json\"\n{\n  \"scripts\": {\n    // ... other scripts\n    \"build\": \"next build\",\n    \"dev\": \"next dev\",\n    \"start\": \"npx intlayer live --process 'next start'\",\n  },\n}\n```\n\nExample using Vite:\n\n```json5 fileName=\"package.json\"\n{\n  \"scripts\": {\n    // ... other scripts\n    \"build\": \"vite build\",\n    \"dev\": \"vite dev\",\n    \"start\": \"npx intlayer live --process 'vite start'\",\n  },\n}\n```\n\nThe Live Sync server wraps your application and automatically applies updated content as it arrives.\n\nTo receive change notifications from the CMS, the Live Sync server maintains an SSE connection to the backend. When content changes in the CMS, the backend forwards the update to the Live Sync server, which writes the new dictionaries. Your application will reflect the update on the next navigation or browser reloadâ€”no rebuild required.\n\nFlow chart (CMS/Backend -> Live Sync Server -> Application Server -> Frontend):\n\n![Live Sync Flow CMS/Backend/Live Sync Server/Application Server/Frontend Schema](https://github.com/aymericzip/intlayer/blob/main/docs/assets/live_sync_flow_scema.svg)\n\nHow it works:\n\n![Live Sync Logic Schema](https://github.com/aymericzip/intlayer/blob/main/docs/assets/live_sync_logic_schema.svg)\n\n### Development workflow (local)\n\n- In development, all remote dictionaries are fetched when the application starts, so you can test updates quickly.\n- To test Live Sync locally with Next.js, wrap your dev server:\n\n```json5 fileName=\"package.json\"\n{\n  \"scripts\": {\n    // ... other scripts\n    \"dev\": \"npx intlayer live --process 'next dev'\",\n    // \"dev\": \"npx intlayer live --process 'vite dev'\", // For Vite\n  },\n}\n```\n\nEnable optimization so Intlayer applies the Live import transformations during development:\n\n```typescript fileName=\"intlayer.config.ts\" codeFormat=\"typescript\"\nimport type { IntlayerConfig } from \"intlayer\";\n\nconst config: IntlayerConfig = {\n  editor: {\n    applicationURL: \"http://localhost:5173\",\n    liveSyncURL: \"http://localhost:4000\",\n    liveSync: true,\n  },\n  dictionary: {\n    importMode: \"fetch\",\n  },\n  build: {\n    optimize: true, // default: process.env.NODE_ENV === 'production'\n  },\n};\n\nexport default config;\n```\n\n```javascript fileName=\"intlayer.config.mjs\" codeFormat=\"esm\"\n/** @type {import('intlayer').IntlayerConfig} */\nconst config = {\n  editor: {\n    applicationURL: \"http://localhost:5173\",\n    liveSyncURL: \"http://localhost:4000\",\n    liveSync: true,\n  },\n  dictionary: {\n    importMode: \"fetch\",\n  },\n  build: {\n    optimize: true, // default: process.env.NODE_ENV === 'production'\n  },\n};\n\nexport default config;\n```\n\n```javascript fileName=\"intlayer.config.cjs\" codeFormat=\"commonjs\"\n/** @type {import('intlayer').IntlayerConfig} */\nconst config = {\n  editor: {\n    applicationURL: \"http://localhost:5173\",\n    liveSyncURL: \"http://localhost:4000\",\n    liveSync: true,\n  },\n  dictionary: {\n    importMode: \"fetch\",\n  },\n  build: {\n    optimize: true, // default: process.env.NODE_ENV === 'production'\n  },\n};\n\nmodule.exports = config;\n```\n\nThis setup wraps your dev server with the Live Sync server, fetches remote dictionaries at startup, and streams updates from the CMS via SSE. Refresh the page to see changes.\n\nNotes and constraints:\n\n- Add the live sync origin to your site security policy (CSP). Ensure the live sync URL is allowed in `connect-src` (and `frame-ancestors` if relevant).\n- Live Sync does not work with static output. For Next.js, the page must be dynamic to receive updates at runtime (e.g., use `generateStaticParams`, `generateMetadata`, `getServerSideProps`, or `getStaticProps` appropriately to avoid full static-only constraints).\n- In the CMS, each dictionary has a `live` flag. Only dictionaries with `live=true` are fetched via the live sync API; others are imported dynamically and remain unchanged at runtime.\n- The `live` flag is evaluated for each dictionary at build time. If remote content wasn't flagged `live=true` during build, you must rebuild to enable Live Sync for that dictionary.\n- The live sync server must be able to write to `.intlayer`. In containers, ensure write access to `/.intlayer`.\n\n## Debug\n\nIf you encounter any issues with the CMS, check the following:\n\n- The application is running.\n\n- The [`editor`](https://intlayer.org/doc/concept/configuration#editor-configuration) configuration are correctly set in your Intlayer configuration file.\n  - Required fields:\n    - The application URL should match the one you set in the editor configuration (`applicationURL`).\n    - The CMS URL\n\n- Ensure that the project configuration was pushed to the Intlayer CMS.\n\n- The visual editor use an iframe to display your website. Ensure that the Content Security Policy (CSP) of your website allows the CMS url as `frame-ancestors` ('https://app.intlayer.org' by default). Check the editor console for any error.\n",
  "createdAt": "2025-08-23",
  "updatedAt": "2025-08-23",
  "title": "Intlayer CMS | Externalize your content into the Intlayer CMS",
  "description": "Externalize your content into the Intlayer CMS to delegate the management of your content to your team.",
  "keywords": [
    "CMS",
    "Visual Editor",
    "Internationalization",
    "Documentation",
    "Intlayer",
    "Next.js",
    "JavaScript",
    "React"
  ],
  "slugs": [
    "doc",
    "concept",
    "cms"
  ],
  "youtubeVideo": "https://www.youtube.com/watch?v=UDDTnirwi_4",
  "history": [
    {
      "version": "6.0.1",
      "date": "2025-09-22",
      "changes": "Add live sync documentation"
    },
    {
      "version": "6.0.0",
      "date": "2025-09-04",
      "changes": "Replace `hotReload` field by `liveSync`"
    },
    {
      "version": "5.5.10",
      "date": "2025-06-29",
      "changes": "Init history"
    }
  ],
  "docKey": "./docs/en/intlayer_CMS.md",
  "githubUrl": "https://github.com/aymericzip/intlayer/blob/main/docs/docs/en/intlayer_CMS.md",
  "relativeUrl": "/doc/concept/cms",
  "url": "https://intlayer.org/doc/concept/cms"
}