{
  "id": "./docs/en/intlayer_with_express.md",
  "content": "---\ncreatedAt: 2025-08-23\nupdatedAt: 2025-12-30\ntitle: Express i18n - How to translate your Express app – guide 2026\ndescription: Discover how to make your Express backend multilingual. Follow the documentation to internationalize (i18n) and translate it.\nkeywords:\n  - Internationalization\n  - Documentation\n  - Intlayer\n  - Express\n  - JavaScript\n  - Backend\nslugs:\n  - doc\n  - environment\n  - express\napplicationTemplate: https://github.com/aymericzip/intlayer-express-template\nhistory:\n  - version: 7.5.9\n    date: 2025-12-30\n    changes: Add init command\n  - version: 5.5.10\n    date: 2025-06-29\n    changes: Init history\n---\n\n# Translate your Express backend website using Intlayer | Internationalization (i18n)\n\n`express-intlayer` is a powerful internationalization (i18n) middleware for Express applications, designed to make your backend services globally accessible by providing localized responses based on the client's preferences.\n\n### Practical Use Cases\n\n- **Displaying Backend Errors in User's Language**: When an error occurs, displaying messages in the user's native language improves understanding and reduces frustration. This is especially useful for dynamic error messages that might be shown in front-end components like toasts or modals.\n\n- **Retrieving Multilingual Content**: For applications pulling content from a database, internationalization ensures that you can serve this content in multiple languages. This is crucial for platforms like e-commerce sites or content management systems that need to display product descriptions, articles, and other content in the language preferred by the user.\n\n- **Sending Multilingual Emails**: Whether it's transactional emails, marketing campaigns, or notifications, sending emails in the recipient’s language can significantly increase engagement and effectiveness.\n\n- **Multilingual Push Notifications**: For mobile applications, sending push notifications in a user's preferred language can enhance interaction and retention. This personal touch can make notifications feel more relevant and actionable.\n\n- **Other Communications**: Any form of communication from the backend, such as SMS messages, system alerts, or user interface updates, benefits from being in the user's language, ensuring clarity and enhancing the overall user experience.\n\nBy internationalizing the backend, your application not only respects cultural differences but also aligns better with global market needs, making it a key step in scaling your services worldwide.\n\n## Getting Started\n\n<iframe\n  src=\"https://stackblitz.com/github/aymericzip/intlayer-express-template?embed=1&ctl=1&file=intlayer.config.ts\"\n  className=\"m-auto overflow-hidden rounded-lg border-0 max-md:size-full max-md:h-[700px] md:aspect-16/9 md:w-full\"\n  title=\"Demo CodeSandbox - How to Internationalize your application using Intlayer\"\n  sandbox=\"allow-forms allow-modals allow-popups allow-presentation allow-same-origin allow-scripts\"\n  loading=\"lazy\"\n/>\n\nSee [Application Template](https://github.com/aymericzip/intlayer-express-template) on GitHub.\n\n### Installation\n\nTo begin using `express-intlayer`, install the package using npm:\n\n```bash packageManager=\"npm\"\nnpm install intlayer express-intlayer\nnpx intlayer init\n```\n\n```bash packageManager=\"pnpm\"\npnpm add intlayer express-intlayer\npnpm intlayer init\n```\n\n```bash packageManager=\"yarn\"\nyarn add intlayer express-intlayer\nyarn intlayer init\n```\n\n```bash packageManager=\"bun\"\nbun add intlayer express-intlayer\nbunx intlayer init\n```\n\n### Setup\n\nConfigure the internationalization settings by creating an `intlayer.config.ts` in your project root:\n\n```typescript fileName=\"intlayer.config.ts\"  codeFormat=\"typescript\"\nimport { Locales, type IntlayerConfig } from \"intlayer\";\n\nconst config: IntlayerConfig = {\n  internationalization: {\n    locales: [\n      Locales.ENGLISH,\n      Locales.FRENCH,\n      Locales.SPANISH_MEXICO,\n      Locales.SPANISH_SPAIN,\n    ],\n    defaultLocale: Locales.ENGLISH,\n  },\n};\n\nexport default config;\n```\n\n```javascript fileName=\"intlayer.config.mjs\" codeFormat=\"esm\"\nimport { Locales } from \"intlayer\";\n\n/** @type {import('intlayer').IntlayerConfig} */\nconst config = {\n  internationalization: {\n    locales: [\n      Locales.ENGLISH,\n      Locales.FRENCH,\n      Locales.SPANISH_MEXICO,\n      Locales.SPANISH_SPAIN,\n    ],\n    defaultLocale: Locales.ENGLISH,\n  },\n};\n\nexport default config;\n```\n\n```javascript fileName=\"intlayer.config.cjs\" codeFormat=\"commonjs\"\nconst { Locales } = require(\"intlayer\");\n\n/** @type {import('intlayer').IntlayerConfig} */\nconst config = {\n  internationalization: {\n    locales: [\n      Locales.ENGLISH,\n      Locales.FRENCH,\n      Locales.SPANISH_MEXICO,\n      Locales.SPANISH_SPAIN,\n    ],\n    defaultLocale: Locales.ENGLISH,\n  },\n};\n\nmodule.exports = config;\n```\n\n### Declare Your Content\n\nCreate and manage your content declarations to store translations:\n\n```typescript fileName=\"src/index.content.ts\" contentDeclarationFormat=\"typescript\"\nimport { t, type Dictionary } from \"intlayer\";\n\nconst indexContent = {\n  key: \"index\",\n  content: {\n    exampleOfContent: t({\n      en: \"Example of returned content in English\",\n      fr: \"Exemple de contenu renvoyé en français\",\n      \"es-ES\": \"Ejemplo de contenido devuelto en español (España)\",\n      \"es-MX\": \"Ejemplo de contenido devuelto en español (México)\",\n    }),\n  },\n} satisfies Dictionary;\n\nexport default indexContent;\n```\n\n```javascript fileName=\"src/index.content.mjs\" contentDeclarationFormat=\"esm\"\nimport { t } from \"intlayer\";\n\n/** @type {import('intlayer').Dictionary} */\nconst indexContent = {\n  key: \"index\",\n  content: {\n    exampleOfContent: t({\n      en: \"Example of returned content in English\",\n      fr: \"Exemple de contenu renvoyé en français\",\n      \"es-ES\": \"Ejemplo de contenido devuelto en español (España)\",\n      \"es-MX\": \"Ejemplo de contenido devuelto en español (México)\",\n    }),\n  },\n};\n\nexport default indexContent;\n```\n\n```javascript fileName=\"src/index.content.cjs\" contentDeclarationFormat=\"commonjs\"\nconst { t } = require(\"intlayer\");\n\n/** @type {import('intlayer').Dictionary} */\nconst indexContent = {\n  key: \"index\",\n  content: {\n    exampleOfContent: t({\n      en: \"Example of returned content in English\",\n      fr: \"Exemple de contenu renvoyé en français\",\n      \"es-ES\": \"Ejemplo de contenido devuelto en español (España)\",\n      \"es-MX\": \"Ejemplo de contenido devuelto en español (México)\",\n    }),\n  },\n};\n\nmodule.exports = indexContent;\n```\n\n```json fileName=\"src/index.content.json\" contentDeclarationFormat=\"json\"\n{\n  \"$schema\": \"https://intlayer.org/schema.json\",\n  \"key\": \"index\",\n  \"content\": {\n    \"exampleOfContent\": {\n      \"nodeType\": \"translation\",\n      \"translation\": {\n        \"en\": \"Example of returned content in English\",\n        \"fr\": \"Exemple de contenu renvoyé en français\",\n        \"es-ES\": \"Ejemplo de contenido devuelto en español (España)\",\n        \"es-MX\": \"Ejemplo de contenido devuelto en español (México)\"\n      }\n    }\n  }\n}\n```\n\n> Your content declarations can be defined anywhere in your application as soon as they are included into the `contentDir` directory (by default, `./src`). And match the content declaration file extension (by default, `.content.{json,ts,tsx,js,jsx,mjs,cjs}`).\n\n> For more details, refer to the [content declaration documentation](https://github.com/aymericzip/intlayer/blob/main/docs/docs/en/dictionary/content_file.md).\n\n### Express Application Setup\n\nSetup your Express application to use `express-intlayer`:\n\n```typescript fileName=\"src/index.ts\" codeFormat=\"typescript\"\nimport express, { type Express } from \"express\";\nimport { intlayer, t, getDictionary, getIntlayer } from \"express-intlayer\";\nimport dictionaryExample from \"./index.content\";\n\nconst app: Express = express();\n\n// Load internationalization request handler\napp.use(intlayer());\n\n// Routes\napp.get(\"/t_example\", (_req, res) => {\n  res.send(\n    t({\n      en: \"Example of returned content in English\",\n      fr: \"Exemple de contenu renvoyé en français\",\n      \"es-ES\": \"Ejemplo de contenido devuelto en español (España)\",\n      \"es-MX\": \"Ejemplo de contenido devuelto en español (México)\",\n    })\n  );\n});\n\napp.get(\"/getIntlayer_example\", (_req, res) => {\n  res.send(getIntlayer(\"index\").exampleOfContent);\n});\n\napp.get(\"/getDictionary_example\", (_req, res) => {\n  res.send(getDictionary(dictionaryExample).exampleOfContent);\n});\n\n// Start server\napp.listen(3000, () => console.log(`Listening on port 3000`));\n```\n\n```javascript fileName=\"src/index.mjs\" codeFormat=\"esm\"\nimport express from \"express\";\nimport { intlayer, t, getDictionary, getIntlayer } from \"express-intlayer\";\nimport dictionaryExample from \"./index.content\";\n\nconst app = express();\n\n// Load internationalization request handler\napp.use(intlayer());\n\n// Routes\napp.get(\"/t_example\", (_req, res) => {\n  res.send(\n    t({\n      en: \"Example of returned content in English\",\n      fr: \"Exemple de contenu renvoyé en français\",\n      \"es-ES\": \"Ejemplo de contenido devuelto en español (España)\",\n      \"es-MX\": \"Ejemplo de contenido devuelto en español (México)\",\n    })\n  );\n});\n\napp.get(\"/getIntlayer_example\", (_req, res) => {\n  res.send(getIntlayer(\"index\").exampleOfContent);\n});\n\napp.get(\"/getDictionary_example\", (_req, res) => {\n  res.send(getDictionary(dictionaryExample).exampleOfContent);\n});\n\n// Start server\napp.listen(3000, () => console.log(`Listening on port 3000`));\n```\n\n```javascript fileName=\"src/index.cjs\" codeFormat=\"commonjs\"\nconst express = require(\"express\");\nconst { intlayer, t, getDictionary, getIntlayer } = require(\"express-intlayer\");\nconst dictionaryExample = require(\"./index.content\");\n\nconst app = express();\n\n// Load internationalization request handler\napp.use(intlayer());\n\n// Routes\napp.get(\"/t_example\", (_req, res) => {\n  res.send(\n    t({\n      en: \"Example of returned content in English\",\n      fr: \"Exemple de contenu renvoyé en français\",\n      \"es-ES\": \"Ejemplo de contenido devuelto en español (España)\",\n      \"es-MX\": \"Ejemplo de contenido devuelto en español (México)\",\n    })\n  );\n});\n\napp.get(\"/getIntlayer_example\", (_req, res) => {\n  res.send(getIntlayer(\"index\").exampleOfContent);\n});\n\napp.get(\"/getDictionary_example\", (_req, res) => {\n  res.send(getDictionary(dictionaryExample).exampleOfContent);\n});\n\n// Start server\napp.listen(3000, () => console.log(`Listening on port 3000`));\n```\n\n### Compatibility\n\n`express-intlayer` is fully compatible with:\n\n- [`react-intlayer`](https://github.com/aymericzip/intlayer/blob/main/docs/docs/en/packages/react-intlayer/index.md) for React applications\n- [`next-intlayer`](https://github.com/aymericzip/intlayer/blob/main/docs/docs/en/packages/next-intlayer/index.md) for Next.js applications\n- [`vite-intlayer`](https://github.com/aymericzip/intlayer/blob/main/docs/docs/en/packages/vite-intlayer/index.md) for Vite applications\n\nIt also works seamlessly with any internationalization solution across various environments, including browsers and API requests. You can customize the middleware to detect locale through headers or cookies:\n\n```typescript fileName=\"intlayer.config.ts\" codeFormat=\"typescript\"\nimport { Locales, type IntlayerConfig } from \"intlayer\";\n\nconst config: IntlayerConfig = {\n  // ... Other configuration options\n  middleware: {\n    headerName: \"my-locale-header\",\n    cookieName: \"my-locale-cookie\",\n  },\n};\n\nexport default config;\n```\n\n```javascript fileName=\"intlayer.config.mjs\" codeFormat=\"esm\"\nimport { Locales } from \"intlayer\";\n\n/** @type {import('intlayer').IntlayerConfig} */\nconst config = {\n  // ... Other configuration options\n  middleware: {\n    headerName: \"my-locale-header\",\n    cookieName: \"my-locale-cookie\",\n  },\n};\n\nexport default config;\n```\n\n```javascript fileName=\"intlayer.config.cjs\" codeFormat=\"commonjs\"\nconst { Locales } = require(\"intlayer\");\n\n/** @type {import('intlayer').IntlayerConfig} */\nconst config = {\n  // ... Other configuration options\n  middleware: {\n    headerName: \"my-locale-header\",\n    cookieName: \"my-locale-cookie\",\n  },\n};\n\nmodule.exports = config;\n```\n\nBy default, `express-intlayer` will interpret the `Accept-Language` header to determine the client's preferred language.\n\n> For more information on configuration and advanced topics, visit our [documentation](https://github.com/aymericzip/intlayer/blob/main/docs/docs/en/configuration.md).\n\n### Configure TypeScript\n\n`express-intlayer` leverages the robust capabilities of TypeScript to enhance the internationalization process. TypeScript's static typing ensures that every translation key is accounted for, reducing the risk of missing translations and improving maintainability.\n\n![Autocompletion](https://github.com/aymericzip/intlayer/blob/main/docs/assets/autocompletion.png?raw=true)\n\n![Translation error](https://github.com/aymericzip/intlayer/blob/main/docs/assets/translation_error.png?raw=true)\n\nEnsure the autogenerated types (by default at ./types/intlayer.d.ts) are included in your tsconfig.json file.\n\n```json5 fileName=\"tsconfig.json\"\n{\n  // ... Your existing TypeScript configurations\n  \"include\": [\n    // ... Your existing TypeScript configurations\n    \".intlayer/**/*.ts\", // Include the auto-generated types\n  ],\n}\n```\n\n### VS Code Extension\n\nTo improve your development experience with Intlayer, you can install the official **Intlayer VS Code Extension**.\n\n[Install from the VS Code Marketplace](https://marketplace.visualstudio.com/items?itemName=intlayer.intlayer-vs-code-extension)\n\nThis extension provides:\n\n- **Autocompletion** for translation keys.\n- **Real-time error detection** for missing translations.\n- **Inline previews** of translated content.\n- **Quick actions** to easily create and update translations.\n\nFor more details on how to use the extension, refer to the [Intlayer VS Code Extension documentation](https://intlayer.org/doc/vs-code-extension).\n\n### Git Configuration\n\nIt is recommended to ignore the files generated by Intlayer. This allows you to avoid committing them to your Git repository.\n\nTo do this, you can add the following instructions to your `.gitignore` file:\n\n```plaintext fileName=\".gitignore\"\n# Ignore the files generated by Intlayer\n.intlayer\n```\n",
  "createdAt": "2025-08-23",
  "updatedAt": "2025-12-30",
  "title": "Express i18n - How to translate your Express app – guide 2026",
  "description": "Discover how to make your Express backend multilingual. Follow the documentation to internationalize (i18n) and translate it.",
  "keywords": [
    "Internationalization",
    "Documentation",
    "Intlayer",
    "Express",
    "JavaScript",
    "Backend"
  ],
  "slugs": [
    "doc",
    "environment",
    "express"
  ],
  "applicationTemplate": "https://github.com/aymericzip/intlayer-express-template",
  "history": [
    {
      "version": "7.5.9",
      "date": "2025-12-30",
      "changes": "Add init command"
    },
    {
      "version": "5.5.10",
      "date": "2025-06-29",
      "changes": "Init history"
    }
  ],
  "docKey": "./docs/en/intlayer_with_express.md",
  "githubUrl": "https://github.com/aymericzip/intlayer/blob/main/docs/docs/en/intlayer_with_express.md",
  "relativeUrl": "/doc/environment/express",
  "url": "https://intlayer.org/doc/environment/express"
}