{
  "id": "./docs/en/packages/solid-intlayer/useRewriteURL.md",
  "content": "---\nupdatedAt: 2025-08-23\ncreatedAt: 2025-08-23\ntitle: useRewriteURL Hook Documentation\ndescription: Solid-specific hook for managing localized URL rewrites in Intlayer.\nkeywords:\n  - useRewriteURL\n  - solid-intlayer\n  - solidjs\n  - internationalization\n  - i18n\nslugs:\n  - doc\n  - packages\n  - solid-intlayer\n  - useRewriteURL\n---\n\n# useRewriteURL Hook\n\nThe `useRewriteURL` hook for SolidJS is designed to manage localized URL rewrites on the client side. It automatically corrects the browser's URL to its \"pretty\" localized version based on the current locale and the configuration in `intlayer.config.ts`.\n\nBy using `window.history.replaceState`, it avoids redundant Solid Router navigations.\n\n## Usage\n\nCall the hook within a component that is part of your application.\n\n```tsx\nimport { useRewriteURL } from \"solid-intlayer\";\n\nconst Layout = (props) => {\n  // Automatically correct /fr/tests to /fr/essais in the address bar if a rewrite rule exists\n  useRewriteURL();\n\n  return <>{props.children}</>;\n};\n```\n\n## How it works\n\n1. **Detection**: The hook uses `createEffect` to monitor changes in the reactive `locale()`.\n2. **Matching**: It identifies if the current `window.location.pathname` corresponds to a canonical route that has a prettier localized alias for the current language.\n3. **URL Correction**: If a prettier alias is found, the hook calls `window.history.replaceState` to update the address bar without affecting the internal navigation state or causing component re-renders.\n\n## Why use it?\n\n- **Authoritative URLs**: Enforces a single URL for each localized version of your content, which is crucial for SEO.\n- **Developer Convenience**: Allows you to keep your internal route definitions canonical while exposing user-friendly, localized paths to the outside world.\n- **Consistency**: Corrects URLs when users manually type a path that doesn't follow your preferred localization rules.\n\n---\n",
  "updatedAt": "2025-08-23",
  "createdAt": "2025-08-23",
  "title": "useRewriteURL Hook Documentation",
  "description": "Solid-specific hook for managing localized URL rewrites in Intlayer.",
  "keywords": [
    "useRewriteURL",
    "solid-intlayer",
    "solidjs",
    "internationalization",
    "i18n"
  ],
  "slugs": [
    "doc",
    "packages",
    "solid-intlayer",
    "useRewriteURL"
  ],
  "docKey": "./docs/en/packages/solid-intlayer/useRewriteURL.md",
  "githubUrl": "https://github.com/aymericzip/intlayer/blob/main/docs/docs/en/packages/solid-intlayer/useRewriteURL.md",
  "relativeUrl": "/doc/packages/solid-intlayer/useRewriteURL",
  "url": "https://intlayer.org/doc/packages/solid-intlayer/useRewriteURL"
}