{
  "id": "./docs/en/packages/express-intlayer/exports.md",
  "content": "---\ncreatedAt: 2026-01-21\nupdatedAt: 2026-01-21\ntitle: express-intlayer Package Documentation\ndescription: Express middleware for Intlayer, providing translation functions and locale detection.\nkeywords:\n  - express-intlayer\n  - express\n  - middleware\n  - internationalization\n  - i18n\nslugs:\n  - doc\n  - packages\n  - express-intlayer\n  - exports\nhistory:\n  - version: 8.0.0\n    date: 2026-01-21\n    changes: Unified documentation for all exports\n---\n\n# express-intlayer Package\n\nThe `express-intlayer` package provides a middleware for Express applications to handle internationalization. It detects the user's locale and provides translation functions.\n\n## Installation\n\n```bash\nnpm install express-intlayer\n```\n\n## Exports\n\n### Middleware\n\nImport:\n\n```tsx\nimport \"express-intlayer\";\n```\n\n| Function   | Description                                                                                                                                                                                                                                                                 | Related Doc                                                                                                     |\n| ---------- | --------------------------------------------------------------------------------------------------------------------------------------------------------------------------------------------------------------------------------------------------------------------------- | --------------------------------------------------------------------------------------------------------------- |\n| `intlayer` | Express middleware that detects the user's locale and populates `res.locals` with Intlayer data. Performs locale detection from cookies/headers, injects `t`, `getIntlayer`, and `getDictionary` into `res.locals`, and sets up CLS namespace for request lifecycle access. | [intlayer](https://github.com/aymericzip/intlayer/blob/main/docs/docs/en/packages/express-intlayer/intlayer.md) |\n\n### Functions\n\nImport:\n\n```tsx\nimport \"express-intlayer\";\n```\n\n| Function        | Description                                                                                                                                                                                            | Related Doc                                                                                            |\n| --------------- | ------------------------------------------------------------------------------------------------------------------------------------------------------------------------------------------------------ | ------------------------------------------------------------------------------------------------------ |\n| `t`             | Translation function that retrieves content for the current locale. Works within the request lifecycle managed by the `intlayer` middleware. Uses CLS (Async Local Storage) to access request context. | [translation](https://github.com/aymericzip/intlayer/blob/main/docs/docs/en/dictionary/translation.md) |\n| `getIntlayer`   | Retrieves a dictionary by its key from the generated declaration and returns its content for the specified locale. Optimized version of `getDictionary`. Uses CLS to access request context.           | -                                                                                                      |\n| `getDictionary` | Processes dictionary objects and returns content for the specified locale. Processes `t()` translations, enumerations, markdown, HTML, etc. Uses CLS to access request context.                        | -                                                                                                      |\n",
  "createdAt": "2026-01-21",
  "updatedAt": "2026-01-21",
  "title": "express-intlayer Package Documentation",
  "description": "Express middleware for Intlayer, providing translation functions and locale detection.",
  "keywords": [
    "express-intlayer",
    "express",
    "middleware",
    "internationalization",
    "i18n"
  ],
  "slugs": [
    "doc",
    "packages",
    "express-intlayer",
    "exports"
  ],
  "history": [
    {
      "version": "8.0.0",
      "date": "2026-01-21",
      "changes": "Unified documentation for all exports"
    }
  ],
  "docKey": "./docs/en/packages/express-intlayer/exports.md",
  "githubUrl": "https://github.com/aymericzip/intlayer/blob/main/docs/docs/en/packages/express-intlayer/exports.md",
  "relativeUrl": "/doc/packages/express-intlayer/exports",
  "url": "https://intlayer.org/doc/packages/express-intlayer/exports"
}