{
  "id": "./docs/en/packages/intlayer/getLocaleLang.md",
  "content": "---\ncreatedAt: 2025-08-23\nupdatedAt: 2025-08-23\ntitle: getLocaleLang Function Documentation | intlayer\ndescription: See how to use the getLocaleLang function for intlayer package\nkeywords:\n  - getLocaleLang\n  - translation\n  - Intlayer\n  - intlayer\n  - Internationalization\n  - Documentation\n  - Next.js\n  - JavaScript\n  - React\nslugs:\n  - doc\n  - packages\n  - intlayer\n  - getLocaleLang\nhistory:\n  - version: 5.5.10\n    date: 2025-06-29\n    changes: Init history\n---\n\n# Documentation: `getLocaleLang` Function in `intlayer`\n\n## Description\n\nThe `getLocaleLang` function extracts the language code from a locale string. It supports locales with or without country codes. If no locale is provided, it defaults to returning an empty string.\n\n## Parameters\n\n- `locale?: Locales`\n  - **Description**: The locale string (e.g., `Locales.ENGLISH_UNITED_STATES`, `Locales.FRENCH_CANADA`) from which the language code is extracted.\n  - **Type**: `Locales` (optional)\n\n## Returns\n\n- **Type**: `string`\n- **Description**: The language code extracted from the locale. If the locale is not provided, it returns an empty string (`''`).\n\n## Example Usage\n\n### Extracting Language Codes:\n\n```typescript codeFormat=\"typescript\"\nimport { getLocaleLang, Locales } from \"intlayer\";\n\ngetLocaleLang(Locales.ENGLISH_UNITED_STATES); // Output: \"en\"\ngetLocaleLang(Locales.ENGLISH); // Output: \"en\"\ngetLocaleLang(Locales.FRENCH_CANADA); // Output: \"fr\"\ngetLocaleLang(Locales.FRENCH); // Output: \"fr\"\n```\n\n```javascript codeFormat=\"esm\"\nimport { getLocaleLang } from \"intlayer\";\n\ngetLocaleLang(Locales.ENGLISH_UNITED_STATES); // Output: \"en\"\ngetLocaleLang(Locales.ENGLISH); // Output: \"en\"\ngetLocaleLang(Locales.FRENCH_CANADA); // Output: \"fr\"\ngetLocaleLang(Locales.FRENCH); // Output: \"fr\"\n```\n\n```javascript codeFormat=\"commonjs\"\nconst { getLocaleLang } = require(\"intlayer\");\n\ngetLocaleLang(Locales.ENGLISH_UNITED_STATES); // Output: \"en\"\ngetLocaleLang(Locales.ENGLISH); // Output: \"en\"\ngetLocaleLang(Locales.FRENCH_CANADA); // Output: \"fr\"\ngetLocaleLang(Locales.FRENCH); // Output: \"fr\"\n```\n\n## Edge Cases\n\n- **No Locale Provided:**\n  - The function returns an empty string when `locale` is `undefined`.\n\n- **Malformed Locale Strings:**\n  - If the `locale` does not follow the `language-country` format (e.g., `Locales.ENGLISH-US`), the function safely returns the part before `'-'` or the entire string if no `'-'` is present.\n",
  "createdAt": "2025-08-23",
  "updatedAt": "2025-08-23",
  "title": "getLocaleLang Function Documentation | intlayer",
  "description": "See how to use the getLocaleLang function for intlayer package",
  "keywords": [
    "getLocaleLang",
    "translation",
    "Intlayer",
    "intlayer",
    "Internationalization",
    "Documentation",
    "Next.js",
    "JavaScript",
    "React"
  ],
  "slugs": [
    "doc",
    "packages",
    "intlayer",
    "getLocaleLang"
  ],
  "history": [
    {
      "version": "5.5.10",
      "date": "2025-06-29",
      "changes": "Init history"
    }
  ],
  "docKey": "./docs/en/packages/intlayer/getLocaleLang.md",
  "githubUrl": "https://github.com/aymericzip/intlayer/blob/main/docs/docs/en/packages/intlayer/getLocaleLang.md",
  "relativeUrl": "/doc/packages/intlayer/getLocaleLang",
  "url": "https://intlayer.org/doc/packages/intlayer/getLocaleLang"
}