{
  "id": "./docs/en/packages/fastify-intlayer/intlayer.md",
  "content": "---\ncreatedAt: 2026-01-21\nupdatedAt: 2026-01-21\ntitle: intlayer Fastify Plugin Documentation | fastify-intlayer\ndescription: See how to use the intlayer plugin for fastify-intlayer package\nkeywords:\n  - intlayer\n  - fastify\n  - plugin\n  - Intlayer\n  - intlayer\n  - Internationalization\n  - Documentation\nslugs:\n  - doc\n  - packages\n  - fastify-intlayer\n  - intlayer\nhistory:\n  - version: 8.0.0\n    date: 2026-01-21\n    changes: Init doc\n---\n\n# intlayer Fastify Plugin Documentation\n\nThe `intlayer` plugin for Fastify detects the user's locale and decorates the request object with Intlayer functions. It also enables the use of global translation functions within the request context.\n\n## Usage\n\n```ts\nimport Fastify from \"fastify\";\nimport { intlayer } from \"fastify-intlayer\";\n\nconst fastify = Fastify();\n\nfastify.register(intlayer);\n\nfastify.get(\"/\", async (req, reply) => {\n  const content = req.intlayer.t({\n    en: \"Hello\",\n    fr: \"Bonjour\",\n  });\n\n  return content;\n});\n```\n\n## Description\n\nThe plugin performs the following tasks:\n\n1. **Locale Detection**: It analyzes the request (headers, cookies, etc.) to determine the user's preferred locale.\n2. **Request Decoration**: It adds an `intlayer` property to the `FastifyRequest` object, containing:\n   - `locale`: The detected locale.\n   - `t`: A translation function.\n   - `getIntlayer`: A function to retrieve dictionaries.\n3. **Context Management**: It uses `cls-hooked` to manage an asynchronous context, allowing global Intlayer functions to access the request-specific locale.\n",
  "createdAt": "2026-01-21",
  "updatedAt": "2026-01-21",
  "title": "intlayer Fastify Plugin Documentation | fastify-intlayer",
  "description": "See how to use the intlayer plugin for fastify-intlayer package",
  "keywords": [
    "intlayer",
    "fastify",
    "plugin",
    "Intlayer",
    "intlayer",
    "Internationalization",
    "Documentation"
  ],
  "slugs": [
    "doc",
    "packages",
    "fastify-intlayer",
    "intlayer"
  ],
  "history": [
    {
      "version": "8.0.0",
      "date": "2026-01-21",
      "changes": "Init doc"
    }
  ],
  "docKey": "./docs/en/packages/fastify-intlayer/intlayer.md",
  "githubUrl": "https://github.com/aymericzip/intlayer/blob/main/docs/docs/en/packages/fastify-intlayer/intlayer.md",
  "relativeUrl": "/doc/packages/fastify-intlayer/intlayer",
  "url": "https://intlayer.org/doc/packages/fastify-intlayer/intlayer"
}