{
  "id": "./docs/en/packages/hono-intlayer/intlayer.md",
  "content": "---\ncreatedAt: 2026-01-29\nupdatedAt: 2026-01-29\ntitle: intlayer Hono Middleware Documentation | hono-intlayer\ndescription: See how to use the intlayer middleware for hono-intlayer package\nkeywords:\n  - intlayer\n  - hono\n  - middleware\n  - Intlayer\n  - Internationalization\n  - Documentation\nslugs:\n  - doc\n  - packages\n  - hono-intlayer\n  - intlayer\nhistory:\n  - version: 8.0.0\n    date: 2026-01-29\n    changes: Init doc\n---\n\n# intlayer Hono Middleware Documentation\n\nThe `intlayer` middleware for Hono detects the user's locale and populates the context object with Intlayer functions. It also enables the use of global translation functions within the request context.\n\n## Usage\n\n```ts\nimport { Hono } from \"hono\";\nimport { intlayer } from \"hono-intlayer\";\n\nconst app = new Hono();\n\napp.use(\"*\", intlayer());\n\napp.get(\"/\", async (c) => {\n  const t = c.get(\"t\");\n  const content = t({\n    en: \"Hello\",\n    fr: \"Bonjour\",\n  });\n\n  return c.text(content);\n});\n```\n\n## Description\n\nThe middleware performs the following tasks:\n\n1. **Locale Detection**: It analyzes the request (headers, cookies, etc.) to determine the user's preferred locale.\n2. **Context Population**: It adds Intlayer data to the Hono context, accessible via `c.get()`. This includes:\n   - `locale`: The detected locale.\n   - `t`: A translation function.\n   - `getIntlayer`: A function to retrieve dictionaries.\n   - `getDictionary`: A function to process dictionary objects.\n3. **Context Management**: It uses `cls-hooked` to manage an asynchronous context, allowing global Intlayer functions (`t`, `getIntlayer`, `getDictionary`) to access the request-specific locale without passing the context object.\n",
  "createdAt": "2026-01-29",
  "updatedAt": "2026-01-29",
  "title": "intlayer Hono Middleware Documentation | hono-intlayer",
  "description": "See how to use the intlayer middleware for hono-intlayer package",
  "keywords": [
    "intlayer",
    "hono",
    "middleware",
    "Intlayer",
    "Internationalization",
    "Documentation"
  ],
  "slugs": [
    "doc",
    "packages",
    "hono-intlayer",
    "intlayer"
  ],
  "history": [
    {
      "version": "8.0.0",
      "date": "2026-01-29",
      "changes": "Init doc"
    }
  ],
  "docKey": "./docs/en/packages/hono-intlayer/intlayer.md",
  "githubUrl": "https://github.com/aymericzip/intlayer/blob/main/docs/docs/en/packages/hono-intlayer/intlayer.md",
  "relativeUrl": "/doc/packages/hono-intlayer/intlayer",
  "url": "https://intlayer.org/doc/packages/hono-intlayer/intlayer"
}