{
  "id": "./docs/en/packages/next-intlayer.md",
  "content": "---\ncreatedAt: 2026-01-21\nupdatedAt: 2026-01-21\ntitle: next-intlayer Package Documentation\ndescription: Next.js-specific integration for Intlayer, providing middleware and providers for App Router and Page Router.\nkeywords:\n  - next-intlayer\n  - nextjs\n  - react\n  - internationalization\n  - i18n\nslugs:\n  - doc\n  - packages\n  - next-intlayer\nhistory:\n  - version: 8.0.0\n    date: 2026-01-21\n    changes: Unified documentation for all exports\n---\n\n# next-intlayer Package\n\nThe `next-intlayer` package provides the necessary tools to integrate Intlayer into Next.js applications. It supports both the App Router and the Page Router, including middleware for locale-based routing.\n\n## Installation\n\n```bash\nnpm install next-intlayer\n```\n\n## Exports\n\n### Middleware\n\n| Function             | Description                                                      |\n| -------------------- | ---------------------------------------------------------------- |\n| `intlayerMiddleware` | Next.js middleware to handle locale-based routing and redirects. |\n\n### Providers\n\n| Component                | Description                                                  |\n| ------------------------ | ------------------------------------------------------------ |\n| `IntlayerClientProvider` | Provider for client-side components in Next.js.              |\n| `IntlayerServerProvider` | Provider for server-side components in Next.js (App Router). |\n\n### Hooks (Client-side)\n\nRe-exports most hooks from `react-intlayer`.\n\n| Hook            | Description                                              |\n| --------------- | -------------------------------------------------------- |\n| `useIntlayer`   | Picks one dictionary by its key and returns the content. |\n| `useDictionary` | Picks one dictionary by its key and returns the content. |\n| `useLocale`     | Returns the current locale and a function to set it.     |\n| `useI18n`       | Returns the current Intlayer context values.             |\n\n### Functions (Server-side)\n\n| Function               | Description                                                             |\n| ---------------------- | ----------------------------------------------------------------------- |\n| `t`                    | Server-side version of the translation function for Next.js App Router. |\n| `generateStaticParams` | Generates static parameters for Next.js's dynamic routes.               |\n\n### Types\n\n| Type                 | Description                                     |\n| -------------------- | ----------------------------------------------- |\n| `NextPageIntlayer`   | Type for Next.js pages with Intlayer support.   |\n| `NextLayoutIntlayer` | Type for Next.js layouts with Intlayer support. |\n",
  "createdAt": "2026-01-21",
  "updatedAt": "2026-01-21",
  "title": "next-intlayer Package Documentation",
  "description": "Next.js-specific integration for Intlayer, providing middleware and providers for App Router and Page Router.",
  "keywords": [
    "next-intlayer",
    "nextjs",
    "react",
    "internationalization",
    "i18n"
  ],
  "slugs": [
    "doc",
    "packages",
    "next-intlayer"
  ],
  "history": [
    {
      "version": "8.0.0",
      "date": "2026-01-21",
      "changes": "Unified documentation for all exports"
    }
  ],
  "docKey": "./docs/en/packages/next-intlayer.md",
  "githubUrl": "https://github.com/aymericzip/intlayer/blob/main/docs/docs/en/packages/next-intlayer.md",
  "relativeUrl": "/doc/packages/next-intlayer",
  "url": "https://intlayer.org/doc/packages/next-intlayer"
}