{
  "id": "./docs/en/packages/next-intlayer/useRewriteURL.md",
  "content": "---\nupdatedAt: 2025-08-23\ncreatedAt: 2025-08-23\ntitle: useRewriteURL Hook Documentation\ndescription: Next.js-specific hook for managing localized URL rewrites in Intlayer.\nkeywords:\n  - useRewriteURL\n  - next-intlayer\n  - nextjs\n  - internationalization\n  - i18n\nslugs:\n  - doc\n  - packages\n  - next-intlayer\n  - useRewriteURL\n---\n\n# useRewriteURL Hook\n\nThe `useRewriteURL` hook for Next.js is a client-side hook that automatically manages localized URL rewrites. It ensures that the browser URL always reflects the \"pretty\" localized path defined in your `intlayer.config.ts`, even if the user manually types a canonical path with a locale prefix.\n\nThis hook works silently by using `window.history.replaceState`, avoiding redundant Next.js router navigations or page refreshes.\n\n## Usage\n\nSimply call the hook in a Client Component that is part of your layout.\n\n```tsx\n\"use client\";\n\nimport { useRewriteURL } from \"next-intlayer\";\n\nconst MyClientComponent = () => {\n  // Automatically correct /fr/privacy-notice to /fr/politique-de-confidentialite in the address bar\n  useRewriteURL();\n\n  return null;\n};\n```\n\n## How it works\n\n1. **Path Monitoring**: The hook listens for changes in the user's `locale`.\n2. **Rewrite Detection**: It checks the current `window.location.pathname` against the rewrite rules in your configuration.\n3. **URL Correction**: If a prettier localized alias is found for the current path, the hook triggers a `window.history.replaceState` to update the address bar while keeping the user on the same internal page.\n\n## Why use it in Next.js?\n\nWhile the `intlayerMiddleware` handles server-side rewrites and initial redirects, the `useRewriteURL` hook ensures that the browser URL stays consistent with your preferred SEO structure even after client-side transitions.\n\n- **Clean URLs**: Enforces the use of localized segments like `/fr/essais` instead of `/fr/tests`.\n- **Performance**: Updates the address bar without triggering a full router cycle or re-fetching data.\n- **SEO Alignment**: Prevents duplicate content issues by ensuring only one URL version is visible to the user and search engine bots.\n",
  "updatedAt": "2025-08-23",
  "createdAt": "2025-08-23",
  "title": "useRewriteURL Hook Documentation",
  "description": "Next.js-specific hook for managing localized URL rewrites in Intlayer.",
  "keywords": [
    "useRewriteURL",
    "next-intlayer",
    "nextjs",
    "internationalization",
    "i18n"
  ],
  "slugs": [
    "doc",
    "packages",
    "next-intlayer",
    "useRewriteURL"
  ],
  "docKey": "./docs/en/packages/next-intlayer/useRewriteURL.md",
  "githubUrl": "https://github.com/aymericzip/intlayer/blob/main/docs/docs/en/packages/next-intlayer/useRewriteURL.md",
  "relativeUrl": "/doc/packages/next-intlayer/useRewriteURL",
  "url": "https://intlayer.org/doc/packages/next-intlayer/useRewriteURL"
}