{
  "id": "./docs/en/packages/intlayer/getEnumeration.md",
  "content": "---\ncreatedAt: 2025-08-23\nupdatedAt: 2025-08-23\ntitle: getEnumeration Function Documentation | intlayer\ndescription: See how to use the getEnumeration function for intlayer package\nkeywords:\n  - getEnumeration\n  - translation\n  - Intlayer\n  - intlayer\n  - Internationalization\n  - Documentation\n  - Next.js\n  - JavaScript\n  - React\nslugs:\n  - doc\n  - packages\n  - intlayer\n  - getEnumeration\nhistory:\n  - version: 5.5.10\n    date: 2025-06-29\n    changes: Init history\n---\n\n# Documentation: `getEnumeration` Function in `intlayer`\n\n## Description\n\nThe `getEnumeration` function (also aliased as `enu`) retrieves content corresponding to a specific quantity based on predefined conditions in an enumeration object. The conditions are defined as keys, and their priority is determined by their order in the object.\n\nFor more details on how to declare enumerations, see the [Enumeration documentation](https://github.com/aymericzip/intlayer/blob/main/docs/docs/en/dictionary/enumeration.md).\n\n## Parameters\n\n- `enumerationContent: QuantityContent<Content>`\n  - **Description**: An object where keys represent conditions (e.g., `<=`, `<`, `>=`, `=`) and values represent the corresponding content. The order of keys defines their matching priority.\n  - **Type**: `QuantityContent<Content>`\n    - `Content` can be any type.\n\n- `quantity: number`\n  - **Description**: The numeric value used to match against the conditions in `enumerationContent`.\n  - **Type**: `number`\n\n## Returns\n\n- **Type**: `Content`\n- **Description**: The content corresponding to the first matching condition in the `enumerationContent`. If no match is found, it defaults to handling based on the implementation (e.g., error or fallback content).\n\n## Example Usage\n\n### Basic Usage\n\n```typescript codeFormat=\"typescript\"\nimport { getEnumeration } from \"intlayer\";\n\nconst content = getEnumeration(\n  {\n    \"<=-2.3\": \"You have less than -2.3\",\n    \"<1\": \"You have less than one\",\n    \"2\": \"You have two\",\n    \">=3\": \"You have three or more\",\n  },\n  2\n);\n\nconsole.log(content); // Output: \"You have two\"\n```\n\n```javascript codeFormat=\"esm\"\nimport { getEnumeration } from \"intlayer\";\n\nconst content = getEnumeration(\n  {\n    \"<1\": \"You have less than one\",\n    \"2\": \"You have two\",\n    \">=3\": \"You have three or more\",\n  },\n  2\n);\n\nconsole.log(content); // Output: \"You have two\"\n```\n\n```javascript codeFormat=\"commonjs\"\nconst { getEnumeration } = require(\"intlayer\");\n\nconst content = getEnumeration(\n  {\n    \"<1\": \"You have less than one\",\n    \"2\": \"You have two\",\n    \">=3\": \"You have three or more\",\n  },\n  2\n);\n\nconsole.log(content); // Output: \"You have two\"\n```\n\n### Priority of Conditions\n\n```typescript codeFormat=\"typescript\"\nimport { getEnumeration } from \"intlayer\";\n\nconst content = getEnumeration(\n  {\n    \"<4\": \"You have less than four\",\n    \"2\": \"You have two\",\n  },\n  2\n);\n\nconsole.log(content); // Output: \"You have less than four\"\n```\n\n```javascript codeFormat=\"esm\"\nimport { getEnumeration } from \"intlayer\";\n\nconst content = getEnumeration(\n  {\n    \"<4\": \"You have less than four\",\n    \"2\": \"You have two\",\n  },\n  2\n);\n\nconsole.log(content); // Output: \"You have less than four\"\n```\n\n```javascript codeFormat=\"commonjs\"\nconst { getEnumeration } = require(\"intlayer\");\n\nconst content = getEnumeration(\n  {\n    \"<4\": \"You have less than four\",\n    \"2\": \"You have two\",\n  },\n  2\n);\n\nconsole.log(content); // Output: \"You have less than four\"\n```\n\n## Edge Cases\n\n- **No Matching Condition:**\n  - If no condition matches the provided quantity, the function will either return `undefined` or handle the default/fallback scenario explicitly.\n\n- **Ambiguous Conditions:**\n  - If conditions overlap, the first matching condition (based on object order) takes precedence.\n\n- **Invalid Keys:**\n  - The function assumes that all keys in `enumerationContent` are valid and parsable as conditions. Invalid or improperly formatted keys may lead to unexpected behavior.\n\n- **TypeScript Enforcement:**\n  - The function ensures that the `Content` type is consistent across all keys, allowing for type safety in the retrieved content.\n\n## Notes\n\n- The `findMatchingCondition` utility is used to determine the appropriate condition based on the given quantity.\n",
  "createdAt": "2025-08-23",
  "updatedAt": "2025-08-23",
  "title": "getEnumeration Function Documentation | intlayer",
  "description": "See how to use the getEnumeration function for intlayer package",
  "keywords": [
    "getEnumeration",
    "translation",
    "Intlayer",
    "intlayer",
    "Internationalization",
    "Documentation",
    "Next.js",
    "JavaScript",
    "React"
  ],
  "slugs": [
    "doc",
    "packages",
    "intlayer",
    "getEnumeration"
  ],
  "history": [
    {
      "version": "5.5.10",
      "date": "2025-06-29",
      "changes": "Init history"
    }
  ],
  "docKey": "./docs/en/packages/intlayer/getEnumeration.md",
  "githubUrl": "https://github.com/aymericzip/intlayer/blob/main/docs/docs/en/packages/intlayer/getEnumeration.md",
  "relativeUrl": "/doc/packages/intlayer/getEnumeration",
  "url": "https://intlayer.org/doc/packages/intlayer/getEnumeration"
}