{
  "id": "./docs/en/packages/react-intlayer/exports.md",
  "content": "---\ncreatedAt: 2026-01-21\nupdatedAt: 2026-01-21\ntitle: react-intlayer Package Documentation\ndescription: React-specific implementation of Intlayer, providing hooks and providers for React applications.\nkeywords:\n  - react-intlayer\n  - react\n  - internationalization\n  - i18n\nslugs:\n  - doc\n  - packages\n  - react-intlayer\n  - exports\nhistory:\n  - version: 7.5.14\n    date: 2026-01-21\n    changes: Unified documentation for all exports\n---\n\n# react-intlayer Package\n\nThe `react-intlayer` package provides the necessary tools to integrate Intlayer into React applications. It includes context providers, hooks, and components for handling multilingual content.\n\n## Installation\n\n```bash\nnpm install react-intlayer\n```\n\n## Exports\n\n### Providers\n\nImport:\n\n```tsx\nimport \"react-intlayer\";\n```\n\n| Component                 | Description                                                                                                          | Related Doc                                                                                                                   |\n| ------------------------- | -------------------------------------------------------------------------------------------------------------------- | ----------------------------------------------------------------------------------------------------------------------------- |\n| `IntlayerProvider`        | The main provider that wraps your application and provides the Intlayer context. Includes editor support by default. | [IntlayerProvider](https://github.com/aymericzip/intlayer/blob/main/docs/docs/en/packages/react-intlayer/IntlayerProvider.md) |\n| `IntlayerProviderContent` | A provider component focused on content without the editor features. Use this when you don't need the visual editor. | -                                                                                                                             |\n| `HTMLProvider`            | Provider for HTML-related internationalization settings. Allows component overrides for HTML tags.                   | -                                                                                                                             |\n\n### Hooks\n\nImport:\n\n```tsx\nimport \"react-intlayer\";\n```\n\n| Hook                   | Description                                                                                                                               | Related Doc                                                                                                             |\n| ---------------------- | ----------------------------------------------------------------------------------------------------------------------------------------- | ----------------------------------------------------------------------------------------------------------------------- |\n| `useHTMLRenderer`      | Hook to get a pre-configured HTML renderer function.                                                                                      | -                                                                                                                       |\n| `useMarkdownRenderer`  | Hook to get a pre-configured Markdown renderer function.                                                                                  | -                                                                                                                       |\n| `useIntlayer`          | Client-side hook that picks one dictionary by its key and returns its content. Uses the locale from context if not provided.              | [useIntlayer](https://github.com/aymericzip/intlayer/blob/main/docs/docs/en/packages/react-intlayer/useIntlayer.md)     |\n| `useDictionary`        | Hook that transforms a dictionary object and returns the content for the current locale. Processes `t()` translations, enumerations, etc. | [useDictionary](https://github.com/aymericzip/intlayer/blob/main/docs/docs/en/packages/react-intlayer/useDictionary.md) |\n| `useDictionaryAsync`   | Hook that handles asynchronous dictionaries. Accepts a promise-based dictionary map and resolves it for the current locale.               | -                                                                                                                       |\n| `useDictionaryDynamic` | Hook that handles dynamic dictionaries loaded by key. Uses React Suspense internally for loading states.                                  | -                                                                                                                       |\n| `useLocale`            | Client-side hook to get the current locale, default locale, available locales, and a function to update the locale.                       | [useLocale](https://github.com/aymericzip/intlayer/blob/main/docs/docs/en/packages/react-intlayer/useLocale.md)         |\n| `useLocaleBase`        | Hook to get the current locale and all related fields (locale, defaultLocale, availableLocales, setLocale) from context.                  | -                                                                                                                       |\n| `useRewriteURL`        | Client-side hook to manage URL rewrites. If a rewrite rule exists for the current pathname and locale, it will update the URL.            | [useRewriteURL](https://github.com/aymericzip/intlayer/blob/main/docs/docs/en/packages/react-intlayer/useRewriteURL.md) |\n| `useI18n`              | Hook that provides a translation function `t()` for accessing nested content by key. Mimics i18next/next-intl pattern.                    | [useI18n](https://github.com/aymericzip/intlayer/blob/main/docs/docs/en/packages/react-intlayer/useI18n.md)             |\n| `useIntl`              | Hook that provides a locale-bound `Intl` object. Automatically injects the current locale and uses optimized caching.                     | -                                                                                                                       |\n| `useLocaleStorage`     | Hook that provides locale persistence in local storage or cookies. Returns getter and setter functions.                                   | -                                                                                                                       |\n| `useLocaleCookie`      | Deprecated. Use `useLocaleStorage` instead. Hook that manages locale persistence in cookies.                                              | -                                                                                                                       |\n| `useLoadDynamic`       | Hook to load dynamic dictionaries using React Suspense. Accepts a key and promise, caches results.                                        | -                                                                                                                       |\n| `useIntlayerContext`   | Hook that provides the current Intlayer client context values (locale, setLocale, etc.).                                                  | -                                                                                                                       |\n| `useHTMLContext`       | Hook to access HTML component overrides from HTMLProvider context.                                                                        | -                                                                                                                       |\n\n### Functions\n\nImport:\n\n```tsx\nimport \"react-intlayer\";\n```\n\n| Function             | Description                                                                                                                                              | Related Doc                                                                                    |\n| -------------------- | -------------------------------------------------------------------------------------------------------------------------------------------------------- | ---------------------------------------------------------------------------------------------- |\n| `renderHTML`         | Standalone utility for rendering HTML outside of components.                                                                                             | -                                                                                              |\n| `renderMarkdown`     | Standalone utility for rendering Markdown outside of components.                                                                                         | -                                                                                              |\n| `t`                  | Client-side translation function that returns the translation of the provided multilang content. Uses context locale if not provided.                    | [translation](https://github.com/aymericzip/intlayer/blob/main/docs/dictionary/translation.md) |\n| `getDictionary`      | Processes dictionary objects and returns content for the specified locale. Processes `t()` translations, enumerations, markdown, HTML, etc.              | -                                                                                              |\n| `getIntlayer`        | Retrieves a dictionary by its key from the generated declaration and returns its content for the specified locale. Optimized version of `getDictionary`. | -                                                                                              |\n| `setLocaleInStorage` | Sets the locale in storage (local storage or cookie based on configuration).                                                                             | -                                                                                              |\n| `setLocaleCookie`    | Deprecated. Use `setLocaleInStorage` instead. Sets the locale in a cookie.                                                                               | -                                                                                              |\n| `localeInStorage`    | Gets the locale from storage (local storage or cookie).                                                                                                  | -                                                                                              |\n| `localeCookie`       | Deprecated. Use `localeInStorage` instead. Gets the locale from cookie.                                                                                  | -                                                                                              |\n\n### Components\n\nImport:\n\n```tsx\nimport \"react-intlayer\";\n```\n\nor\n\n```tsx\nimport \"react-intlayer/markdown\";\n```\n\n| Component          | Description                                                                                                            | Related Doc                                                                                                                   |\n| ------------------ | ---------------------------------------------------------------------------------------------------------------------- | ----------------------------------------------------------------------------------------------------------------------------- |\n| `HTMLRenderer`     | Renders HTML content with custom components.                                                                           | -                                                                                                                             |\n| `MarkdownProvider` | Provider for markdown rendering context. Allows custom component overrides for markdown elements.                      | -                                                                                                                             |\n| `MarkdownRenderer` | Renders markdown content with custom components. Supports all standard markdown features and Intlayer-specific syntax. | [MarkdownRenderer](https://github.com/aymericzip/intlayer/blob/main/docs/docs/en/packages/react-intlayer/MarkdownRenderer.md) |\n\n### Types\n\nImport:\n\n```tsx\nimport \"react-intlayer\";\n```\n\n| Type           | Description                                                                                     |\n| -------------- | ----------------------------------------------------------------------------------------------- |\n| `IntlayerNode` | Type representing a node in the Intlayer content tree. Used for type-safe content manipulation. |\n\n### Server-side (react-intlayer/server)\n\nImport:\n\n```tsx\nimport \"react-intlayer/server\";\n```\n\n| Export                   | Type        | Description                                      |\n| ------------------------ | ----------- | ------------------------------------------------ |\n| `IntlayerServerProvider` | `Component` | Provider for server-side rendering.              |\n| `IntlayerServer`         | `Component` | Server-side wrapper for Intlayer content.        |\n| `t`                      | `Function`  | Server-side version of the translation function. |\n| `useLocale`              | `Hook`      | Hook to access locale on the server side.        |\n| `useIntlayer`            | `Hook`      | Server-side version of `useIntlayer`.            |\n| `useDictionary`          | `Hook`      | Server-side version of `useDictionary`.          |\n| `useI18n`                | `Hook`      | Server-side version of `useI18n`.                |\n| `locale`                 | `Function`  | Function to get or set the locale on the server. |\n",
  "createdAt": "2026-01-21",
  "updatedAt": "2026-01-21",
  "title": "react-intlayer Package Documentation",
  "description": "React-specific implementation of Intlayer, providing hooks and providers for React applications.",
  "keywords": [
    "react-intlayer",
    "react",
    "internationalization",
    "i18n"
  ],
  "slugs": [
    "doc",
    "packages",
    "react-intlayer",
    "exports"
  ],
  "history": [
    {
      "version": "7.5.14",
      "date": "2026-01-21",
      "changes": "Unified documentation for all exports"
    }
  ],
  "docKey": "./docs/en/packages/react-intlayer/exports.md",
  "githubUrl": "https://github.com/aymericzip/intlayer/blob/main/docs/docs/en/packages/react-intlayer/exports.md",
  "relativeUrl": "/doc/packages/react-intlayer/exports",
  "url": "https://intlayer.org/doc/packages/react-intlayer/exports"
}