{
  "id": "./docs/en/packages/fastify-intlayer/exports.md",
  "content": "---\ncreatedAt: 2026-01-21\nupdatedAt: 2026-01-21\ntitle: fastify-intlayer Package Documentation\ndescription: Fastify plugin for Intlayer, providing translation functions and locale detection.\nkeywords:\n  - fastify-intlayer\n  - fastify\n  - plugin\n  - internationalization\n  - i18n\nslugs:\n  - doc\n  - packages\n  - fastify-intlayer\n  - exports\nhistory:\n  - version: 8.0.0\n    date: 2026-01-21\n    changes: Unified documentation for all exports\n---\n\n# fastify-intlayer Package\n\nThe `fastify-intlayer` package provides a plugin for Fastify applications to handle internationalization. It detects the user's locale and decorates the request object.\n\n## Installation\n\n```bash\nnpm install fastify-intlayer\n```\n\n## Exports\n\n### Plugin\n\nImport:\n\n```tsx\nimport \"fastify-intlayer\";\n```\n\n| Function   | Description                                                                                                                                                                                                                                                                                                            | Related Doc                                                                                                     |\n| ---------- | ---------------------------------------------------------------------------------------------------------------------------------------------------------------------------------------------------------------------------------------------------------------------------------------------------------------------- | --------------------------------------------------------------------------------------------------------------- |\n| `intlayer` | Fastify plugin that integrates Intlayer into your Fastify application. Handles locale detection from storage (cookies, headers), decorates the request object with `intlayer` data containing `t`, `getIntlayer`, and `getDictionary`, and sets up CLS namespace for programmatic access during the request lifecycle. | [intlayer](https://github.com/aymericzip/intlayer/blob/main/docs/docs/en/packages/fastify-intlayer/intlayer.md) |\n\n### Functions\n\nImport:\n\n```tsx\nimport \"fastify-intlayer\";\n```\n\n| Function        | Description                                                                                                                                                                                                                                       | Related Doc                                                                                            |\n| --------------- | ------------------------------------------------------------------------------------------------------------------------------------------------------------------------------------------------------------------------------------------------- | ------------------------------------------------------------------------------------------------------ |\n| `t`             | Global translation function that retrieves content for the current locale in Fastify. Utilizes CLS (Async Local Storage) and must be used within a request context managed by the `intlayer` plugin. Can also be accessed via `req.intlayer.t`.   | [translation](https://github.com/aymericzip/intlayer/blob/main/docs/docs/en/dictionary/translation.md) |\n| `getIntlayer`   | Retrieves a dictionary by its key from the generated declaration and returns its content for the specified locale. Optimized version of `getDictionary`. Uses CLS to access request context. Can also be accessed via `req.intlayer.getIntlayer`. | -                                                                                                      |\n| `getDictionary` | Processes dictionary objects and returns content for the specified locale. Processes `t()` translations, enumerations, markdown, HTML, etc. Uses CLS to access request context. Can also be accessed via `req.intlayer.getDictionary`.            | -                                                                                                      |\n",
  "createdAt": "2026-01-21",
  "updatedAt": "2026-01-21",
  "title": "fastify-intlayer Package Documentation",
  "description": "Fastify plugin for Intlayer, providing translation functions and locale detection.",
  "keywords": [
    "fastify-intlayer",
    "fastify",
    "plugin",
    "internationalization",
    "i18n"
  ],
  "slugs": [
    "doc",
    "packages",
    "fastify-intlayer",
    "exports"
  ],
  "history": [
    {
      "version": "8.0.0",
      "date": "2026-01-21",
      "changes": "Unified documentation for all exports"
    }
  ],
  "docKey": "./docs/en/packages/fastify-intlayer/exports.md",
  "githubUrl": "https://github.com/aymericzip/intlayer/blob/main/docs/docs/en/packages/fastify-intlayer/exports.md",
  "relativeUrl": "/doc/packages/fastify-intlayer/exports",
  "url": "https://intlayer.org/doc/packages/fastify-intlayer/exports"
}