{
  "id": "./docs/en/packages/next-intlayer/exports.md",
  "content": "---\ncreatedAt: 2026-01-21\nupdatedAt: 2026-01-21\ntitle: next-intlayer Package Documentation\ndescription: Next.js-specific integration for Intlayer, providing middleware and providers for App Router and Page Router.\nkeywords:\n  - next-intlayer\n  - nextjs\n  - react\n  - internationalization\n  - i18n\nslugs:\n  - doc\n  - packages\n  - next-intlayer\n  - exports\nhistory:\n  - version: 8.0.0\n    date: 2026-01-21\n    changes: Unified documentation for all exports\n---\n\n# next-intlayer Package\n\nThe `next-intlayer` package provides the necessary tools to integrate Intlayer into Next.js applications. It supports both the App Router and the Page Router, including middleware for locale-based routing.\n\n## Installation\n\n```bash\nnpm install next-intlayer\n```\n\n## Exports\n\n### Middleware\n\nImport:\n\n```tsx\nimport \"next-intlayer/middleware\";\n```\n\n| Function             | Description                                                                                                                                    | Related Doc                                                                                                                      |\n| -------------------- | ---------------------------------------------------------------------------------------------------------------------------------------------- | -------------------------------------------------------------------------------------------------------------------------------- |\n| `intlayerMiddleware` | Next.js middleware to handle locale-based routing and redirects. Detects locale from headers/cookies and redirects to appropriate locale path. | [intlayerMiddleware](https://github.com/aymericzip/intlayer/blob/main/docs/docs/en/packages/next-intlayer/intlayerMiddleware.md) |\n\n### Configuration Helpers\n\nImport:\n\n```tsx\nimport \"next-intlayer/server\";\n```\n\n| Function           | Description                                                                                                                                                          | Related Doc |\n| ------------------ | -------------------------------------------------------------------------------------------------------------------------------------------------------------------- | ----------- |\n| `withIntlayer`     | Asynchronous helper to wrap Next.js configuration, ensuring Intlayer dictionaries are prepared before build. Prepares content files and sets up webpack/SWC plugins. | -           |\n| `withIntlayerSync` | Synchronous helper to wrap Next.js configuration, ideal for configurations where async is not possible/desired. Does not prepare dictionaries on server start.       | -           |\n\n### Providers\n\nImport:\n\n```tsx\nimport \"next-intlayer\";\n```\n\nor\n\n```tsx\nimport \"next-intlayer/server\";\n```\n\n| Component                | Description                                                                                                  | Related Doc |\n| ------------------------ | ------------------------------------------------------------------------------------------------------------ | ----------- |\n| `IntlayerClientProvider` | Provider for client-side components in Next.js App Router. Wraps `IntlayerProvider` from react-intlayer.     | -           |\n| `IntlayerServerProvider` | Provider for server-side components in Next.js (App Router). Provides locale context on the server.          | -           |\n| `IntlayerServer`         | Server-side wrapper for Intlayer content in App Router. Ensures proper locale handling in Server Components. | -           |\n| `HTMLProvider`           | Provider for HTML-related internationalization settings. Allows component overrides for HTML tags.           | -           |\n| `HTMLRenderer`           | Renders HTML content with custom components.                                                                 | -           |\n| `MarkdownProvider`       | Provider for markdown rendering context. Allows custom component overrides for markdown elements.            | -           |\n| `MarkdownRenderer`       | Renders markdown content with custom components.                                                             | -           |\n\n### Hooks (Client-side)\n\nImport:\n\n```tsx\nimport \"next-intlayer\";\n```\n\nRe-exports most hooks from `react-intlayer`.\n\n| Hook                   | Description                                                                                                                               | Related Doc                                                                                                             |\n| ---------------------- | ----------------------------------------------------------------------------------------------------------------------------------------- | ----------------------------------------------------------------------------------------------------------------------- |\n| `useIntlayer`          | Client-side hook that picks one dictionary by its key and returns its content. Uses the locale from context if not provided.              | [useIntlayer](https://github.com/aymericzip/intlayer/blob/main/docs/docs/en/packages/react-intlayer/useIntlayer.md)     |\n| `useDictionary`        | Hook that transforms a dictionary object and returns the content for the current locale. Processes `t()` translations, enumerations, etc. | [useDictionary](https://github.com/aymericzip/intlayer/blob/main/docs/docs/en/packages/react-intlayer/useDictionary.md) |\n| `useDictionaryAsync`   | Hook that handles asynchronous dictionaries. Accepts a promise-based dictionary map and resolves it for the current locale.               | -                                                                                                                       |\n| `useDictionaryDynamic` | Hook that handles dynamic dictionaries loaded by key. Uses React Suspense internally for loading states.                                  | -                                                                                                                       |\n| `useLocale`            | Client-side hook to get the current locale and a function to set it. Enhanced for Next.js App Router with navigation support.             | [useLocale](https://github.com/aymericzip/intlayer/blob/main/docs/docs/en/packages/react-intlayer/useLocale.md)         |\n| `useRewriteURL`        | Client-side hook to manage URL rewrites. Automatically updates the URL if a prettier localized rewrite rule exists.                       | [useRewriteURL](https://github.com/aymericzip/intlayer/blob/main/docs/docs/en/packages/next-intlayer/useRewriteURL.md)  |\n| `useLocalePageRouter`  | Next.js Page Router specific hook for locale management. Handles redirections and page reloads upon locale changes.                       | -                                                                                                                       |\n| `useI18n`              | Hook that provides a translation function `t()` for accessing nested content by key. Mimics i18next/next-intl pattern.                    | [useI18n](https://github.com/aymericzip/intlayer/blob/main/docs/docs/en/packages/react-intlayer/useI18n.md)             |\n| `useIntl`              | Hook that provides a locale-bound `Intl` object. Automatically injects the current locale and uses optimized caching.                     | -                                                                                                                       |\n| `useLoadDynamic`       | Hook to load dynamic dictionaries using React Suspense. Accepts a key and promise, caches results.                                        | -                                                                                                                       |\n| `useHTMLRenderer`      | Hook to get a pre-configured HTML renderer function.                                                                                      | -                                                                                                                       |\n| `useMarkdownRenderer`  | Hook to get a pre-configured Markdown renderer function.                                                                                  | -                                                                                                                       |\n\n### Functions (Server-side)\n\nImport:\n\n```tsx\nimport \"next-intlayer/server\";\n```\n\n| Function               | Description                                                                                                                                        | Related Doc                                                                                            |\n| ---------------------- | -------------------------------------------------------------------------------------------------------------------------------------------------- | ------------------------------------------------------------------------------------------------------ |\n| `t`                    | Server-side version of the translation function for Next.js App Router. Returns the translation of multilang content for the server locale.        | [translation](https://github.com/aymericzip/intlayer/blob/main/docs/docs/en/dictionary/translation.md) |\n| `getLocale`            | Helper function to extract the current locale from Next.js headers and cookies. Designed for Server Components, Server Actions, or Route Handlers. | -                                                                                                      |\n| `generateStaticParams` | Generates static parameters for Next.js's dynamic routes based on configured locales. Returns array of locale objects for pre-rendering.           | -                                                                                                      |\n| `locale`               | Function to get or set the locale in the server context (App Router). Provides locale management in Server Components.                             | -                                                                                                      |\n\n### Types\n\nImport:\n\n```tsx\nimport \"next-intlayer\";\n```\n\n| Type                   | Description                                                                                                            |\n| ---------------------- | ---------------------------------------------------------------------------------------------------------------------- |\n| `NextPageIntlayer`     | Type for Next.js pages with Intlayer support. Generic type that includes locale parameter.                             |\n| `Next14PageIntlayer`   | Type for Next.js 14 pages with Intlayer support.                                                                       |\n| `Next15PageIntlayer`   | Type for Next.js 15 pages with Intlayer support.                                                                       |\n| `NextLayoutIntlayer`   | Type for Next.js layouts with Intlayer support. Generic type that includes locale parameter.                           |\n| `Next14LayoutIntlayer` | Type for Next.js 14 layouts with Intlayer support.                                                                     |\n| `Next15LayoutIntlayer` | Type for Next.js 15 layouts with Intlayer support.                                                                     |\n| `LocalParams`          | Type for Next.js route parameters with locale. Object with `locale` property.                                          |\n| `LocalPromiseParams`   | Type for Next.js route parameters with locale (async version). Promise that resolves to object with `locale` property. |\n",
  "createdAt": "2026-01-21",
  "updatedAt": "2026-01-21",
  "title": "next-intlayer Package Documentation",
  "description": "Next.js-specific integration for Intlayer, providing middleware and providers for App Router and Page Router.",
  "keywords": [
    "next-intlayer",
    "nextjs",
    "react",
    "internationalization",
    "i18n"
  ],
  "slugs": [
    "doc",
    "packages",
    "next-intlayer",
    "exports"
  ],
  "history": [
    {
      "version": "8.0.0",
      "date": "2026-01-21",
      "changes": "Unified documentation for all exports"
    }
  ],
  "docKey": "./docs/en/packages/next-intlayer/exports.md",
  "githubUrl": "https://github.com/aymericzip/intlayer/blob/main/docs/docs/en/packages/next-intlayer/exports.md",
  "relativeUrl": "/doc/packages/next-intlayer/exports",
  "url": "https://intlayer.org/doc/packages/next-intlayer/exports"
}