{
  "id": "./docs/en/packages/adonis-intlayer/intlayer.md",
  "content": "---\ncreatedAt: 2026-01-30\nupdatedAt: 2026-01-30\ntitle: intlayer AdonisJS Middleware Documentation | adonis-intlayer\ndescription: See how to use the intlayer middleware for adonis-intlayer package\nkeywords:\n  - intlayer\n  - adonisjs\n  - middleware\n  - Intlayer\n  - Internationalization\n  - Documentation\nslugs:\n  - doc\n  - packages\n  - adonis-intlayer\n  - intlayer\nhistory:\n  - version: 8.0.0\n    date: 2026-01-30\n    changes: Initial documentation\n---\n\n# intlayer AdonisJS Middleware Documentation\n\nThe `intlayer` middleware for AdonisJS detects the user's locale and provides translation functions through the request context. It also enables the use of global translation functions within the request flow.\n\n## Usage\n\n```ts fileName=\"start/kernel.ts\"\nrouter.use([() => import(\"adonis-intlayer/middleware\")]);\n```\n\n```ts fileName=\"start/routes.ts\"\nimport router from \"@adonisjs/core/services/router\";\nimport { t } from \"adonis-intlayer\";\n\nrouter.get(\"/\", async () => {\n  return t({\n    en: \"Hello\",\n    fr: \"Bonjour\",\n  });\n});\n```\n\n## Description\n\nThe middleware performs the following tasks:\n\n1. **Locale Detection**: It analyzes the request (headers, cookies, etc.) to determine the user's preferred locale.\n2. **Context Setup**: It populates the request context with locale information.\n3. **Async Local Storage**: It uses `cls-hooked` to manage an asynchronous context, allowing global Intlayer functions like `t`, `getIntlayer`, and `getDictionary` to access the request-specific locale without passing it manually.\n\n> Note: To use cookies for locale detection, ensure `@adonisjs/cookie` is configured and used in your application.\n",
  "createdAt": "2026-01-30",
  "updatedAt": "2026-01-30",
  "title": "intlayer AdonisJS Middleware Documentation | adonis-intlayer",
  "description": "See how to use the intlayer middleware for adonis-intlayer package",
  "keywords": [
    "intlayer",
    "adonisjs",
    "middleware",
    "Intlayer",
    "Internationalization",
    "Documentation"
  ],
  "slugs": [
    "doc",
    "packages",
    "adonis-intlayer",
    "intlayer"
  ],
  "history": [
    {
      "version": "8.0.0",
      "date": "2026-01-30",
      "changes": "Initial documentation"
    }
  ],
  "docKey": "./docs/en/packages/adonis-intlayer/intlayer.md",
  "githubUrl": "https://github.com/aymericzip/intlayer/blob/main/docs/docs/en/packages/adonis-intlayer/intlayer.md",
  "relativeUrl": "/doc/packages/adonis-intlayer/intlayer",
  "url": "https://intlayer.org/doc/packages/adonis-intlayer/intlayer"
}