{
  "id": "./docs/en/packages/intlayer/getLocaleName.md",
  "content": "---\ncreatedAt: 2025-08-23\nupdatedAt: 2025-08-23\ntitle: getLocaleName Function Documentation | intlayer\ndescription: See how to use the getLocaleName function for intlayer package\nkeywords:\n  - getLocaleName\n  - translation\n  - Intlayer\n  - intlayer\n  - Internationalization\n  - Documentation\n  - Next.js\n  - JavaScript\n  - React\nslugs:\n  - doc\n  - packages\n  - intlayer\n  - getLocaleName\nhistory:\n  - version: 7.5.0\n    date: 2025-12-18\n    changes: Add polyfills for React Native and older environments\n  - version: 5.5.10\n    date: 2025-06-29\n    changes: Init history\n---\n\n# Documentation: `getLocaleName` Function in `intlayer`\n\n## Description\n\nThe `getLocaleName` function returns the localized name of a given locale (`targetLocale`) in the display locale (`displayLocale`). If no `targetLocale` is provided, it returns the name of the `displayLocale` in its own language.\n\n## Parameters\n\n- `displayLocale: Locales`\n  - **Description**: The locale in which the name of the target locale will be displayed.\n  - **Type**: Enum or string representing valid locales.\n\n- `targetLocale?: Locales`\n  - **Description**: The locale whose name is to be localized.\n  - **Type**: Optional. Enum or string representing valid locales.\n\n## Returns\n\n- **Type**: `string`\n- **Description**: The localized name of the `targetLocale` in the `displayLocale`, or the `displayLocale`'s own name if `targetLocale` is not provided. If no translation is found, it returns `\"Unknown locale\"`.\n\n## Example Usage\n\n```typescript codeFormat=\"typescript\"\nimport { Locales, getLocaleName } from \"intlayer\";\n\ngetLocaleName(Locales.ENGLISH); // Output: \"English\"\ngetLocaleName(Locales.ENGLISH, Locales.FRENCH); // Output: \"Anglais\"\ngetLocaleName(Locales.ENGLISH, Locales.ESPANOL); // Output: \"Inglés\"\ngetLocaleName(Locales.ENGLISH, Locales.ENGLISH); // Output: \"English\"\n\ngetLocaleName(Locales.FRENCH); // Output: \"Français\"\ngetLocaleName(Locales.FRENCH, Locales.FRENCH); // Output: \"Français\"\ngetLocaleName(Locales.FRENCH, Locales.ESPANOL); // Output: \"Francés\"\ngetLocaleName(Locales.FRENCH, Locales.ENGLISH); // Output: \"French\"\n\ngetLocaleName(Locales.CHINESE); // Output: \"中文\"\ngetLocaleName(Locales.CHINESE, Locales.FRENCH); // Output: \"Chinois\"\ngetLocaleName(Locales.CHINESE, Locales.ESPANOL); // Output: \"Chino\"\ngetLocaleName(Locales.CHINESE, Locales.ENGLISH); // Output: \"Chinese\"\n\ngetLocaleName(\"unknown-locale\"); // Output: \"Unknown locale\"\n```\n\n```javascript codeFormat=\"esm\"\nimport { Locales, getLocaleName } from \"intlayer\";\n\ngetLocaleName(Locales.ENGLISH); // Output: \"English\"\ngetLocaleName(Locales.ENGLISH, Locales.FRENCH); // Output: \"Anglais\"\ngetLocaleName(Locales.ENGLISH, Locales.ESPANOL); // Output: \"Inglés\"\ngetLocaleName(Locales.ENGLISH, Locales.ENGLISH); // Output: \"English\"\n\ngetLocaleName(Locales.FRENCH); // Output: \"Français\"\ngetLocaleName(Locales.FRENCH, Locales.FRENCH); // Output: \"Français\"\ngetLocaleName(Locales.FRENCH, Locales.ESPANOL); // Output: \"Francés\"\ngetLocaleName(Locales.FRENCH, Locales.ENGLISH); // Output: \"French\"\n\ngetLocaleName(Locales.CHINESE); // Output: \"中文\"\ngetLocaleName(Locales.CHINESE, Locales.FRENCH); // Output: \"Chinois\"\ngetLocaleName(Locales.CHINESE, Locales.ESPANOL); // Output: \"Chino\"\ngetLocaleName(Locales.CHINESE, Locales.ENGLISH); // Output: \"Chinese\"\n\ngetLocaleName(\"unknown-locale\"); // Output: \"Unknown locale\"\n```\n\n```javascript codeFormat=\"commonjs\"\nconst { Locales, getLocaleName } = require(\"intlayer\");\n\ngetLocaleName(Locales.ENGLISH); // Output: \"English\"\ngetLocaleName(Locales.ENGLISH, Locales.FRENCH); // Output: \"Anglais\"\ngetLocaleName(Locales.ENGLISH, Locales.ESPANOL); // Output: \"Inglés\"\ngetLocaleName(Locales.ENGLISH, Locales.ENGLISH); // Output: \"English\"\n\ngetLocaleName(Locales.FRENCH); // Output: \"Français\"\ngetLocaleName(Locales.FRENCH, Locales.FRENCH); // Output: \"Français\"\ngetLocaleName(Locales.FRENCH, Locales.ESPANOL); // Output: \"Francés\"\ngetLocaleName(Locales.FRENCH, Locales.ENGLISH); // Output: \"French\"\n\ngetLocaleName(Locales.CHINESE); // Output: \"中文\"\ngetLocaleName(Locales.CHINESE, Locales.FRENCH); // Output: \"Chinois\"\ngetLocaleName(Locales.CHINESE, Locales.ESPANOL); // Output: \"Chino\"\ngetLocaleName(Locales.CHINESE, Locales.ENGLISH); // Output: \"Chinese\"\n\ngetLocaleName(\"unknown-locale\"); // Output: \"Unknown locale\"\n```\n\n## Edge Cases\n\n- **No `targetLocale` provided:**\n  - The function defaults to returning the `displayLocale`'s own name.\n- **Missing translations:**\n  - If `localeNameTranslations` does not contain an entry for the `targetLocale` or the specific `displayLocale`, the function falls back to the `ownLocalesName` or returns `\"Unknown locale\"`.\n\n## Polyfills for React Native and Older Environments\n\nThe `getLocaleName` function relies on the `Intl.DisplayNames` API, which is not available in React Native or older JavaScript environments. If you're using `getLocaleName` in these environments, you need to add polyfills.\n\nImport the polyfills early in your application, ideally in your entry point file (e.g., `index.js`, `App.tsx`, or `main.tsx`):\n\n```typescript\nimport \"intl\";\nimport \"@formatjs/intl-locale/polyfill\";\nimport \"@formatjs/intl-displaynames/polyfill\";\n```\n\nFor more details, see the [FormatJS polyfills documentation](https://formatjs.io/docs/polyfills/intl-displaynames/).\n",
  "createdAt": "2025-08-23",
  "updatedAt": "2025-08-23",
  "title": "getLocaleName Function Documentation | intlayer",
  "description": "See how to use the getLocaleName function for intlayer package",
  "keywords": [
    "getLocaleName",
    "translation",
    "Intlayer",
    "intlayer",
    "Internationalization",
    "Documentation",
    "Next.js",
    "JavaScript",
    "React"
  ],
  "slugs": [
    "doc",
    "packages",
    "intlayer",
    "getLocaleName"
  ],
  "history": [
    {
      "version": "7.5.0",
      "date": "2025-12-18",
      "changes": "Add polyfills for React Native and older environments"
    },
    {
      "version": "5.5.10",
      "date": "2025-06-29",
      "changes": "Init history"
    }
  ],
  "docKey": "./docs/en/packages/intlayer/getLocaleName.md",
  "githubUrl": "https://github.com/aymericzip/intlayer/blob/main/docs/docs/en/packages/intlayer/getLocaleName.md",
  "relativeUrl": "/doc/packages/intlayer/getLocaleName",
  "url": "https://intlayer.org/doc/packages/intlayer/getLocaleName"
}