{
  "id": "./docs/en/packages/vue-intlayer.md",
  "content": "---\ncreatedAt: 2026-01-21\nupdatedAt: 2026-01-21\ntitle: vue-intlayer Package Documentation\ndescription: Vue-specific integration for Intlayer, providing plugins and composables for Vue applications.\nkeywords:\n  - vue-intlayer\n  - vue\n  - internationalization\n  - i18n\nslugs:\n  - doc\n  - packages\n  - vue-intlayer\nhistory:\n  - version: 8.0.0\n    date: 2026-01-21\n    changes: Unified documentation for all exports\n---\n\n# vue-intlayer Package\n\nThe `vue-intlayer` package provides the necessary tools to integrate Intlayer into Vue applications. It includes a Vue plugin and composables for handling multilingual content.\n\n## Installation\n\n```bash\nnpm install vue-intlayer\n```\n\n## Exports\n\n### Plugin\n\n| Function          | Description                                         |\n| ----------------- | --------------------------------------------------- |\n| `installIntlayer` | Vue plugin to install Intlayer in your application. |\n\n### Composables\n\n| Composable      | Description                                              |\n| --------------- | -------------------------------------------------------- |\n| `useIntlayer`   | Picks one dictionary by its key and returns the content. |\n| `useDictionary` | Picks one dictionary by its key and returns the content. |\n| `useLocale`     | Returns the current locale and a function to set it.     |\n| `useIntl`       | Returns the Intl object for the current locale.          |\n\n### Functions\n\n| Function        | Description                          |\n| --------------- | ------------------------------------ |\n| `getDictionary` | Retrieves a dictionary.              |\n| `getIntlayer`   | Retrieves content from a dictionary. |\n\n### Markdown\n\n| Function                  | Description                                                  |\n| ------------------------- | ------------------------------------------------------------ |\n| `installIntlayerMarkdown` | Vue plugin to install Intlayer Markdown in your application. |\n",
  "createdAt": "2026-01-21",
  "updatedAt": "2026-01-21",
  "title": "vue-intlayer Package Documentation",
  "description": "Vue-specific integration for Intlayer, providing plugins and composables for Vue applications.",
  "keywords": [
    "vue-intlayer",
    "vue",
    "internationalization",
    "i18n"
  ],
  "slugs": [
    "doc",
    "packages",
    "vue-intlayer"
  ],
  "history": [
    {
      "version": "8.0.0",
      "date": "2026-01-21",
      "changes": "Unified documentation for all exports"
    }
  ],
  "docKey": "./docs/en/packages/vue-intlayer.md",
  "githubUrl": "https://github.com/aymericzip/intlayer/blob/main/docs/docs/en/packages/vue-intlayer.md",
  "relativeUrl": "/doc/packages/vue-intlayer",
  "url": "https://intlayer.org/doc/packages/vue-intlayer"
}