{
  "id": "./docs/en/packages/adonis-intlayer/exports.md",
  "content": "---\ncreatedAt: 2026-01-30\nupdatedAt: 2026-01-30\ntitle: adonis-intlayer Package Documentation\ndescription: AdonisJS middleware for Intlayer, providing translation functions and locale detection.\nkeywords:\n  - adonis-intlayer\n  - adonisjs\n  - middleware\n  - internationalization\n  - i18n\nslugs:\n  - doc\n  - packages\n  - adonis-intlayer\n  - exports\nhistory:\n  - version: 8.0.0\n    date: 2026-01-30\n    changes: Initial documentation\n---\n\n# adonis-intlayer Package\n\nThe `adonis-intlayer` package provides a middleware for AdonisJS applications to handle internationalization. It detects the user's locale and provides translation functions.\n\n## Installation\n\n```bash\nnpm install adonis-intlayer\n```\n\n## Exports\n\n### Middleware\n\nThe package provides an AdonisJS middleware to handle internationalization.\n\n| Function             | Description                                                                                                                                                                                                                                                     | Related Doc                                                                                                    |\n| -------------------- | --------------------------------------------------------------------------------------------------------------------------------------------------------------------------------------------------------------------------------------------------------------- | -------------------------------------------------------------------------------------------------------------- |\n| `IntlayerMiddleware` | AdonisJS middleware that detects the user's locale and populates the request context with Intlayer data. It also sets up a CLS (Async Local Storage) namespace for request lifecycle access, enabling the use of global functions like `t`, `getIntlayer`, etc. | [intlayer](https://github.com/aymericzip/intlayer/blob/main/docs/docs/en/packages/adonis-intlayer/intlayer.md) |\n\n### Functions\n\n| Function        | Description                                                                                                                                                                                            | Related Doc                                                                                            |\n| --------------- | ------------------------------------------------------------------------------------------------------------------------------------------------------------------------------------------------------ | ------------------------------------------------------------------------------------------------------ |\n| `t`             | Translation function that retrieves content for the current locale. Works within the request lifecycle managed by the `intlayer` middleware. Uses CLS (Async Local Storage) to access request context. | [translation](https://github.com/aymericzip/intlayer/blob/main/docs/docs/en/dictionary/translation.md) |\n| `getIntlayer`   | Retrieves a dictionary by its key from the generated declaration and returns its content for the specified locale. Optimized version of `getDictionary`. Uses CLS to access request context.           | -                                                                                                      |\n| `getDictionary` | Processes dictionary objects and returns content for the specified locale. Processes `t()` translations, enumerations, markdown, HTML, etc. Uses CLS to access request context.                        | -                                                                                                      |\n| `getLocale`     | Retrieves the current locale from the request context using CLS.                                                                                                                                       | -                                                                                                      |\n",
  "createdAt": "2026-01-30",
  "updatedAt": "2026-01-30",
  "title": "adonis-intlayer Package Documentation",
  "description": "AdonisJS middleware for Intlayer, providing translation functions and locale detection.",
  "keywords": [
    "adonis-intlayer",
    "adonisjs",
    "middleware",
    "internationalization",
    "i18n"
  ],
  "slugs": [
    "doc",
    "packages",
    "adonis-intlayer",
    "exports"
  ],
  "history": [
    {
      "version": "8.0.0",
      "date": "2026-01-30",
      "changes": "Initial documentation"
    }
  ],
  "docKey": "./docs/en/packages/adonis-intlayer/exports.md",
  "githubUrl": "https://github.com/aymericzip/intlayer/blob/main/docs/docs/en/packages/adonis-intlayer/exports.md",
  "relativeUrl": "/doc/packages/adonis-intlayer/exports",
  "url": "https://intlayer.org/doc/packages/adonis-intlayer/exports"
}