{
  "id": "./docs/en/packages/intlayer/getLocale.md",
  "content": "---\ncreatedAt: 2026-01-21\nupdatedAt: 2026-01-21\ntitle: getLocale Function Documentation | intlayer\ndescription: See how to use the getLocale function for intlayer package\nkeywords:\n  - getLocale\n  - translation\n  - Intlayer\n  - intlayer\n  - Internationalization\n  - Documentation\nslugs:\n  - doc\n  - packages\n  - intlayer\n  - getLocale\nhistory:\n  - version: 8.0.0\n    date: 2026-01-21\n    changes: Init doc\n---\n\n# getLocale Function Documentation\n\nThe `getLocale` function allows you to detect the locale from a given string, such as a URL or a path.\n\n## Usage\n\n```ts\nimport { getLocale } from \"intlayer\";\n\nconst locale = getLocale(\"/fr/about\");\n\n// Output: 'fr'\n```\n\n## Parameters\n\n| Parameter | Type     | Description                                    |\n| --------- | -------- | ---------------------------------------------- |\n| `path`    | `string` | The path or string to extract the locale from. |\n\n## Returns\n\nThe detected locale, or the default locale if no locale is detected.\n",
  "createdAt": "2026-01-21",
  "updatedAt": "2026-01-21",
  "title": "getLocale Function Documentation | intlayer",
  "description": "See how to use the getLocale function for intlayer package",
  "keywords": [
    "getLocale",
    "translation",
    "Intlayer",
    "intlayer",
    "Internationalization",
    "Documentation"
  ],
  "slugs": [
    "doc",
    "packages",
    "intlayer",
    "getLocale"
  ],
  "history": [
    {
      "version": "8.0.0",
      "date": "2026-01-21",
      "changes": "Init doc"
    }
  ],
  "docKey": "./docs/en/packages/intlayer/getLocale.md",
  "githubUrl": "https://github.com/aymericzip/intlayer/blob/main/docs/docs/en/packages/intlayer/getLocale.md",
  "relativeUrl": "/doc/packages/intlayer/getLocale",
  "url": "https://intlayer.org/doc/packages/intlayer/getLocale"
}