{
  "id": "./docs/en/per_locale_file.md",
  "content": "---\ncreatedAt: 2025-04-18\nupdatedAt: 2025-06-29\ntitle: Declaration of `Per-Locale` Content Declaration in Intlayer\ndescription: Discover how to declare content per locale in Intlayer. Follow the documentation to understand the different formats and use cases.\nkeywords:\n  - Internationalization\n  - Documentation\n  - Intlayer\n  - Per-Locale\n  - TypeScript\n  - JavaScript\nslugs:\n  - doc\n  - concept\n  - per-locale-file\nhistory:\n  - version: 7.3.1\n    date: 2025-11-29\n    changes: Add global configuration for per-locale files\n  - version: 5.5.10\n    date: 2025-06-29\n    changes: Init history\n---\n\n# Declaration of `Per-Locale` Content Declaration in Intlayer\n\nIntlayer supports two ways to declare multilingual content:\n\n- Single file with all translations\n- One file per locale (per-locale format)\n\nThis flexibility enables:\n\n- Easy migration from other i18n tools\n- Support for automated translation workflows\n- Clear organization of translations into separate, locale-specific files\n\n## Per-Locale Format\n\nThis format is useful when:\n\n- You want to version or override translations independently.\n- You're integrating machine or human translation workflows.\n\nYou can also split translations into individual locale files by specifying the locale field:\n\n```tsx fileName=\"hello-world.en.content.ts\" contentDeclarationFormat=\"typescript\"\nimport { t, Locales, type Dictionary } from \"intlayer\";\n\nconst helloWorldContent = {\n  key: \"hello-world\",\n  locale: Locales.ENGLISH, // Important\n  content: { multilingualContent: \"Title of my component\" },\n} satisfies Dictionary;\n\nexport default helloWorldContent;\n```\n\n```tsx fileName=\"hello-world.es.content.ts\" contentDeclarationFormat=\"typescript\"\nimport { t, Locales, type Dictionary } from \"intlayer\";\n\nconst helloWorldContent = {\n  key: \"hello-world\",\n  locale: Locales.SPANISH, // Important\n  content: { multilingualContent: \"Título de mi componente\" },\n} satisfies Dictionary;\n\nexport default helloWorldContent;\n```\n\n```js fileName=\"hello-world.en.content.mjs\" contentDeclarationFormat=\"esm\"\nimport { t, Locales } from \"intlayer\";\n\n/** @type {import('intlayer').Dictionary} */\nconst helloWorldContent = {\n  key: \"hello-world\",\n  locale: Locales.ENGLISH, // Important\n  content: { multilingualContent: \"Title of my component\" },\n};\n\nexport default helloWorldContent;\n```\n\n```tsx fileName=\"hello-world.es.content.mjs\" contentDeclarationFormat=\"esm\"\nimport { t, Locales } from \"intlayer\";\n\n/** @type {import('intlayer').Dictionary} */\nconst helloWorldContent = {\n  key: \"hello-world\",\n  locale: Locales.SPANISH, // Important\n  content: { multilingualContent: \"Título de mi componente\" },\n};\n\nexport default helloWorldContent;\n```\n\n```js fileName=\"hello-world.en.content.cjs\" contentDeclarationFormat=\"commonjs\"\nconst { t, Locales } = require(\"intlayer\");\n\n/** @type {import('intlayer').Dictionary} */\nconst helloWorldContent = {\n  key: \"hello-world\",\n  locale: Locales.ENGLISH, // Important\n  content: {\n    multilingualContent: \"Title of my component\",\n  },\n};\n\nmodule.exports = helloWorldContent;\n```\n\n```tsx fileName=\"hello-world.es.content.cjs\" contentDeclarationFormat=\"commonjs\"\nconst { t, Locales } = require(\"intlayer\");\n\n/** @type {import('intlayer').Dictionary} */\nconst helloWorldContent = {\n  key: \"hello-world\",\n  locale: Locales.SPANISH, // Important\n  content: {\n    multilingualContent: \"Título de mi componente\",\n  },\n};\n\nmodule.exports = helloWorldContent;\n```\n\n```json5 fileName=\"hello-world.en.content.json\" contentDeclarationFormat=\"json\"\n{\n  \"$schema\": \"https://intlayer.org/schema.json\",\n  \"key\": \"hello-world\",\n  \"locale\": \"en\", // Important\n  \"content\": {\n    \"multilingualContent\": \"Title of my component\",\n  },\n}\n```\n\n```json5 fileName=\"hello-world.es.content.json\" contentDeclarationFormat=\"json\"\n{\n  \"$schema\": \"https://intlayer.org/schema.json\",\n  \"key\": \"hello-world\",\n  \"locale\": \"es\", // Important\n  \"content\": {\n    \"multilingualContent\": \"Título de mi componente\",\n  },\n}\n```\n\n> Important: Make sure the locale field is defined. It tells Intlayer which language the file represents.\n\n> Note: In both cases, the content declaration file must follow the naming pattern `*.content.{ts,tsx,js,jsx,mjs,cjs,json}` to be recognized by Intlayer. The `.[locale]` suffix is optional and used only as a naming convention.\n\n### Global Configuration for Per-Locale Files\n\nYou can configure the global configuration for per-locale files by adding the following to your `intlayer.config.ts` file:\n\n```ts\nimport { Locales, type IntlayerConfig } from \"intlayer\";\n\nconst config: IntlayerConfig = {\n  dictionary: {\n    locale: Locales.ENGLISH,\n  },\n};\n\nexport default config;\n```\n\nUsing this configuration, all per-locale files will be generated with the default locale set to English. It also include generation of `.content` files using the `transform` command, and the compiler. (See [Compiler](https://intlayer.org/doc/compiler) or [Transform](https://intlayer.org/doc/concept/cli/transform) for more information.)\n\n## Single File with Multiple Translations\n\nThis format is ideal for:\n\n- Quick iteration in code.\n- Seamless integration with the CMS.\n\nThis is the recommended approach for most use cases. It centralizes translations, making it easy to iterate and integrate with the CMS.\n\n```tsx fileName=\"hello-world.content.ts\" contentDeclarationFormat=\"typescript\"\nimport { t, type Dictionary } from \"intlayer\";\n\nconst helloWorldContent = {\n  key: \"hello-world\",\n  content: {\n    multilingualContent: t({\n      en: \"Title of my component\",\n      es: \"Título de mi componente\",\n    }),\n  },\n} satisfies Dictionary;\n\nexport default helloWorldContent;\n```\n\n```js fileName=\"hello-world.content.mjs\" contentDeclarationFormat=\"esm\"\nimport { t } from \"intlayer\";\n\n/** @type {import('intlayer').Dictionary} */\nconst helloWorldContent = {\n  key: \"hello-world\",\n  content: {\n    multilingualContent: t({\n      en: \"Title of my component\",\n      es: \"Título de mi componente\",\n    }),\n  },\n};\n\nexport default helloWorldContent;\n```\n\n```js fileName=\"hello-world.content.cjs\" contentDeclarationFormat=\"json\"\nconst { t } = require(\"intlayer\");\n\n/** @type {import('intlayer').Dictionary} */\nconst helloWorldContent = {\n  key: \"hello-world\",\n  content: {\n    multilingualContent: t({\n      en: \"Title of my component\",\n      es: \"Título de mi componente\",\n    }),\n  },\n};\n\nmodule.exports = helloWorldContent;\n```\n\n```json fileName=\"hello-world.content.ts\" contentDeclarationFormat=\"json\"\n{\n  \"$schema\": \"https://intlayer.org/schema.json\",\n  \"key\": \"hello-world\",\n  \"content\": {\n    \"multilingualContent\": {\n      \"nodeType\": \"translation\",\n      \"translation\": {\n        \"en\": \"Title of my component\",\n        \"es\": \"Título de mi componente\"\n      }\n    }\n  }\n}\n```\n\n> Recommended: This format is best when using Intlayer's visual editor or managing translations directly in the code.\n\n## Mixing Formats\n\nYou can combine both declaration approaches for the same content key. For example:\n\n- Declare your base content statically in a file like index.content.ts.\n- Add or override specific translations in separate files such as index.fr.content.ts or index.content.json.\n\nThis setup is especially useful when:\n\n- You want to define the initial content structure in code.\n- You plan to enrich or complete translations later using the CMS or automated tools.\n\n```bash codeFormat=\"typescript\"\n.\n└── Components\n    └── MyComponent\n        ├── index.content.ts\n        ├── index.content.json\n        └── index.ts\n```\n\n### Example\n\nHere a multilingual content declaration file:\n\n```tsx fileName=\"Components/MyComponent/index.content.ts\"\nimport { t, type Dictionary } from \"intlayer\";\n\nconst helloWorldContent = {\n  key: \"hello-world\",\n  locale: Locales.ENGLISH,\n  content: {\n    multilingualContent: \"Title of my component\",\n    projectName: \"My project\",\n  },\n} satisfies Dictionary;\n\nexport default helloWorldContent;\n```\n\n```json fileName=\"Components/MyComponent/index.content.json\"\n{\n  \"$schema\": \"https://intlayer.org/schema.json\",\n  \"key\": \"hello-world\",\n  \"content\": {\n    \"multilingualContent\": {\n      \"nodeType\": \"translation\",\n      \"translation\": {\n        \"fr\": \"Titre de mon composant\",\n        \"es\": \"Título de mi componente\"\n      }\n    }\n  }\n}\n```\n\nIntlayer merges multilingual and per-locale files automatically.\n\n```tsx fileName=\"Components/MyComponent/index.ts\"\nimport { getIntlayer, Locales } from \"intlayer\";\n\nconst intlayer = getIntlayer(\"hello-world\"); // Default locale is ENGLISH, so it will return the ENGLISH content\n\nconsole.log(JSON.stringify(intlayer, null, 2));\n// Result:\n// {\n//  \"multilingualContent\": \"Title of my component\",\n//  \"projectName\": \"My project\"\n// }\n\nconst intlayer = getIntlayer(\"hello-world\", Locales.SPANISH);\n\nconsole.log(JSON.stringify(intlayer, null, 2));\n// Result:\n// {\n//  \"multilingualContent\": \"Título de mi componente\",\n//  \"projectName\": \"My project\"\n// }\n\nconst intlayer = getIntlayer(\"hello-world\", Locales.FRENCH);\n\nconsole.log(JSON.stringify(intlayer, null, 2));\n// Result:\n// {\n//  \"multilingualContent\": \"Titre de mon composant\",\n//  \"projectName\": \"My project\"\n// }\n```\n\n### Automatic Translation Generation\n\nUse the [intlayer CLI](https://github.com/aymericzip/intlayer/blob/main/docs/docs/en/cli/index.md) to auto-fill missing translations based on your preferred services.\n",
  "createdAt": "2025-04-18",
  "updatedAt": "2025-06-29",
  "title": "Declaration of `Per-Locale` Content Declaration in Intlayer",
  "description": "Discover how to declare content per locale in Intlayer. Follow the documentation to understand the different formats and use cases.",
  "keywords": [
    "Internationalization",
    "Documentation",
    "Intlayer",
    "Per-Locale",
    "TypeScript",
    "JavaScript"
  ],
  "slugs": [
    "doc",
    "concept",
    "per-locale-file"
  ],
  "history": [
    {
      "version": "7.3.1",
      "date": "2025-11-29",
      "changes": "Add global configuration for per-locale files"
    },
    {
      "version": "5.5.10",
      "date": "2025-06-29",
      "changes": "Init history"
    }
  ],
  "docKey": "./docs/en/per_locale_file.md",
  "githubUrl": "https://github.com/aymericzip/intlayer/blob/main/docs/docs/en/per_locale_file.md",
  "relativeUrl": "/doc/concept/per-locale-file",
  "url": "https://intlayer.org/doc/concept/per-locale-file"
}