{
  "id": "./docs/en/releases/v6.md",
  "content": "---\ncreatedAt: 2025-09-22\nupdatedAt: 2025-09-23\ntitle: New Intlayer v6 - What's new?\ndescription: Discover what's new in Intlayer v6. Major improvements in performance, developer experience, and new features to enhance your internationalization workflow.\nkeywords:\n  - Intlayer\n  - Localization\n  - Development\n  - Performance\n  - Developer Experience\n  - Features\n  - React\n  - Next.js\n  - JavaScript\n  - TypeScript\nslugs:\n  - doc\n  - releases\n  - v6\n---\n\n# New Intlayer v6 - What's new?\n\nWelcome to Intlayer v6! This release focuses on performance, developer experience, and reliability. Below are the highlights, with migration notes and copy‑pasteable examples.\n\n## Table of contents\n\n<TOC levels={[2]} maxDepth={1} />\n\n## Highlights\n\n- New command: `npx intlayer content test` to detect missing translations\n- New global `autoFill` option to auto‑generate missing translations\n- Fill command defaults to skipping existing translations: `npx intlayer fill`\n- VS Code extension: new Intlayer Activity Bar (Search & Dictionaries), toolbar/context actions, auto‑reveal, Fill/Test commands\n- 10× faster builds thanks to promise parallelization\n- Remote dictionary caching to avoid refetch at app start\n- Improved logging: set `log.mode: 'verbose'` to inspect behavior\n- Stronger validation to prevent app crashes on dictionary issues\n- Live updates with CMS using `build.importMode = 'live'` and `pnpm intlayer live`\n- Fixes: Vue.js integration, Lynx adapter, Visual Editor on Windows\n\n---\n\n## New: Test missing translations\n\nQuickly audit your project to find which keys/locales are missing.\n\n```bash\nnpx intlayer content test\n```\n\nOutput:\n\n```bash\npnpm intlayer content test\nMissing translations:\n - blog-data       - Japanese (ja), Korean (ko), Chinese (zh), German (de), Italian (it) - src/components/BlogPage/blogData.content.ts\n - demo-page       - French (fr), Italian (it)                                         - src/components/DemoPage/demo.content.ts\n - locale-switcher - Italian (it), Portuguese (pt)                                       - src/components/LocaleSwitcher/localeSwitcher.content.ts\nLocales: English (en), Russian (ru), Japanese (ja), French (fr), Korean (ko), Chinese (zh), Spanish (es), German (de), Arabic (ar), Italian (it), British English (en-GB), Portuguese (pt), Hindi (hi)\nRequired locales: English (en)\nMissing locales: Japanese (ja), Korean (ko), Chinese (zh), German (de), Italian (it), French (fr), Portuguese (pt)\nMissing required locales: -\nTotal missing locales: 7\nTotal missing required locales: 0\n```\n\nSee more options in the CLI docs: [CLI reference](https://github.com/aymericzip/intlayer/blob/main/docs/docs/en/cli/index.md) → \"Test missing translations\". As well as the [Testing](https://github.com/aymericzip/intlayer/blob/main/docs/docs/en/testing.md) guide.\n\n---\n\n## New: Global autoFill to complete missing translations\n\nYou can now enable auto‑fill globally so any dictionary with missing translations gets completed automatically.\n\n```ts fileName=\"intlayer.config.ts\"\nimport { type IntlayerConfig, Locales } from \"intlayer\";\n\nconst config: IntlayerConfig = {\n  internationalization: {\n    locales: [Locales.ENGLISH, Locales.FRENCH, Locales.SPANISH],\n    defaultLocale: Locales.ENGLISH,\n    requiredLocales: [Locales.ENGLISH, Locales.FRENCH],\n  },\n  content: {\n    // Auto-generate missing translations for all dictionaries\n    autoFill: \"./{{fileName}}Filled.content.ts\",\n    //\n    // autoFill: \"/messages/{{locale}}/{{key}}/{{fileName}}.content.json\",\n    //\n    // autoFill: true, // auto-generate missing translations for all dictionaries like using \"./{{fileName}}.content.json\"\n    //\n    // autoFill: {\n    //   en: \"./{{fileName}}.en.content.json\",\n    //   fr: \"./{{fileName}}.fr.content.json\",\n    //   es: \"./{{fileName}}.es.content.json\",\n    // },\n  },\n};\n\nexport default config;\n```\n\nAuto-fill your missing translations using the `npx intlayer fill` command.\n\nYou can still fine‑tune per dictionary using the `autoFill` field in content files. Intlayer will first consider the per dictionary configuration and then fallback to the global configuration. See the full reference in [Auto-fill](https://github.com/aymericzip/intlayer/blob/main/docs/docs/en/autoFill.md) and [Content file reference](https://github.com/aymericzip/intlayer/blob/main/docs/docs/en/dictionary/content_file.md).\n\n---\n\n## Fill command: safer defaults\n\nThe fill command now, by default, only fills missing translations and skips existing content.\n\n```bash\nnpx intlayer fill\n```\n\n```bash\nAffected dictionary keys for processing: access-key-creation-form-schema, doc-search-metadata, doc-search-page\n  - [access-key-creation-form-schema]      Dictionary has no file path. Skipping.\n  - [access-key-creation-form-schema]      Processing content declaration: src/components/Dashboard/ProjectForm/AccessKey/useAccessKeyCreationFormSchema.content.ts\n  - [access-key-creation-form-schema]      No locales to fill - Skipping dictionary\n  - [doc-search-metadata]                  Dictionary has no file path. Skipping.\n  - [doc-search-metadata]                  Processing content declaration: src/app/[locale]/(docs)/doc/search/metadata.content.ts\n  - [doc-search-metadata]                  No locales to fill - Skipping dictionary\n  - [doc-search-page]                      Dictionary has no file path. Skipping.\n  - [doc-search-page]                      Processing content declaration: src/app/[locale]/(docs)/doc/search/page.content.ts\n  - [doc-search-page]                     [Russian (ru)]                   Preparing translation for dictionary from English (en) to Russian (ru)\n[intlayer]  Applied Prettier formatting to src/app/[locale]/(docs)/doc/search/page.content.ts\n  - [doc-search-page]                      Content declaration written to src/app/[locale]/(docs)/doc/search/page.content.ts\n```\n\nCI examples are available in [CI/CD](https://github.com/aymericzip/intlayer/blob/main/docs/docs/en/CI_CD.md).\n\n---\n\n## Updated VS Code extension\n\nThe extension now includes a dedicated Intlayer tab in the Activity Bar and several workflow improvements:\n\n- Intlayer Activity Bar with two views:\n  - Search webview for live dictionary/content search\n  - Dictionaries tree listing environments, dictionaries, and contributing files\n- Toolbar on Dictionaries view: Build, Pull, Push, Fill, Refresh, Test, Create Dictionary File\n- Context menus: Pull/Push on dictionaries; Fill on files\n- Auto‑reveal: the current editor file is highlighted in the Dictionaries tree when applicable\n- New commands available from the Command Palette: Fill Dictionaries and Test Dictionaries\n\nSee details in the [Official VS Code Extension](https://github.com/aymericzip/intlayer/blob/main/docs/docs/en/vs_code_extension.md) documentation.\n\n---\n\nUpdated the MCP server to support the new features.\n\n- Auto-fill\n- Test missing translations\n- Live updates\n- Logging\n- Validation\n- Migration notes\n- Documentation\n\n> MCP server helps for the automatisation of project using Intlayer. Testing missing translations for autogenerated code. It helps understanding your config, and embed the documentation of Intlayer in your IDE.\n\n---\n\n## Performance: 10× faster\n\n- Parallel resolution of local and remote dictionaries\n- Remote dictionaries are cached to avoid re‑fetching at app startup\n\n```bash\nnpx intlayer build\n```\n\nOutput:\n\n```bash\n[intlayer]  Preparing Intlayer (v6.0.1)\n[intlayer]  Dictionaries:\n[intlayer]  ✓ Local content: 163/163\n[intlayer]  ✓ Remote content: 100/100\n[intlayer]   - access-key-creation-form             [local: ✔ built] [distant: ✔ imported]\n[intlayer]   - access-key-form                      [local: ✔ built] [distant: ✔ imported]\n[intlayer]   - ai-ab-testing-section                                 [distant: ✔ imported]\n[intlayer]   - application-not-running-view         [local: ✔ built] [distant: ✔ imported]\n[intlayer]   - available-techno-section             [local: ✔ built] [distant: ✔ imported]\n[intlayer]   - blog-data                            [local: ✔ built]\n[intlayer]   - blog-metadata                        [local: ✔ built]\n[intlayer]   - blog-nav-list                        [local: ✔ built] [distant: ✔ imported]\n[intlayer]   - blog-page                                             [distant: ✔ fetched]\n[intlayer]   - blog-search-page                     [local: ✔ built] [distant: ✔ imported]\n...\n[intlayer]  Content loaded  (Total: 8401ms - Local: 4050ms - Remote: 4222ms)\n```\n\n---\n\n## Logging improvements\n\nThe logging system has been improved to provide more detailed information about what happens during build and runtime transformations.\n\n> Enable verbose logs to better understand what happens during build and runtime transformations.\n\n```ts fileName=\"intlayer.config.ts\"\nexport default {\n  log: {\n    mode: \"verbose\", // options: \"default\" | \"verbose\" | \"disabled\"\n  },\n};\n```\n\nSee [Configuration](https://github.com/aymericzip/intlayer/blob/main/docs/docs/en/configuration.md) for all logging options.\n\n---\n\n## Stronger validation\n\nDictionary processing now performs more robust validation. When a dictionary fails to process, Intlayer avoids breaking your application and surfaces actionable errors.\n\n---\n\n## Live updates with CMS (Production‑safe)\n\nServe live content updates (e.g., editorial updates) in production without rebuilding your application.\n\n1. Enable live import mode:\n\n```ts fileName=\"intlayer.config.ts\"\nimport { type IntlayerConfig } from \"intlayer\";\n\nconst config: IntlayerConfig = {\n  build: {\n    importMode: \"live\", // \"static\" | \"dynamic\" | \"live\"\n  },\n  editor: {\n    liveSync: true, // enable live sync server side\n  },\n};\n\nexport default config;\n```\n\n2. Run your app and live process side‑by‑side:\n\n```bash\nnpx intlayer live --with 'vite preview'\n```\n\nNotes:\n\n- Only dictionaries flagged to use live mode will be fetched live. Others are optimized for performance.\n- Falls back to dynamic import if the live API isn’t reachable.\n\nSee [CMS and Live Sync](https://github.com/aymericzip/intlayer/blob/main/docs/docs/en/intlayer_CMS.md) and [Configuration](https://github.com/aymericzip/intlayer/blob/main/docs/docs/en/configuration.md) for complete guidance.\n\n## Parallel process to watch files on turbopack\n\nWhen using Turbopack on Next.js 14 and above as your development server with the `next dev --turbopack` command, dictionary changes will not be automatically detected by default.\n\nThis limitation occurs because Turbopack cannot run webpack plugins in parallel to monitor changes in your content files.\n\nTo work around this, we dropped the `intlayer watch` command, using the `--with` option to run both the development server and the Intlayer build watcher simultaneously.\n\n```json5 fileName=\"package.json\"\n{\n  \"scripts\": {\n    \"dev\": \"npx intlayer watch --with 'next dev --turbopack'\",\n  },\n}\n```\n\n---\n\n## Migration notes\n\n- Removed: `dictionaryOutput` (previously `i18next` or `next-intl`). This will come back as pluggable adapters in future versions. Remove the field from your config.\n- Related removal: `i18nextResourcesDir` (see `doc/configuration` changelog).\n- Prefer the new global `content.autoFill` option to generate missing translations at scale.\n- Use `npx intlayer content test` to gate PRs on missing translations.\n- For verbose diagnostics, set `log.mode = 'verbose'`.\n- Use `intlayer` instead of `intlayerPlugin` and `intlayerProxy` instead of `intlayerProxyPlugin` in your Vite configuration.\n\n---\n\n## Fixes\n\n- Vue.js integration stability\n- Lynx adapter improvements\n- Visual Editor on Windows\n\n---\n\n## Migration notes from v6 to v7\n\nCheck the [migration notes from v6 to v7](https://github.com/aymericzip/intlayer/blob/main/docs/docs/en/releases/v7.md) for more information.\n\n---\n\n## Useful links\n\n- [CLI reference](https://github.com/aymericzip/intlayer/blob/main/docs/docs/en/cli/index.md)\n- [Auto‑fill](https://github.com/aymericzip/intlayer/blob/main/docs/docs/en/autoFill.md)\n- [Configuration](https://github.com/aymericzip/intlayer/blob/main/docs/docs/en/configuration.md)\n- [Content file reference](https://github.com/aymericzip/intlayer/blob/main/docs/docs/en/dictionary/content_file.md)\n- [Official VS Code Extension](https://github.com/aymericzip/intlayer/blob/main/docs/docs/en/vs_code_extension.md)\n- [CMS and Live Sync](https://github.com/aymericzip/intlayer/blob/main/docs/docs/en/intlayer_CMS.md)\n",
  "createdAt": "2025-09-22",
  "updatedAt": "2025-09-23",
  "title": "New Intlayer v6 - What's new?",
  "description": "Discover what's new in Intlayer v6. Major improvements in performance, developer experience, and new features to enhance your internationalization workflow.",
  "keywords": [
    "Intlayer",
    "Localization",
    "Development",
    "Performance",
    "Developer Experience",
    "Features",
    "React",
    "Next.js",
    "JavaScript",
    "TypeScript"
  ],
  "slugs": [
    "doc",
    "releases",
    "v6"
  ],
  "docKey": "./docs/en/releases/v6.md",
  "githubUrl": "https://github.com/aymericzip/intlayer/blob/main/docs/docs/en/releases/v6.md",
  "relativeUrl": "/doc/releases/v6",
  "url": "https://intlayer.org/doc/releases/v6"
}