{
  "id": "./docs/en/roadmap.md",
  "content": "---\ncreatedAt: 2025-03-01\nupdatedAt: 2025-06-29\ntitle: Roadmap\ndescription: Discover the roadmap of Intlayer. See all the features that Intlayer implemented, and is planning to implement.\nkeywords:\n  - Roadmap\n  - Intlayer\n  - Internationalization\n  - CMS\n  - Content Management System\n  - Visual Editor\nslugs:\n  - doc\n  - roadmap\nhistory:\n  - version: 5.5.10\n    date: 2025-06-30\n    changes: Add Preact and Nuxt support, MCP Server, update CLI\n  - version: 5.5.11\n    date: 2025-06-29\n    changes: Add `docs` commands\n  - version: 5.5.10\n    date: 2025-06-29\n    changes: Init history\n---\n\n# Intlayer: Feature Overview & Roadmap\n\nIntlayer is a content management and internationalization solution designed to streamline how you declare, manage, and update content across your applications. It offers powerful features such as centralized or distributed content declaration, extensive internationalization options, Markdown support, conditional rendering, TypeScript/JavaScript/JSON integration, and more. Below is a comprehensive overview of what Intlayer currently provides, followed by upcoming roadmap features.\n\n---\n\n## Table of Contents\n\n<TOC/>\n\n---\n\n## Current Features\n\n### 1. Content Declaration\n\n#### Centralized or Distributed\n\n- **Centralized**: Declare all your content in a single, large file at the base of your application, similar to i18next, so you can manage everything in one place.\n- **Distributed**: Alternatively, split your content into separate files at the component or feature level for better maintainability. This keeps your content close to the relevant code (components, tests, Storybook, etc.). Removing a component ensures any associated content is also removed, preventing leftover data from cluttering your codebase.\n\n> Resources:\n>\n> - [Content Declaration](https://github.com/aymericzip/intlayer/blob/main/docs/docs/en/dictionary/content_file.md)\n\n### 2. Internationalization\n\n- Support for **230 languages and locales** (including regional variants like French (France), English (Canada), English (UK), Portuguese (Portugal), etc.).\n- Easily manage translations for all these locales from one place.\n\n> Resources:\n>\n> - [Internationalization](https://github.com/aymericzip/intlayer/blob/main/docs/docs/en/dictionary/translation.md)\n\n### 3. Markdown Support\n\n- Declare content using **Markdown**, allowing you to automatically format text with paragraphs, headings, links, and more.\n- Ideal for blog posts, articles, documentation pages, or any scenario where rich text formatting is needed.\n\n> Resources:\n>\n> - [Markdown](https://github.com/aymericzip/intlayer/blob/main/docs/docs/en/dictionary/markdown.md)\n\n### 4. External file support\n\n- Import content from external files as text format, such as TXT, HTML, JSON, YAML, or CSV.\n- Use the `file` function in Intlayer to embed external file content into a dictionary, ensuring seamless integration with the Intlayer Visual Editor and CMS.\n- Supports dynamic content updates, meaning that when the source file is modified, the content updates automatically within Intlayer.\n- Enables multilingual content management by linking language-specific Markdown files dynamically.\n\n> Resources:\n>\n> - [File Content Embedding](https://github.com/aymericzip/intlayer/blob/main/docs/docs/en/dictionary/file.md)\n\n### 5. Dynamic Content & Function Fetching\n\nIntlayer provides various methods to insert and manage dynamic content, ensuring flexibility and adaptability in content delivery. This includes functions for dynamic content insertion, conditional rendering, enumeration, nesting, and function fetching.\n\n1. Dynamic Content Insertion\n\n   Use the insert function to define content with placeholders ({{name}}, {{age}}, etc.).\n\n   Enables template-like content that adapts based on user input, API responses, or other dynamic data sources.\n\n   Works seamlessly with TypeScript, ESM, CommonJS, and JSON configurations.\n\n   Easily integrates with React Intlayer and Next Intlayer using useIntlayer.\n\n2. Conditional Rendering\n\n   Define content that adapts based on user-specific conditions, such as language or authentication status.\n\n   Tailor personalized experiences without duplicating content across multiple files.\n\n3. Enumeration & Pluralization\n\n   Use the enu function to define content variations based on numeric values, ranges, or custom keys.\n\n   Ensures automatic selection of the correct phrase based on a given value.\n\n   Supports ordering rules, ensuring predictable behavior.\n\n4. Nesting & Sub-Content Referencing\n\n   Use the nest function to reference and reuse content from another dictionary, reducing duplication.\n\n   Supports structured and hierarchical content management for better maintainability.\n\n5. Function Fetching\n\n   Intlayer allows content to be declared as functions, enabling both synchronous and asynchronous content retrieval.\n\n   Synchronous Functions: Content is generated dynamically at build time.\n\n   Asynchronous Functions: Fetch data from external sources (e.g., APIs, databases) dynamically.\n\n   Integration: Works with TypeScript, ESM, and CommonJS but is not supported in JSON or remote content files.\n\n### 6. Content Declaration Formats\n\nIntlayer supports **TypeScript** (also JavaScript) and **JSON** for declaring content.\n\n- **TypeScript**:\n  - Ensures your content structure is correct and that no translations are missing.\n  - Offers strict or more flexible validation modes.\n  - Allows dynamic data fetching from variables, functions, or external APIs.\n\n- **JSON**:\n  - Makes it easy to integrate with external tools (like visual editors) due to its standardized format.\n\n  > Resources:\n  >\n  > - [Content Declaration Formats](https://github.com/aymericzip/intlayer/blob/main/docs/docs/en/dictionary/content_file.md)\n\n### 7. Purging, bundle optimization and dynamic imports\n\n- Intlayer integrates `Babel` and `SWC` plugins to optimize your bundle and improve performance. It replace imports, to allows importing only the dictionaries that are used into the bundle.\n- By activating the option, Intlayer also allows to import dynamically the dictionary content for the current locale only.\n\n> Resources:\n>\n> - [Build Configuration](https://intlayer.org/doc/concept/configuration#build-configuration)\n\n---\n\n## Integration with Frameworks & Environments\n\n### 1. Next.js\n\n#### a. Server and Client Components\n\n- Provides a **unified content management approach** for both server and client components.\n- Offers a built-in context for server components, simplifying implementation compared to other solutions.\n\n#### b. Metadata, Sitemaps, and robots.txt\n\n- Fetch and inject content dynamically to generate metadata, sitemaps, or `robots.txt` files.\n\n#### c. Middleware\n\n- Add a middleware to **redirect users** to content based on their preferred language.\n\n#### d. Turbopack and Webpack Compatibility\n\n- Fully compatible with the new Next.js Turbopack as well as traditional Webpack.\n\n> Resources:\n>\n> - [Next.js](https://github.com/aymericzip/intlayer/blob/main/docs/docs/en/intlayer_with_nextjs_15.md)\n\n### 2. Vite\n\n- Similar to Next.js, you can integrate Intlayer with Vite and use a **middleware** to redirect users to content based on their preferred language.\n\n> Resources:\n>\n> - [Vite](https://github.com/aymericzip/intlayer/blob/main/docs/docs/en/intlayer_with_vite+react.md)\n\n### 3. Express\n\n- Manage content and internationalize backend services built on Express.\n- Personalize emails, error messages, push notifications, and more with localized text.\n\n> Resources:\n>\n> - [Express](https://github.com/aymericzip/intlayer/blob/main/docs/docs/en/intlayer_with_express.md)\n\n### 4. React Native\n\n- Integrate Intlayer with React Native to manage content and internationalize your mobile applications.\n- Supports both iOS and Android platforms.\n\n> Resources:\n>\n> - [React Native](https://github.com/aymericzip/intlayer/blob/main/docs/docs/en/intlayer_with_react_native.md)\n\n### 5. Lynx\n\n- Integrate Intlayer with Lynx to manage content and internationalize your mobile applications.\n- Supports both iOS and Android platforms.\n\n> Resources:\n>\n> - [Lynx](https://github.com/aymericzip/intlayer/blob/main/docs/docs/en/intlayer_with_lynx.md)\n\n### 6. Vue\n\n- Integrate Intlayer with Vue to manage content and internationalize your Vite / Vue.js applications.\n\n> Resources:\n>\n> - [Vue](https://github.com/aymericzip/intlayer/blob/main/docs/docs/en/intlayer_with_vue.md)\n\n### 7. Nuxt\n\n- Integrate Intlayer with Nuxt to manage content and internationalize your Nuxt / Vue.js applications.\n- Supports both server and client components.\n- Integrates routing and middleware to redirect users to content based on their preferred language.\n\n> Resources:\n>\n> - [Nuxt](https://github.com/aymericzip/intlayer/blob/main/docs/docs/en/intlayer_with_nuxt.md)\n\n### 8. Preact\n\n- Integrate Intlayer with Preact to manage content and internationalize your Preact applications.\n\n> Resources:\n>\n> - [Preact](https://github.com/aymericzip/intlayer/blob/main/docs/docs/en/intlayer_with_preact.md)\n\n---\n\n## Visual Editors and CMS\n\n### 1. Local Visual Editor\n\n- A **free, local visual editor** that lets you edit your application content by directly selecting elements on the page.\n- Integrates AI features to help:\n  - Generate or fix translations\n  - Check syntax and spelling\n  - Suggest improvements\n- Can be hosted locally or deployed on a remote server.\n\n> Resources:\n>\n> - [Visual Editor](https://github.com/aymericzip/intlayer/blob/main/docs/docs/en/intlayer_visual_editor.md)\n\n### 2. Intlayer CMS (Remote)\n\n- A **hosted CMS** solution that allows you to manage application content online, without touching your codebase.\n- Provides AI-assisted features for declaring content, managing translations, and fixing syntax or spelling errors.\n- Interact with your content via your live application interface.\n\n> Resources:\n>\n> - [CMS](https://github.com/aymericzip/intlayer/blob/main/docs/docs/en/intlayer_CMS.md)\n\n---\n\n## IDE Extensions\n\n- Extensions for major IDEs to provide a **graphical interface** for managing local and remote translations.\n- Features could include auto-generating content declaration files for components, direct integration with the Intlayer CMS, and real-time validation.\n\n---\n\n## MCP Server\n\n- A **MCP server** that allows you to manage your content and translations using an integrated tool in your IDE.\n\n---\n\n## Intlayer CLI\n\n- **Translation and file generation**: Run audits on your content files to generate missing translations and review inconsistencies.\n- **Remote Interaction**: Push your local content to the remote CMS or pull remote content to integrate into your local application.\n- **Doc translation and review**: Translate and review your documentation / files etc.\n\n> Resources:\n>\n> - [CLI](https://github.com/aymericzip/intlayer/blob/main/docs/docs/en/cli/index.md)\n\n---\n\n## Environments\n\n- Use **environment variables** to configure Intlayer differently across production, testing, and local environments.\n- Define which visual editor or remote CMS project to target depending on your environment.\n\n---\n\n## Hot Content Updates\n\n- When using remote dictionaries and the Intlayer CMS, you can **update your applicationâ€™s content on the fly**, without needing to redeploy.\n\n> Resources:\n>\n> - [CMS](https://github.com/aymericzip/intlayer/blob/main/docs/docs/en/intlayer_CMS.md)\n\n---\n\n## Upcoming Features\n\n### 1. A/B Testing & Personalization\n\n- **Multivariate Testing**: Test different versions of a given piece of content to see which performs best (e.g., higher click rate).\n- **Data-Driven Personalization**: Display different content based on user demographics (gender, age, location, etc.), or other behavior patterns.\n- **Automated Iteration**: Allow AI to automatically test multiple versions and either pick the top performer or recommend options for admin approval.\n\n### 2. Versioning\n\n- Restore previous versions of your content with **content versioning**.\n- Track changes over time and revert to earlier states if needed.\n\n### 3. Automatic Translation\n\n- For remote CMS users, **one-click translation generation** for any supported language.\n- The system would generate translations in the background and then prompt you for validation or edits.\n\n### 4. SEO Enhancements\n\n- Tools to **analyze keywords**, user search intent, and emerging trends.\n- Suggest improved content for better rankings, and track long-term performance.\n\n### 5. Compatibility with More Frameworks\n\n- Efforts are underway to support **Solid, Svelte, Angular**, and more.\n- Aim to make Intlayer compatible with **any JavaScript-powered application**.\n\n---\n\n## Conclusion\n\nIntlayer aims to be a one-stop solution for content management and internationalization. It focuses on flexibility (centralized or distributed files), broad language support, easy integration with modern frameworks and bundlers, and powerful AI-driven features. As new capabilities, such as A/B testing, versioning, and automated translations, become available, Intlayer will continue to simplify content workflows and elevate user experiences across different platforms.\n\nStay tuned for upcoming releases, and feel free to explore the existing features to see how Intlayer can help centralize and optimize your content management processes today!\n\n---\n",
  "createdAt": "2025-03-01",
  "updatedAt": "2025-06-29",
  "title": "Roadmap",
  "description": "Discover the roadmap of Intlayer. See all the features that Intlayer implemented, and is planning to implement.",
  "keywords": [
    "Roadmap",
    "Intlayer",
    "Internationalization",
    "CMS",
    "Content Management System",
    "Visual Editor"
  ],
  "slugs": [
    "doc",
    "roadmap"
  ],
  "history": [
    {
      "version": "5.5.10",
      "date": "2025-06-30",
      "changes": "Add Preact and Nuxt support, MCP Server, update CLI"
    },
    {
      "version": "5.5.11",
      "date": "2025-06-29",
      "changes": "Add `docs` commands"
    },
    {
      "version": "5.5.10",
      "date": "2025-06-29",
      "changes": "Init history"
    }
  ],
  "docKey": "./docs/en/roadmap.md",
  "githubUrl": "https://github.com/aymericzip/intlayer/blob/main/docs/docs/en/roadmap.md",
  "relativeUrl": "/doc/roadmap",
  "url": "https://intlayer.org/doc/roadmap"
}